Workbook
Name AnalysisDate: Dashboard!$P$3
Name BPJSKesCap: 'Company Info'!$C$44
Name CashBS: 'Balance Sheet'!$E$14
Name CFF: 'Cash Flow'!$E$36
Name CFI: 'Cash Flow'!$E$30
Name CFO: 'Cash Flow'!$E$25
Name CITRate: 'Company Info'!$C$40
Name CompanyName: 'Company Info'!$C$6
Name CompDate: 'Company Info'!$C$33
Name CompLabel: 'Company Info'!$C$49
Name ControlStatus: Controls!$E$28
Name CurLabel: 'Company Info'!$C$48
Name CutOff: 'Company Info'!$C$30
Name Fac31E: 'Company Info'!$C$41
Name Fac31ELimit: 'Company Info'!$C$42
Name FinanceCosts: 'Income Statement'!$E$21
Name FYear: 'Company Info'!$C$29
Name GrossProfit: 'Income Statement'!$E$14
Name Industry: 'Company Info'!$C$7
Name IP_CostLabel: 'Industry Profile'!$C$9
Name IP_Desc: 'Industry Profile'!$C$7
Name IP_InvLabel: 'Industry Profile'!$C$10
Name IP_Policy: 'Industry Profile'!$C$28
Name IP_RevLabel: 'Industry Profile'!$C$8
Name IP_Unit: 'Industry Profile'!$C$11
Name JPCap: 'Company Info'!$C$45
Name NetIncome: 'Income Statement'!$E$25
Name OpProfit: 'Income Statement'!$E$18
Name PBT: 'Income Statement'!$E$23
Name PEnd: 'Company Info'!$C$32
Name PeriodTitle: 'Company Info'!$C$47
Name PPh25Inst: 'Company Info'!$C$43
Name PStart: 'Company Info'!$C$31
Name R_JHTEe: Payroll!$AE$12
Name R_JHTEr: Payroll!$AE$11
Name R_JKK: Payroll!$AE$9
Name R_JKM: Payroll!$AE$10
Name R_JPEe: Payroll!$AE$14
Name R_JPEr: Payroll!$AE$13
Name R_KesEe: Payroll!$AE$8
Name R_KesEr: Payroll!$AE$7
Name Revenue: 'Income Statement'!$E$12
Name TerA_L: Payroll!$AD$18:$AD$61
Name TerA_R: Payroll!$AE$18:$AE$61
Name TerB_L: Payroll!$AF$18:$AF$57
Name TerB_R: Payroll!$AG$18:$AG$57
Name TerC_L: Payroll!$AH$18:$AH$58
Name TerC_R: Payroll!$AI$18:$AI$58
Name TotalAssets: 'Balance Sheet'!$E$26
Name TotalEquity: 'Balance Sheet'!$E$48
Name TotalLiab: 'Balance Sheet'!$E$42
Name VATEff: 'Company Info'!$C$39
Name VATFactor: 'Company Info'!$C$38
Name VATRate: 'Company Info'!$C$37
Name WHTRates: 'Company Info'!$C$56:$C$59
Name WHTTypes: 'Company Info'!$B$56:$B$59

Sheet Dashboard
B2: =UPPER(CompanyName) -> PT NUSANTARA SEJAHTERA ABADI | N2: ="Controls: "&ControlStatus -> Controls: ✔ ALL CONTROLS OK
B3: ="Financial Dashboard • "&Industry&" — "&IP_Desc&" • "&PeriodTitle -> Financial Dashboard • Retail — Retail of fashion, lifestyle & consumer electronics • For the Period from 1 January to 31 October 2026 | N3: Analysis Date ▸ | P3: 46303
B5: ☰ MAIN MENU — click a module to open it
B6: ⚙ Company Info | D6: 🏭 Industry Profile | F6: 📒 Chart of Accounts | H6: 👥 Customers | J6: 🚚 Vendors | L6: 👔 Employees | N6: 📦 Products | P6: 🧾 Sales
B8: 🛒 Purchases | D8: 💰 Payroll | F8: 🏦 Bank Statement | H8: ✍ General Journal | J8: 🏗 Fixed Assets | L8: 📅 Prepaid Schedule | N8: 📖 General Ledger | P8: ⚖ Trial Balance
B10: 📈 Income Statement | D10: 🏛 Balance Sheet | F10: 🔄 Changes in Equity | H10: 💧 Cash Flow | J10: 📝 Notes to FS | L10: 🧮 Tax Reconciliation | N10: 🔗 Bank Reconciliation | P10: ✅ Controls
B12: 🧾 Sales Invoice | D12: 📊 Ratios | F12: 📆 Monthly P&L | H12: 🗂 Dashboard Data
B13: ■ Setup ■ Master Data ■ Transactions ■ Schedules ■ Reports ■ Tax & Reconciliation ■ Tools
B15: SYSTEM STATUS
B16: CONTROL CHECKS | F16: TAX RECONCILIATION | J16: BANK RECONCILIATION | N16: BANK ITEMS TO BOOK
B17: =ControlStatus -> ✔ ALL CONTROLS OK | F17: ='Tax Reconciliation'!E91 -> ✔ ALL TAXES RECONCILED | J17: =IF(AND(LEFT(Controls!E21,1)="✔",LEFT(Controls!E22,1)="✔"),"✔ BCA & MANDIRI RECONCILED","✖ UNEXPLAINED DIFFERENCE") -> ✔ BCA & MANDIRI RECONCILED | N17: =Controls!E26 -> ⚠ 6 item(s) to book
B18: ="20 integrity checks – see Controls" -> 20 integrity checks – see Controls | F18: ="PPN • PPh 21 • Unifikasi • PPh 25 • PPh Badan" -> PPN • PPh 21 • Unifikasi • PPh 25 • PPh Badan | J18: ="Books vs bank statement at "&CurLabel -> Books vs bank statement at 31 October 2026 | N18: ="Interest / fees on statement not yet in GJ" -> Interest / fees on statement not yet in GJ
B20: ="FINANCIAL PERFORMANCE — YTD "&'Company Info'!C50&" "&FYear -> FINANCIAL PERFORMANCE — YTD October 2026
B21: REVENUE | F21: GROSS PROFIT | J21: NET PROFIT | N21: CASH & EQUIVALENTS
B22: =Revenue -> 11350565000 | F22: =GrossProfit -> 4518180000 | J22: =NetIncome -> 922723240 | N22: =CashBS -> 1563245568
B23: ="Avg Rp "&FIXED(Revenue/CutOff/1000000,1)&" m / month" -> Avg Rp 1.135,1 m / month | F23: ="Gross margin "&FIXED(Ratios!D13*100,1)&"%" -> Gross margin 39,8% | J23: ="Net margin "&FIXED(Ratios!D16*100,1)&"% • ROE "&FIXED(Ratios!D18*100,1)&"% (ann.)" -> Net margin 8,1% • ROE 26,6% (ann.) | N23: ="vs opening "&IF(CashBS>='Balance Sheet'!F14,"+","")&FIXED((CashBS/'Balance Sheet'!F14-1)*100,1)&"%" -> vs opening -29,7%
B25: TOTAL ASSETS | F25: CURRENT RATIO | J25: DEBT TO EQUITY | N25: CASH CONVERSION CYCLE
B26: =TotalAssets -> 7134292003 | F26: =Ratios!D9 -> 3.3235778 | J26: =Ratios!D20 -> 0.59510387 | N26: =Ratios!D28 -> 33.061539
B27: ="Equity Rp "&FIXED(TotalEquity/1000000000,2)&" bn • Liabilities Rp "&FIXED(TotalLiab/1000000000,2)&" bn" -> Equity Rp 4,47 bn • Liabilities Rp 2,66 bn | F27: =Ratios!G9&" • Quick "&FIXED(Ratios!D10,2)&"x" -> ✔ Healthy • Quick 2,41x | J27: =Ratios!G20&" • ICR "&FIXED(Ratios!D22,1)&"x" -> ✔ Healthy • ICR 10,3x | N27: ="DSO "&FIXED(Ratios!D25,0)&" • DIO "&FIXED(Ratios!D26,0)&" • DPO "&FIXED(Ratios!D27,0) -> DSO 25 • DIO 44 • DPO 36
B29: ="DAILY SNAPSHOT — "&TEXT(AnalysisDate,"[$-409]dddd, d mmmm yyyy") -> DAILY SNAPSHOT — Thursday, 8 October 2026
B30: SALES TODAY | F30: INVOICES TODAY | J30: TOP PRODUCT TODAY | N30: MONTH-TO-DATE SALES
B31: ='Dashboard Data'!C23 -> 48480000 | F31: ='Dashboard Data'!C26 -> 9 | J31: ='Dashboard Data'!C28 -> Casual Shirt | N31: ='Dashboard Data'!C30 -> 352390000
B32: =IF('Dashboard Data'!C25>=0,"▲ ","▼ ")&FIXED(ABS('Dashboard Data'!C25)*100,1)&"% vs yesterday (Rp "&FIXED('Dashboard Data'!C24/1000000,1)&" m)" -> ▲ 26,4% vs yesterday (Rp 38,3 m) | F32: ="Avg Rp "&FIXED('Dashboard Data'!C27/1000000,2)&" m / invoice • "&'Dashboard Data'!C35&" units" -> Avg Rp 5,39 m / invoice • 394 units | J32: ="Rp "&FIXED('Dashboard Data'!C29/1000000,1)&" m sold today" -> Rp 15,2 m sold today | N32: =IF('Dashboard Data'!C32>=0,"▲ ","▼ ")&FIXED(ABS('Dashboard Data'!C32)*100,1)&"% vs same period last month" -> ▲ 24,0% vs same period last month
B34: TRENDS, PRODUCTS & COST STRUCTURE
B68: TOP PRODUCTS, TODAY'S SALES BY PRODUCT, FINANCIAL HEALTH & TOP CUSTOMERS
B69: 🏆 TOP 5 PRODUCTS / SERVICES (YTD) | J69: ="📅 SALES BY PRODUCT ON "&TEXT(AnalysisDate,"[$-409]dd mmm yyyy") -> 📅 SALES BY PRODUCT ON 08 Oct 2026
B70: # | C70: Product / Service | F70: Sales | H70: Share | I70: Gross Profit | J70: Product / Service | N70: Qty | O70: Sales | Q70: Share
B71: ='Dashboard Data'!P21 -> 1 | C71: ='Dashboard Data'!Q21 -> Chino Pants | F71: ='Dashboard Data'!R21*1000000 -> 1471350000 | H71: ='Dashboard Data'!S21 -> 0.12962791 | I71: ='Dashboard Data'!T21 -> 608158000 | J71: {=INDEX(_xlfn.SORTBY('Dashboard Data'!$Q$7:$Q$16,'Dashboard Data'!$U$7:$U$16,-1),1)} -> Casual Shirt | N71: =_xlfn.XLOOKUP(J71,'Dashboard Data'!$Q$7:$Q$16,'Dashboard Data'!$V$7:$V$16,0) -> 127 | O71: =_xlfn.XLOOKUP(J71,'Dashboard Data'!$Q$7:$Q$16,'Dashboard Data'!$U$7:$U$16,0) -> 15240000 | Q71: =IFERROR(O71/'Dashboard Data'!$U$17,0) -> 0.31435644
B72: ='Dashboard Data'!P22 -> 2 | C72: ='Dashboard Data'!Q22 -> Casual Shirt | F72: ='Dashboard Data'!R22*1000000 -> 1400280000 | H72: ='Dashboard Data'!S22 -> 0.12336655 | I72: ='Dashboard Data'!T22 -> 560112000 | J72: {=INDEX(_xlfn.SORTBY('Dashboard Data'!$Q$7:$Q$16,'Dashboard Data'!$U$7:$U$16,-1),2)} -> Casual Shorts | N72: =_xlfn.XLOOKUP(J72,'Dashboard Data'!$Q$7:$Q$16,'Dashboard Data'!$V$7:$V$16,0) -> 124 | O72: =_xlfn.XLOOKUP(J72,'Dashboard Data'!$Q$7:$Q$16,'Dashboard Data'!$U$7:$U$16,0) -> 10540000 | Q72: =IFERROR(O72/'Dashboard Data'!$U$17,0) -> 0.21740924
B73: ='Dashboard Data'!P23 -> 3 | C73: ='Dashboard Data'!Q23 -> Wireless Earbuds Pro | F73: ='Dashboard Data'!R23*1000000 -> 1393750000 | H73: ='Dashboard Data'!S23 -> 0.12279124 | I73: ='Dashboard Data'!T23 -> 479450000 | J73: {=INDEX(_xlfn.SORTBY('Dashboard Data'!$Q$7:$Q$16,'Dashboard Data'!$U$7:$U$16,-1),3)} -> Sneakers | N73: =_xlfn.XLOOKUP(J73,'Dashboard Data'!$Q$7:$Q$16,'Dashboard Data'!$V$7:$V$16,0) -> 24 | O73: =_xlfn.XLOOKUP(J73,'Dashboard Data'!$Q$7:$Q$16,'Dashboard Data'!$U$7:$U$16,0) -> 6000000 | Q73: =IFERROR(O73/'Dashboard Data'!$U$17,0) -> 0.12376238
B74: ='Dashboard Data'!P24 -> 4 | C74: ='Dashboard Data'!Q24 -> Backpack | F74: ='Dashboard Data'!R24*1000000 -> 1265500000 | H74: ='Dashboard Data'!S24 -> 0.11149225 | I74: ='Dashboard Data'!T24 -> 531510000 | J74: {=INDEX(_xlfn.SORTBY('Dashboard Data'!$Q$7:$Q$16,'Dashboard Data'!$U$7:$U$16,-1),4)} -> Bomber Jacket | N74: =_xlfn.XLOOKUP(J74,'Dashboard Data'!$Q$7:$Q$16,'Dashboard Data'!$V$7:$V$16,0) -> 16 | O74: =_xlfn.XLOOKUP(J74,'Dashboard Data'!$Q$7:$Q$16,'Dashboard Data'!$U$7:$U$16,0) -> 5600000 | Q74: =IFERROR(O74/'Dashboard Data'!$U$17,0) -> 0.11551155
B75: ='Dashboard Data'!P25 -> 5 | C75: ='Dashboard Data'!Q25 -> Casual Shorts | F75: ='Dashboard Data'!R25*1000000 -> 1166030000 | H75: ='Dashboard Data'!S25 -> 0.10272881 | I75: ='Dashboard Data'!T25 -> 480130000 | J75: {=INDEX(_xlfn.SORTBY('Dashboard Data'!$Q$7:$Q$16,'Dashboard Data'!$U$7:$U$16,-1),5)} -> Premium Basic T-shirt | N75: =_xlfn.XLOOKUP(J75,'Dashboard Data'!$Q$7:$Q$16,'Dashboard Data'!$V$7:$V$16,0) -> 80 | O75: =_xlfn.XLOOKUP(J75,'Dashboard Data'!$Q$7:$Q$16,'Dashboard Data'!$U$7:$U$16,0) -> 5200000 | Q75: =IFERROR(O75/'Dashboard Data'!$U$17,0) -> 0.10726073
J76: {=INDEX(_xlfn.SORTBY('Dashboard Data'!$Q$7:$Q$16,'Dashboard Data'!$U$7:$U$16,-1),6)} -> Backpack | N76: =_xlfn.XLOOKUP(J76,'Dashboard Data'!$Q$7:$Q$16,'Dashboard Data'!$V$7:$V$16,0) -> 10 | O76: =_xlfn.XLOOKUP(J76,'Dashboard Data'!$Q$7:$Q$16,'Dashboard Data'!$U$7:$U$16,0) -> 5000000 | Q76: =IFERROR(O76/'Dashboard Data'!$U$17,0) -> 0.10313531
B77: 🩺 FINANCIAL HEALTH | J77: {=INDEX(_xlfn.SORTBY('Dashboard Data'!$Q$7:$Q$16,'Dashboard Data'!$U$7:$U$16,-1),7)} -> Socks & Accessories | N77: =_xlfn.XLOOKUP(J77,'Dashboard Data'!$Q$7:$Q$16,'Dashboard Data'!$V$7:$V$16,0) -> 10 | O77: =_xlfn.XLOOKUP(J77,'Dashboard Data'!$Q$7:$Q$16,'Dashboard Data'!$U$7:$U$16,0) -> 450000 | Q77: =IFERROR(O77/'Dashboard Data'!$U$17,0) -> 0.0092821782
B78: Ratio | F78: Value | H78: Status | J78: {=INDEX(_xlfn.SORTBY('Dashboard Data'!$Q$7:$Q$16,'Dashboard Data'!$U$7:$U$16,-1),8)} -> Chino Pants | N78: =_xlfn.XLOOKUP(J78,'Dashboard Data'!$Q$7:$Q$16,'Dashboard Data'!$V$7:$V$16,0) -> 3 | O78: =_xlfn.XLOOKUP(J78,'Dashboard Data'!$Q$7:$Q$16,'Dashboard Data'!$U$7:$U$16,0) -> 450000 | Q78: =IFERROR(O78/'Dashboard Data'!$U$17,0) -> 0.0092821782
B79: Current ratio | F79: =Ratios!D9 -> 3.3235778 | H79: =Ratios!G9 -> ✔ Healthy | J79: {=INDEX(_xlfn.SORTBY('Dashboard Data'!$Q$7:$Q$16,'Dashboard Data'!$U$7:$U$16,-1),9)} -> Smartwatch | N79: =_xlfn.XLOOKUP(J79,'Dashboard Data'!$Q$7:$Q$16,'Dashboard Data'!$V$7:$V$16,0) -> 0 | O79: =_xlfn.XLOOKUP(J79,'Dashboard Data'!$Q$7:$Q$16,'Dashboard Data'!$U$7:$U$16,0) -> 0 | Q79: =IFERROR(O79/'Dashboard Data'!$U$17,0) -> 0
B80: Quick ratio | F80: =Ratios!D10 -> 2.4115836 | H80: =Ratios!G10 -> ✔ Healthy | J80: {=INDEX(_xlfn.SORTBY('Dashboard Data'!$Q$7:$Q$16,'Dashboard Data'!$U$7:$U$16,-1),10)} -> Wireless Earbuds Pro | N80: =_xlfn.XLOOKUP(J80,'Dashboard Data'!$Q$7:$Q$16,'Dashboard Data'!$V$7:$V$16,0) -> 0 | O80: =_xlfn.XLOOKUP(J80,'Dashboard Data'!$Q$7:$Q$16,'Dashboard Data'!$U$7:$U$16,0) -> 0 | Q80: =IFERROR(O80/'Dashboard Data'!$U$17,0) -> 0
B81: Net profit margin | F81: =Ratios!D16 -> 0.081293155 | H81: =Ratios!G16 -> ✔ Healthy | J81: Total today | N81: ='Dashboard Data'!V17 -> 394 | O81: ='Dashboard Data'!U17 -> 48480000
B82: Return on assets (ann.) | F82: =Ratios!D17 -> 0.15911664 | H82: =Ratios!G17 -> ✔ Healthy
B83: Return on equity (ann.) | F83: =Ratios!D18 -> 0.26608973 | H83: =Ratios!G18 -> ✔ Healthy | J83: 🤝 TOP 5 CUSTOMERS (YTD, excl. walk-in)
B84: Debt to equity | F84: =Ratios!D20 -> 0.59510387 | H84: =Ratios!G20 -> ✔ Healthy | J84: # | K84: Customer | O84: Sales | Q84: Share
B85: Interest coverage | F85: =Ratios!D22 -> 10.316882 | H85: =Ratios!G22 -> ✔ Healthy | J85: 1 | K85: ='Dashboard Data'!X28 -> PT Graha Nusa Persada | O85: ='Dashboard Data'!Y28 -> 927360000 | Q85: =IFERROR(O85/Revenue,0) -> 0.08170166
J86: 2 | K86: ='Dashboard Data'!X29 -> PT Bintang Timur Sejahtera | O86: ='Dashboard Data'!Y29 -> 844240000 | Q86: =IFERROR(O86/Revenue,0) -> 0.074378676
J87: 3 | K87: ='Dashboard Data'!X30 -> PT Cahaya Abadi Makmur | O87: ='Dashboard Data'!Y30 -> 827360000 | Q87: =IFERROR(O87/Revenue,0) -> 0.072891526
J88: 4 | K88: ='Dashboard Data'!X31 -> PT Delta Inti Selaras | O88: ='Dashboard Data'!Y31 -> 821240000 | Q88: =IFERROR(O88/Revenue,0) -> 0.072352345
J89: 5 | K89: ='Dashboard Data'!X32 -> PT Mega Prima Distribusi | O89: ='Dashboard Data'!Y32 -> 776080000 | Q89: =IFERROR(O89/Revenue,0) -> 0.068373689
B91: CASH, PAYMENT METHODS & TRANSACTION VOLUME
B109: Dummy data for demonstration • Replace Sales / Purchases / Payroll / Bank Statement with real data – all reports update automatically

Sheet Company Info
B2: 🏠 HOME | D2: ◀ PREV | F2: NEXT ▶ | I2: ☰ MENU | L2: Journal | O2: Trial Bal. | R2: Income St. | U2: Balance Sh. | X2: Tax Recon | AA2: Bank Recon | AD2: Controls
B4: COMPANY INFORMATION & SETTINGS
B5: IDENTITY
B6: Company Name | C6: PT Nusantara Sejahtera Abadi | D6: Appears on all reports
B7: Business Type | C7: Retail | D7: ▼ Select industry
B8: Business Description | C8: =IP_Desc -> Retail of fashion, lifestyle & consumer electronics | D8: Auto from Industry Profile
B9: Tax ID (NPWP) | C9: 0123456789012000 | D9: 16-digit NPWP
B10: Business ID (NIB) | C10: 9120001234567
B11: VAT Status | C11: PKP (VAT-registered)
B12: Address | C12: Jl. Jend. Sudirman Kav. 52-53, Jakarta Selatan 12190
B13: City | C13: Jakarta
B14: Phone | C14: +62 21 5150 8888
B15: Email | C15: finance@nusantarasejahtera.co.id
B16: Date of Establishment | C16: 43174
B17: Deed of Establishment | C17: Deed No. 12 dated 15 March 2018, Notary Andi Wijaya, S.H., M.Kn.
B18: Ministry Approval | C18: AHU-0012345.AH.01.01.Tahun 2018
B19: Number of Employees | C19: =ROWS(tblEmployees[Employee ID]) -> 15 | D19: Auto from Employees
B20: Shares Outstanding | C20: 2500000 | D20: shares
B21: Par Value per Share (IDR) | C21: 1000
B22: MANAGEMENT
B23: President Commissioner | C23: Hendra Gunawan
B24: President Director | C24: Budi Santoso
B25: Finance Director | C25: Siti Rahmawati
B26: Accounting Manager | C26: Dewi Lestari
B28: REPORTING PERIOD
B29: Fiscal Year | C29: 2026
B30: Cut-off Month (1-12) | C30: 10 | D30: ▼ All reports run YTD to this month
B31: Period Start | C31: =DATE(C29,1,1) -> 46023
B32: Period End | C32: =EOMONTH(DATE(C29,C30,1),0) -> 46326 | D32: Auto
B33: Comparative Date | C33: =DATE(C29-1,12,31) -> 46022 | D33: Opening balances date
B34: Reporting Currency | C34: Indonesian Rupiah (IDR)
B35: Presentation Unit | C35: Full Rupiah
B36: TAX SETTINGS
B37: VAT Rate (PPN) | C37: 0.12 | D37: UU HPP; from 1 Jan 2025
B38: VAT Base Factor (DPP Nilai Lain) | C38: =11/12 -> 0.91666667 | D38: PMK 131/2024 – non-luxury goods
B39: Effective VAT Rate | C39: =C37*C38 -> 0.11
B40: Corporate Income Tax Rate | C40: 0.22 | D40: Art. 17 UU PPh
B41: Apply Art. 31E Facility (Yes/No) | C41: Yes | D41: ▼ 50% rate cut on revenue ≤ IDR 4.8bn portion
B42: Art. 31E Revenue Threshold | C42: 4800000000
B43: Monthly PPh 25 Installment | C43: 20000000 | D43: Per prior-year SPT
B44: BPJS Health Wage Cap | C44: 12000000 | D44: Monthly
B45: BPJS Pension (JP) Wage Cap | C45: 10547400 | D45: Update per BPJS circular
B46: REPORT LABELS (auto)
B47: Period Title | C47: {="For the Period from 1 January to "&DAY(C32)&" "&INDEX({"January","February","March","April","May","June","July","August","September","October","November","December"},MONTH(C32))&" "&YEAR(C32)} -> For the Period from 1 January to 31 October 2026
B48: Current Date Label | C48: {=DAY(C32)&" "&INDEX({"January","February","March","April","May","June","July","August","September","October","November","December"},MONTH(C32))&" "&YEAR(C32)} -> 31 October 2026
B49: Comparative Date Label | C49: {=DAY(C33)&" "&INDEX({"January","February","March","April","May","June","July","August","September","October","November","December"},MONTH(C33))&" "&YEAR(C33)} -> 31 December 2025
B50: Cut-off Month Name | C50: {=INDEX({"January","February","March","April","May","June","July","August","September","October","November","December"},C30)} -> October
B51: Independent Auditor | C51: KAP Wijaya & Partners
B52: FS Authorisation Date | C52: 46346
B54: WITHHOLDING TAX (PPh UNIFIKASI) RATES
B55: WHT Type | C55: Rate | D55: Description
B56: None | C56: 0 | D56: Not subject to withholding
B57: Art. 23 - Services | C57: 0.02 | D57: PPh 23 on services (2%)
B58: Art. 4(2) - Building Rent | C58: 0.1 | D58: Final PPh 4(2) on land/building rent (10%)
B59: Art. 23 - Rent (non-building) | C59: 0.02 | D59: PPh 23 on asset rental (2%)

Sheet Industry Profile
B2: 🏠 HOME | D2: ◀ PREV | F2: NEXT ▶ | H2: ☰ MENU | J2: Journal | L2: Trial Bal. | O2: Income St. | R2: Balance Sh. | U2: Tax Recon | X2: Bank Recon | AA2: Controls
B4: INDUSTRY PROFILE LIBRARY
B5: Edit any industry column (blue) to customise labels/products. Column C is driven by Company Info › Business Type.
B6: Attribute | C6: ▶ Selected | D6: Retail | E6: Services | F6: Manufacturing | G6: Distribution | H6: Construction | I6: Trading Company | J6: Fulfillment | K6: F&B
B7: Description | C7: =INDEX(D7:K7,MATCH(Industry,$D$6:$K$6,0)) -> Retail of fashion, lifestyle & consumer electronics | D7: Retail of fashion, lifestyle & consumer electronics | E7: Business consulting, creative & digital services | F7: Manufacturing of furniture & home products | G7: Wholesale distribution of fast-moving consumer goods | H7: Building construction & finishing contractor | I7: B2B trading of industrial supplies & equipment | J7: E-commerce fulfillment & warehousing services | K7: Restaurant, café & catering services
B8: Revenue Label | C8: =INDEX(D8:K8,MATCH(Industry,$D$6:$K$6,0)) -> Sales of goods | D8: Sales of goods | E8: Service revenue | F8: Sales of manufactured goods | G8: Sales of goods - distribution | H8: Contract revenue | I8: Trading revenue | J8: Fulfillment service revenue | K8: Food & beverage sales
B9: Cost of Revenue Label | C9: =INDEX(D9:K9,MATCH(Industry,$D$6:$K$6,0)) -> Cost of goods sold | D9: Cost of goods sold | E9: Cost of services | F9: Cost of goods manufactured & sold | G9: Cost of goods sold | H9: Contract costs | I9: Cost of goods sold | J9: Cost of services | K9: Cost of food & beverage
B10: Inventory Label | C10: =INDEX(D10:K10,MATCH(Industry,$D$6:$K$6,0)) -> Merchandise inventory | D10: Merchandise inventory | E10: Service supplies | F10: Finished goods & raw materials | G10: Merchandise inventory | H10: Construction materials | I10: Trading inventory | J10: Packaging & supplies | K10: Food & beverage inventory
B11: Unit | C11: =INDEX(D11:K11,MATCH(Industry,$D$6:$K$6,0)) -> pcs | D11: pcs | E11: session | F11: unit | G11: carton | H11: m² / m³ | I11: unit | J11: order batch | K11: portion
B12: Category 1 | C12: =INDEX(D12:K12,MATCH(Industry,$D$6:$K$6,0)) -> Accessories & Basics | D12: Accessories & Basics | E12: Digital Content | F12: Small Furniture | G12: Beverages | H12: Finishing Works | I12: Packaging Supplies | J12: Handling Services | K12: Beverages & Snacks
B13: Category 2 | C13: =INDEX(D13:K13,MATCH(Industry,$D$6:$K$6,0)) -> Apparel & Footwear | D13: Apparel & Footwear | E13: Consulting | F13: Chairs & Tables | G13: Food Staples | H13: Structural Works | I13: Industrial Parts | J13: Storage Services | K13: Main Courses
B14: Category 3 | C14: =INDEX(D14:K14,MATCH(Industry,$D$6:$K$6,0)) -> Bags & Gadgets | D14: Bags & Gadgets | E14: Projects & Retainers | F14: Large Furniture | G14: Household Goods | H14: Concrete & Heavy Works | I14: Machinery & Tools | J14: Value-added Services | K14: Packages & Catering
B15: Channel 1 | C15: =INDEX(D15:K15,MATCH(Industry,$D$6:$K$6,0)) -> In-store | D15: In-store | E15: Direct Client | F15: Distributor | G15: Modern Trade | H15: Private Projects | I15: Direct Sales | J15: Marketplace Sellers | K15: Dine-in
B16: Channel 2 | C16: =INDEX(D16:K16,MATCH(Industry,$D$6:$K$6,0)) -> Marketplace | D16: Marketplace | E16: Referral | F16: Direct B2B | G16: General Trade | H16: Government Projects | I16: Tender | J16: D2C Brands | K16: Delivery App
B17: Channel 3 | C17: =INDEX(D17:K17,MATCH(Industry,$D$6:$K$6,0)) -> Website & Social Media | D17: Website & Social Media | E17: Online Platform | F17: E-commerce | G17: B2B Online | H17: Subcontract | I17: E-procurement | J17: Corporate | K17: Catering Order
B18: Product P01 | C18: =INDEX(D18:K18,MATCH(Industry,$D$6:$K$6,0)) -> Socks & Accessories | D18: Socks & Accessories | E18: Online Consultation (30 min) | F18: Plastic Stool | G18: Mineral Water 600ml (carton) | H18: Painting Works (m²) | I18: Packing Tape (pack) | J18: Pick & Pack (10 orders) | K18: Iced Palm Sugar Coffee
... B28: Revenue Recognition Policy | C28: =INDEX(D28:K28,MATCH(Industry,$D$6:$K$6,0)) -> Revenue from the sale of goods is recognised at a point in time when control transfers to the customer, generally upon handover at the store or delivery to the courier (PSAK 115). | D28: Revenue from the sale of goods is recognised at a point in time when control transfers to the customer, generally upon handover at the store or delivery to the courier (PSAK 115). | E28: Service revenue is recognised over time as the services are rendered, or at a point in time when a discrete session/deliverable is completed (PSAK 115). | F28: Revenue is recognised at a point in time when manufactured goods are delivered and accepted by the customer (PSAK 115). | G28: Revenue is recognised when goods are delivered to the customer's warehouse and control has transferred (PSAK 115). | H28: Contract revenue is recognised over time using the input method, based on costs incurred relative to total estimated contract costs (PSAK 115). | I28: Revenue is recognised at a point in time when control passes to the buyer in accordance with the agreed delivery terms (PSAK 115). | J28: Fulfillment and storage revenue is recognised over time as the services are performed (PSAK 115). | K28: Revenue is recognised at a point in time when food and beverages are served or delivered to the customer (PSAK 115).

Sheet COA
B2: 🏠 HOME | E2: ◀ PREV | G2: NEXT ▶ | J2: ☰ MENU | M2: Journal | P2: Trial Bal. | S2: Income St. | V2: Balance Sh. | Y2: Tax Recon | AB2: Bank Recon | AE2: Controls
B4: CHART OF ACCOUNTS & OPENING BALANCES
B5: Opening balances as at Comparative Date. Black = linked to schedules (FA / Prepaid). Add new accounts at the bottom; FS Line & CF Line control where they appear.
B6: Code | C6: Account Name | D6: Class | E6: FS Line | F6: Normal | G6: Note | H6: CF Line | I6: Opening Balance | K6: OPENING BALANCE CHECK | L6: Amount
B7: 1110 | C7: Cash on Hand | D7: Asset | E7: Cash and cash equivalents | F7: D | G7: 3 | H7: Cash | I7: 25000000 | K7: Total debit-normal balances | L7: =SUMIFS(tblCOA[Opening Balance],tblCOA[Normal],"D") -> 8742000000
B8: 1120 | C8: Bank BCA - Current Account | D8: Asset | E8: Cash and cash equivalents | F8: D | G8: 3 | H8: Cash | I8: 1250000000 | K8: Total credit-normal balances | L8: =SUMIFS(tblCOA[Opening Balance],tblCOA[Normal],"C") -> 8742000000
B9: 1130 | C9: Bank Mandiri - Current Account | D9: Asset | E9: Cash and cash equivalents | F9: D | G9: 3 | H9: Cash | I9: 450000000 | K9: Difference (must be 0) | L9: =L7-L8 -> 0
B10: 1140 | C10: Time Deposit (≤ 3 months) | D10: Asset | E10: Cash and cash equivalents | F10: D | G10: 3 | H10: Cash | I10: 500000000 | K10: Status | L10: =IF(ABS(L9)<1,"✔ Balanced","✖ Not balanced") -> ✔ Balanced
B11: 1210 | C11: Trade Receivables | D11: Asset | E11: Trade receivables - net | F11: D | G11: 4 | H11: Receivables | I11: 420000000 | K11: Accounts in COA | L11: =ROWS(tblCOA[Code]) -> 68
B12: 1220 | C12: Allowance for Expected Credit Losses | D12: Asset | E12: Trade receivables - net | F12: C | G12: 4 | H12: Receivables | I12: 20000000
B13: 1230 | C13: Other Receivables | D13: Asset | E13: Other receivables | F13: D | G13: 4 | H13: Receivables | I13: 25000000
B14: 1310 | C14: =IP_InvLabel -> Merchandise inventory | D14: Asset | E14: Inventories | F14: D | G14: 5 | H14: Inventories | I14: 950000000
B15: 1410 | C15: Prepaid Rent | D15: Asset | E15: Prepaid expenses | F15: D | G15: 6 | H15: Prepaid expenses | I15: =SUMIFS(tblPrepaid[Opening Balance],tblPrepaid[Prepaid Account],tblCOA[[#This Row],[Code]]) -> 132000000
B16: 1420 | C16: Prepaid Insurance | D16: Asset | E16: Prepaid expenses | F16: D | G16: 6 | H16: Prepaid expenses | I16: =SUMIFS(tblPrepaid[Opening Balance],tblPrepaid[Prepaid Account],tblCOA[[#This Row],[Code]]) -> 25000000
B17: 1430 | C17: Prepaid Software Subscriptions | D17: Asset | E17: Prepaid expenses | F17: D | G17: 6 | H17: Prepaid expenses | I17: =SUMIFS(tblPrepaid[Opening Balance],tblPrepaid[Prepaid Account],tblCOA[[#This Row],[Code]]) -> 15000000
B18: 1510 | C18: Input VAT (PPN Masukan) | D18: Asset | E18: Prepaid taxes | F18: D | G18: 7 | H18: Prepaid taxes | I18: 0
B19: 1520 | C19: Prepaid Income Tax - Art. 25 | D19: Asset | E19: Prepaid taxes | F19: D | G19: 7 | H19: Prepaid taxes | I19: 0
B20: 1610 | C20: Land | D20: Asset | E20: Fixed assets - net | F20: D | G20: 8 | H20: Fixed assets | I20: =SUMIFS(tblFA[Cost],tblFA[Cost Account],tblCOA[[#This Row],[Code]],tblFA[Acquisition Date],"<="&CompDate) -> 1200000000
B21: 1620 | C21: Buildings | D21: Asset | E21: Fixed assets - net | F21: D | G21: 8 | H21: Fixed assets | I21: =SUMIFS(tblFA[Cost],tblFA[Cost Account],tblCOA[[#This Row],[Code]],tblFA[Acquisition Date],"<="&CompDate) -> 1800000000
B22: 1630 | C22: Vehicles | D22: Asset | E22: Fixed assets - net | F22: D | G22: 8 | H22: Fixed assets | I22: =SUMIFS(tblFA[Cost],tblFA[Cost Account],tblCOA[[#This Row],[Code]],tblFA[Acquisition Date],"<="&CompDate) -> 700000000
B23: 1640 | C23: Machinery & Equipment | D23: Asset | E23: Fixed assets - net | F23: D | G23: 8 | H23: Fixed assets | I23: =SUMIFS(tblFA[Cost],tblFA[Cost Account],tblCOA[[#This Row],[Code]],tblFA[Acquisition Date],"<="&CompDate) -> 800000000
B24: 1650 | C24: Office Furniture & Equipment | D24: Asset | E24: Fixed assets - net | F24: D | G24: 8 | H24: Fixed assets | I24: =SUMIFS(tblFA[Cost],tblFA[Cost Account],tblCOA[[#This Row],[Code]],tblFA[Acquisition Date],"<="&CompDate) -> 270000000
B25: 1691 | C25: Acc. Depreciation - Buildings | D25: Asset | E25: Fixed assets - net | F25: C | G25: 8 | H25: Depreciation & amortization | I25: =SUMIFS(tblFA[Opening Acc. Dep.],tblFA[Acc. Dep. Account],tblCOA[[#This Row],[Code]]) -> 697500000
B26: 1693 | C26: Acc. Depreciation - Vehicles | D26: Asset | E26: Fixed assets - net | F26: C | G26: 8 | H26: Depreciation & amortization | I26: =SUMIFS(tblFA[Opening Acc. Dep.],tblFA[Acc. Dep. Account],tblCOA[[#This Row],[Code]]) -> 377708349
B27: 1694 | C27: Acc. Depreciation - Machinery & Equipment | D27: Asset | E27: Fixed assets - net | F27: C | G27: 8 | H27: Depreciation & amortization | I27: =SUMIFS(tblFA[Opening Acc. Dep.],tblFA[Acc. Dep. Account],tblCOA[[#This Row],[Code]]) -> 523645817
B28: 1695 | C28: Acc. Depreciation - Office Furniture & Equipment | D28: Asset | E28: Fixed assets - net | F28: C | G28: 8 | H28: Depreciation & amortization | I28: =SUMIFS(tblFA[Opening Acc. Dep.],tblFA[Acc. Dep. Account],tblCOA[[#This Row],[Code]]) -> 204750000
B29: 1710 | C29: Software & Licenses | D29: Asset | E29: Intangible assets - net | F29: D | G29: 9 | H29: Intangible assets | I29: =SUMIFS(tblFA[Cost],tblFA[Cost Account],tblCOA[[#This Row],[Code]],tblFA[Acquisition Date],"<="&CompDate) -> 180000000
B30: 1719 | C30: Acc. Amortization - Software | D30: Asset | E30: Intangible assets - net | F30: C | G30: 9 | H30: Depreciation & amortization | I30: =SUMIFS(tblFA[Opening Acc. Dep.],tblFA[Acc. Dep. Account],tblCOA[[#This Row],[Code]]) -> 135000000
B31: 2110 | C31: Trade Payables | D31: Liability | E31: Trade payables | F31: C | G31: 10 | H31: Trade payables | I31: 620000000
B32: 2120 | C32: Other Payables | D32: Liability | E32: Other payables | F32: C | G32: 11 | H32: Other liabilities | I32: 35000000
B33: 2130 | C33: Accrued Expenses | D33: Liability | E33: Accrued expenses | F33: C | G33: 11 | H33: Other liabilities | I33: 45000000
B34: 2140 | C34: Contract Liabilities | D34: Liability | E34: Contract liabilities | F34: C | G34: 11 | H34: Other liabilities | I34: 40000000
B35: 2150 | C35: BPJS Payable | D35: Liability | E35: Accrued expenses | F35: C | G35: 11 | H35: Other liabilities | I35: 18000000
B36: 2210 | C36: Output VAT (PPN Keluaran) | D36: Liability | E36: Taxes payable | F36: C | G36: 7 | H36: Taxes payable | I36: 0
B37: 2220 | C37: VAT Payable - Net | D37: Liability | E37: Taxes payable | F37: C | G37: 7 | H37: Taxes payable | I37: 85000000
B38: 2230 | C38: WHT Payable - Art. 21 | D38: Liability | E38: Taxes payable | F38: C | G38: 7 | H38: Taxes payable | I38: 14000000
B39: 2240 | C39: WHT Payable - Unifikasi (Art. 23/4(2)) | D39: Liability | E39: Taxes payable | F39: C | G39: 7 | H39: Taxes payable | I39: 6500000
B40: 2250 | C40: Corporate Income Tax Payable (Art. 29) | D40: Liability | E40: Taxes payable | F40: C | G40: 7 | H40: Taxes payable | I40: 60000000
B41: 2310 | C41: Short-term Bank Loan | D41: Liability | E41: Short-term bank loans | F41: C | G41: 12 | H41: Bank loans | I41: 300000000
B42: 2410 | C42: Long-term Bank Loan | D42: Liability | E42: Long-term bank loans | F42: C | G42: 12 | H42: Bank loans | I42: 1500000000
... B47: 3310 | C47: Dividends | D47: Equity | E47: Retained earnings | F47: D | G47: 14 | H47: Dividends | I47: 0
B48: 4100 | C48: =IP_RevLabel -> Sales of goods | D48: Revenue | E48: Revenue | F48: C | G48: 15 | I48: 0
B49: 5100 | C49: =IP_CostLabel -> Cost of goods sold | D49: Expense | E49: Cost of revenue | F49: D | G49: 16 | I49: 0
B50: 6110 | C50: Salaries & Allowances - Selling | D50: Expense | E50: Selling expenses | F50: D | G50: 17 | I50: 0
B51: 6111 | C51: BPJS Employer Contributions - Selling | D51: Expense | E51: Selling expenses | F51: D | G51: 17 | I51: 0
B52: 6120 | C52: Advertising & Promotion | D52: Expense | E52: Selling expenses | F52: D | G52: 17 | I52: 0
B53: 6130 | C53: Marketplace & Sales Commissions | D53: Expense | E53: Selling expenses | F53: D | G53: 17 | I53: 0
B54: 6140 | C54: Shipping & Delivery | D54: Expense | E54: Selling expenses | F54: D | G54: 17 | I54: 0
B55: 6210 | C55: Salaries & Allowances - G&A | D55: Expense | E55: General & administrative expenses | F55: D | G55: 18 | I55: 0
B56: 6211 | C56: BPJS Employer Contributions - G&A | D56: Expense | E56: General & administrative expenses | F56: D | G56: 18 | I56: 0
B57: 6220 | C57: Rent Expense | D57: Expense | E57: General & administrative expenses | F57: D | G57: 18 | I57: 0
B58: 6230 | C58: Utilities & Telecommunication | D58: Expense | E58: General & administrative expenses | F58: D | G58: 18 | I58: 0
B59: 6240 | C59: Depreciation Expense | D59: Expense | E59: General & administrative expenses | F59: D | G59: 18 | I59: 0
B60: 6250 | C60: Amortization Expense - Software | D60: Expense | E60: General & administrative expenses | F60: D | G60: 18 | I60: 0
B61: 6260 | C61: Insurance Expense | D61: Expense | E61: General & administrative expenses | F61: D | G61: 18 | I61: 0
... B74: 8200 | C74: Final Income Tax Expense | D74: Expense | E74: Other expenses | F74: D | G74: 19 | I74: 0

Sheet Customers
B2: 🏠 HOME | E2: ◀ PREV | G2: NEXT ▶ | I2: ☰ MENU | K2: Journal | M2: Trial Bal. | P2: Income St. | S2: Balance Sh. | V2: Tax Recon | Y2: Bank Recon | AB2: Controls
B4: CUSTOMER MASTER
B5: Add new customers at the bottom of the table. Customer ID is used in Sales & Sales Invoice.
B6: Customer ID | C6: Customer Name | D6: Type | E6: NPWP | F6: Address | G6: City | H6: Email | I6: Phone | J6: Payment Terms (days) | K6: Credit Limit | L6: Sales YTD (DPP) | M6: Outstanding AR (est.)
B7: C000 | C7: Walk-in Customer | D7: Retail | E7: 0000000000000000 | F7: - | G7: Jakarta | H7: - | I7: - | J7: 0 | K7: 0 | L7: =SUMIFS(tblSales[DPP (excl. VAT)],tblSales[Customer ID],tblCustomers[[#This Row],[Customer ID]],tblSales[Date],"<="&PEnd) -> 3191885000 | M7: =SUMIFS(tblSales[Total incl. VAT],tblSales[Customer ID],tblCustomers[[#This Row],[Customer ID]],tblSales[Payment Method],"Credit (Term)",tblSales[Month],CutOff) -> 0
B8: C001 | C8: PT Cahaya Abadi Makmur | D8: Corporate | E8: 0213456789012000 | F8: Jl. Gatot Subroto No. 21 | G8: Jakarta | H8: ap@cahayaabadi.co.id | I8: 021-5201188 | J8: 30 | K8: 250000000 | L8: =SUMIFS(tblSales[DPP (excl. VAT)],tblSales[Customer ID],tblCustomers[[#This Row],[Customer ID]],tblSales[Date],"<="&PEnd) -> 827360000 | M8: =SUMIFS(tblSales[Total incl. VAT],tblSales[Customer ID],tblCustomers[[#This Row],[Customer ID]],tblSales[Payment Method],"Credit (Term)",tblSales[Month],CutOff) -> 117615600
B9: C002 | C9: PT Bintang Timur Sejahtera | D9: Corporate | E9: 0314567890123000 | F9: Jl. Ahmad Yani No. 88 | G9: Surabaya | H9: finance@bintangtimur.co.id | I9: 031-5678120 | J9: 30 | K9: 200000000 | L9: =SUMIFS(tblSales[DPP (excl. VAT)],tblSales[Customer ID],tblCustomers[[#This Row],[Customer ID]],tblSales[Date],"<="&PEnd) -> 844240000 | M9: =SUMIFS(tblSales[Total incl. VAT],tblSales[Customer ID],tblCustomers[[#This Row],[Customer ID]],tblSales[Payment Method],"Credit (Term)",tblSales[Month],CutOff) -> 192340800
B10: C003 | C10: CV Mitra Karya Mandiri | D10: SME | E10: 0415678901234000 | F10: Jl. Asia Afrika No. 102 | G10: Bandung | H10: mitrakarya@gmail.com | I10: 022-4231987 | J10: 14 | K10: 100000000 | L10: =SUMIFS(tblSales[DPP (excl. VAT)],tblSales[Customer ID],tblCustomers[[#This Row],[Customer ID]],tblSales[Date],"<="&PEnd) -> 512560000 | M10: =SUMIFS(tblSales[Total incl. VAT],tblSales[Customer ID],tblCustomers[[#This Row],[Customer ID]],tblSales[Payment Method],"Credit (Term)",tblSales[Month],CutOff) -> 97014000
B11: C004 | C11: PT Graha Nusa Persada | D11: Corporate | E11: 0516789012345000 | F11: Jl. HR Rasuna Said Kav. 5 | G11: Jakarta | H11: ap@grahanusa.co.id | I11: 021-5290044 | J11: 30 | K11: 300000000 | L11: =SUMIFS(tblSales[DPP (excl. VAT)],tblSales[Customer ID],tblCustomers[[#This Row],[Customer ID]],tblSales[Date],"<="&PEnd) -> 927360000 | M11: =SUMIFS(tblSales[Total incl. VAT],tblSales[Customer ID],tblCustomers[[#This Row],[Customer ID]],tblSales[Payment Method],"Credit (Term)",tblSales[Month],CutOff) -> 91108800
B12: C005 | C12: PT Samudra Jaya Logistik | D12: Corporate | E12: 0617890123456000 | F12: Jl. Yos Sudarso No. 17 | G12: Jakarta Utara | H12: finance@samudrajaya.co.id | I12: 021-4301255 | J12: 45 | K12: 250000000 | L12: =SUMIFS(tblSales[DPP (excl. VAT)],tblSales[Customer ID],tblCustomers[[#This Row],[Customer ID]],tblSales[Date],"<="&PEnd) -> 712240000 | M12: =SUMIFS(tblSales[Total incl. VAT],tblSales[Customer ID],tblCustomers[[#This Row],[Customer ID]],tblSales[Payment Method],"Credit (Term)",tblSales[Month],CutOff) -> 82006800
B13: C006 | C13: PT Arunika Digital Kreatif | D13: Corporate | E13: 0718901234567000 | F13: Jl. Kemang Raya No. 9 | G13: Jakarta Selatan | H13: billing@arunika.id | I13: 021-7190033 | J13: 30 | K13: 150000000 | L13: =SUMIFS(tblSales[DPP (excl. VAT)],tblSales[Customer ID],tblCustomers[[#This Row],[Customer ID]],tblSales[Date],"<="&PEnd) -> 443600000 | M13: =SUMIFS(tblSales[Total incl. VAT],tblSales[Customer ID],tblCustomers[[#This Row],[Customer ID]],tblSales[Payment Method],"Credit (Term)",tblSales[Month],CutOff) -> 68464800
B14: C007 | C14: PT Mega Prima Distribusi | D14: Corporate | E14: 0819012345678000 | F14: Jl. Raya Bekasi Km 22 | G14: Bekasi | H14: ap@megaprima.co.id | I14: 021-8834567 | J14: 30 | K14: 300000000 | L14: =SUMIFS(tblSales[DPP (excl. VAT)],tblSales[Customer ID],tblCustomers[[#This Row],[Customer ID]],tblSales[Date],"<="&PEnd) -> 776080000 | M14: =SUMIFS(tblSales[Total incl. VAT],tblSales[Customer ID],tblCustomers[[#This Row],[Customer ID]],tblSales[Payment Method],"Credit (Term)",tblSales[Month],CutOff) -> 65978400
B15: C008 | C15: CV Sumber Rejeki Utama | D15: SME | E15: 0910123456789000 | F15: Jl. Pemuda No. 45 | G15: Semarang | H15: sumberrejeki@yahoo.com | I15: 024-3567812 | J15: 14 | K15: 80000000 | L15: =SUMIFS(tblSales[DPP (excl. VAT)],tblSales[Customer ID],tblCustomers[[#This Row],[Customer ID]],tblSales[Date],"<="&PEnd) -> 456720000 | M15: =SUMIFS(tblSales[Total incl. VAT],tblSales[Customer ID],tblCustomers[[#This Row],[Customer ID]],tblSales[Payment Method],"Credit (Term)",tblSales[Month],CutOff) -> 72416400
B16: C009 | C16: PT Kencana Wira Usaha | D16: Corporate | E16: 1011234567890000 | F16: Jl. Diponegoro No. 61 | G16: Medan | H16: finance@kencanawira.co.id | I16: 061-4155223 | J16: 30 | K16: 200000000 | L16: =SUMIFS(tblSales[DPP (excl. VAT)],tblSales[Customer ID],tblCustomers[[#This Row],[Customer ID]],tblSales[Date],"<="&PEnd) -> 768960000 | M16: =SUMIFS(tblSales[Total incl. VAT],tblSales[Customer ID],tblCustomers[[#This Row],[Customer ID]],tblSales[Payment Method],"Credit (Term)",tblSales[Month],CutOff) -> 33344400
B17: C010 | C17: PT Delta Inti Selaras | D17: Corporate | E17: 1112345678901000 | F17: Jl. Sudirman No. 120 | G17: Pekanbaru | H17: ap@deltainti.co.id | I17: 0761-855421 | J17: 30 | K17: 150000000 | L17: =SUMIFS(tblSales[DPP (excl. VAT)],tblSales[Customer ID],tblCustomers[[#This Row],[Customer ID]],tblSales[Date],"<="&PEnd) -> 821240000 | M17: =SUMIFS(tblSales[Total incl. VAT],tblSales[Customer ID],tblCustomers[[#This Row],[Customer ID]],tblSales[Payment Method],"Credit (Term)",tblSales[Month],CutOff) -> 122277600
B18: C011 | C18: PT Harmoni Pangan Lestari | D18: Corporate | E18: 1213456789012000 | F18: Jl. Raya Kuta No. 77 | G18: Badung, Bali | H18: finance@harmonipangan.co.id | I18: 0361-756210 | J18: 30 | K18: 200000000 | L18: =SUMIFS(tblSales[DPP (excl. VAT)],tblSales[Customer ID],tblCustomers[[#This Row],[Customer ID]],tblSales[Date],"<="&PEnd) -> 491440000 | M18: =SUMIFS(tblSales[Total incl. VAT],tblSales[Customer ID],tblCustomers[[#This Row],[Customer ID]],tblSales[Payment Method],"Credit (Term)",tblSales[Month],CutOff) -> 33655200
B19: C012 | C19: PT Lintas Benua Niaga | D19: Corporate | E19: 1314567890123000 | F19: Jl. MH Thamrin No. 3 | G19: Jakarta Pusat | H19: ap@lintasbenua.co.id | I19: 021-3900812 | J19: 45 | K19: 350000000 | L19: =SUMIFS(tblSales[DPP (excl. VAT)],tblSales[Customer ID],tblCustomers[[#This Row],[Customer ID]],tblSales[Date],"<="&PEnd) -> 576880000 | M19: =SUMIFS(tblSales[Total incl. VAT],tblSales[Customer ID],tblCustomers[[#This Row],[Customer ID]],tblSales[Payment Method],"Credit (Term)",tblSales[Month],CutOff) -> 81118800

Sheet Vendors
B2: 🏠 HOME | E2: ◀ PREV | G2: NEXT ▶ | I2: ☰ MENU | K2: Journal | M2: Trial Bal. | O2: Income St. | R2: Balance Sh. | U2: Tax Recon | X2: Bank Recon | AA2: Controls
B4: VENDOR MASTER
B5: VAT Status drives Input VAT; WHT Type drives PPh Unifikasi withholding on Purchases.
B6: Vendor ID | C6: Vendor Name | D6: Category | E6: NPWP | F6: VAT Status | G6: WHT Type | H6: Default Account | I6: Address | J6: Bank Account | K6: Payment Terms (days) | L6: Purchases YTD (DPP) | M6: Unpaid at Period End
B7: V001 | C7: PT Sumber Barang Utama | D7: Inventory Supplier | E7: 0123987654321000 | F7: PKP | G7: None | H7: 1310 | I7: Jl. Industri Raya No. 8, Tangerang | J7: BCA 5270011122 | K7: 30 | L7: =SUMIFS(tblPurchases[DPP (excl. VAT)],tblPurchases[Vendor ID],tblVendors[[#This Row],[Vendor ID]],tblPurchases[Date],"<="&PEnd) -> 3431971000 | M7: =SUMIFS(tblPurchases[Total Payable],tblPurchases[Vendor ID],tblVendors[[#This Row],[Vendor ID]],tblPurchases[Date],"<="&PEnd,tblPurchases[Payment Date],">"&PEnd) -> 431996460
B8: V002 | C8: PT Prima Supply Nusantara | D8: Inventory Supplier | E8: 0234987654321000 | F8: PKP | G8: None | H8: 1310 | I8: Kawasan Pulogadung Blok C2, Jakarta | J8: Mandiri 1230004455 | K8: 30 | L8: =SUMIFS(tblPurchases[DPP (excl. VAT)],tblPurchases[Vendor ID],tblVendors[[#This Row],[Vendor ID]],tblPurchases[Date],"<="&PEnd) -> 2402381000 | M8: =SUMIFS(tblPurchases[Total Payable],tblPurchases[Vendor ID],tblVendors[[#This Row],[Vendor ID]],tblPurchases[Date],"<="&PEnd,tblPurchases[Payment Date],">"&PEnd) -> 302397300
B9: V003 | C9: CV Aneka Grosir Jaya | D9: Inventory Supplier | E9: 0345987654321000 | F9: Non-PKP | G9: None | H9: 1310 | I9: Pasar Tanah Abang Blok A, Jakarta | J9: BRI 0342010099 | K9: 7 | L9: =SUMIFS(tblPurchases[DPP (excl. VAT)],tblPurchases[Vendor ID],tblVendors[[#This Row],[Vendor ID]],tblPurchases[Date],"<="&PEnd) -> 1029592000 | M9: =SUMIFS(tblPurchases[Total Payable],tblPurchases[Vendor ID],tblVendors[[#This Row],[Vendor ID]],tblPurchases[Date],"<="&PEnd,tblPurchases[Payment Date],">"&PEnd) -> 0
B10: V004 | C10: PT Graha Properti Sudirman | D10: Building Rent | E10: 0456987654321000 | F10: PKP | G10: Art. 4(2) - Building Rent | H10: 1410 | I10: Jl. Jend. Sudirman Kav. 52, Jakarta | J10: BNI 0098812233 | K10: 0 | L10: =SUMIFS(tblPurchases[DPP (excl. VAT)],tblPurchases[Vendor ID],tblVendors[[#This Row],[Vendor ID]],tblPurchases[Date],"<="&PEnd) -> 0 | M10: =SUMIFS(tblPurchases[Total Payable],tblPurchases[Vendor ID],tblVendors[[#This Row],[Vendor ID]],tblPurchases[Date],"<="&PEnd,tblPurchases[Payment Date],">"&PEnd) -> 0
B11: V005 | C11: PT Asuransi Proteksi Indonesia | D11: Insurance | E11: 0567987654321000 | F11: VAT-exempt | G11: None | H11: 1420 | I11: Jl. Thamrin No. 15, Jakarta | J11: BCA 6040987654 | K11: 14 | L11: =SUMIFS(tblPurchases[DPP (excl. VAT)],tblPurchases[Vendor ID],tblVendors[[#This Row],[Vendor ID]],tblPurchases[Date],"<="&PEnd) -> 36000000 | M11: =SUMIFS(tblPurchases[Total Payable],tblPurchases[Vendor ID],tblVendors[[#This Row],[Vendor ID]],tblPurchases[Date],"<="&PEnd,tblPurchases[Payment Date],">"&PEnd) -> 36000000
B12: V006 | C12: PT Cloud Software Indonesia | D12: Software Subscription | E12: 0678987654321000 | F12: PKP | G12: Art. 23 - Services | H12: 1430 | I12: Jl. TB Simatupang No. 18, Jakarta | J12: BCA 8830556677 | K12: 7 | L12: =SUMIFS(tblPurchases[DPP (excl. VAT)],tblPurchases[Vendor ID],tblVendors[[#This Row],[Vendor ID]],tblPurchases[Date],"<="&PEnd) -> 72000000 | M12: =SUMIFS(tblPurchases[Total Payable],tblPurchases[Vendor ID],tblVendors[[#This Row],[Vendor ID]],tblPurchases[Date],"<="&PEnd,tblPurchases[Payment Date],">"&PEnd) -> 0
B13: V007 | C13: PT Kreasi Iklan Digital | D13: Advertising Agency | E13: 0789987654321000 | F13: PKP | G13: Art. 23 - Services | H13: 6120 | I13: Jl. Senopati No. 40, Jakarta | J13: Mandiri 1650098877 | K13: 30 | L13: =SUMIFS(tblPurchases[DPP (excl. VAT)],tblPurchases[Vendor ID],tblVendors[[#This Row],[Vendor ID]],tblPurchases[Date],"<="&PEnd) -> 124856000 | M13: =SUMIFS(tblPurchases[Total Payable],tblPurchases[Vendor ID],tblVendors[[#This Row],[Vendor ID]],tblPurchases[Date],"<="&PEnd,tblPurchases[Payment Date],">"&PEnd) -> 15033280
B14: V008 | C14: PT Ekspedisi Cepat Nusantara | D14: Shipping & Courier | E14: 0890987654321000 | F14: PKP | G14: Art. 23 - Services | H14: 6140 | I14: Jl. Daan Mogot Km 13, Jakarta | J14: BCA 2210334455 | K14: 14 | L14: =SUMIFS(tblPurchases[DPP (excl. VAT)],tblPurchases[Vendor ID],tblVendors[[#This Row],[Vendor ID]],tblPurchases[Date],"<="&PEnd) -> 102156000 | M14: =SUMIFS(tblPurchases[Total Payable],tblPurchases[Vendor ID],tblVendors[[#This Row],[Vendor ID]],tblPurchases[Date],"<="&PEnd,tblPurchases[Payment Date],">"&PEnd) -> 12300650
B15: V009 | C15: PT Utilitas Listrik & Telekom | D15: Utilities | E15: 0901987654321000 | F15: PKP | G15: None | H15: 6230 | I15: Jl. Gatot Subroto Kav. 18, Jakarta | J15: BNI 0123456789 | K15: 14 | L15: =SUMIFS(tblPurchases[DPP (excl. VAT)],tblPurchases[Vendor ID],tblVendors[[#This Row],[Vendor ID]],tblPurchases[Date],"<="&PEnd) -> 125473000 | M15: =SUMIFS(tblPurchases[Total Payable],tblPurchases[Vendor ID],tblVendors[[#This Row],[Vendor ID]],tblPurchases[Date],"<="&PEnd,tblPurchases[Payment Date],">"&PEnd) -> 0
B16: V010 | C16: KKP Mitra Pajak & Konsultan | D16: Professional Services | E16: 1012987654321000 | F16: PKP | G16: Art. 23 - Services | H16: 6280 | I16: Jl. Kuningan Barat No. 26, Jakarta | J16: BCA 3450778899 | K16: 14 | L16: =SUMIFS(tblPurchases[DPP (excl. VAT)],tblPurchases[Vendor ID],tblVendors[[#This Row],[Vendor ID]],tblPurchases[Date],"<="&PEnd) -> 140000000 | M16: =SUMIFS(tblPurchases[Total Payable],tblPurchases[Vendor ID],tblVendors[[#This Row],[Vendor ID]],tblPurchases[Date],"<="&PEnd,tblPurchases[Payment Date],">"&PEnd) -> 0
B17: V011 | C17: CV Teknik Servis Mandiri | D17: Repair & Maintenance | E17: 1123987654321000 | F17: Non-PKP | G17: Art. 23 - Services | H17: 6295 | I17: Jl. Fatmawati No. 66, Jakarta | J17: BRI 0567002233 | K17: 7 | L17: =SUMIFS(tblPurchases[DPP (excl. VAT)],tblPurchases[Vendor ID],tblVendors[[#This Row],[Vendor ID]],tblPurchases[Date],"<="&PEnd) -> 40738000 | M17: =SUMIFS(tblPurchases[Total Payable],tblPurchases[Vendor ID],tblVendors[[#This Row],[Vendor ID]],tblPurchases[Date],"<="&PEnd,tblPurchases[Payment Date],">"&PEnd) -> 0
B18: V012 | C18: Toko ATK Sentosa | D18: Office Supplies | E18: 1234987654321000 | F18: Non-PKP | G18: None | H18: 6270 | I18: Jl. Mangga Dua Raya No. 5, Jakarta | J18: BCA 4410223344 | K18: 0 | L18: =SUMIFS(tblPurchases[DPP (excl. VAT)],tblPurchases[Vendor ID],tblVendors[[#This Row],[Vendor ID]],tblPurchases[Date],"<="&PEnd) -> 29893000 | M18: =SUMIFS(tblPurchases[Total Payable],tblPurchases[Vendor ID],tblVendors[[#This Row],[Vendor ID]],tblPurchases[Date],"<="&PEnd,tblPurchases[Payment Date],">"&PEnd) -> 0
... B23: V017 | C23: Various Restaurants & Donations | D23: Entertainment & Donations | E23: 0000000000000000 | F23: Non-PKP | G23: None | H23: 6296 | I23: Various | J23: - | K23: 0 | L23: =SUMIFS(tblPurchases[DPP (excl. VAT)],tblPurchases[Vendor ID],tblVendors[[#This Row],[Vendor ID]],tblPurchases[Date],"<="&PEnd) -> 24449000 | M23: =SUMIFS(tblPurchases[Total Payable],tblPurchases[Vendor ID],tblVendors[[#This Row],[Vendor ID]],tblPurchases[Date],"<="&PEnd,tblPurchases[Payment Date],">"&PEnd) -> 0

Sheet Employees
B2: 🏠 HOME | E2: ◀ PREV | H2: NEXT ▶ | K2: ☰ MENU | M2: Journal | O2: Trial Bal. | Q2: Income St. | T2: Balance Sh. | W2: Tax Recon | Z2: Bank Recon | AC2: Controls
B4: EMPLOYEE MASTER
B5: Salary, PTKP and department feed the Payroll sheet automatically. TER category is derived from PTKP status (PP 58/2023).
B6: Employee ID | C6: Full Name | D6: Position | E6: Department | F6: Join Date | G6: NIK / NPWP | H6: PTKP Status | I6: Basic Salary | J6: Fixed Allowance | K6: Bank Account | L6: TER Category | M6: Gross Pay YTD | N6: PPh 21 YTD
B7: E001 | C7: Budi Santoso | D7: President Director | E7: G&A | F7: 43174 | G7: 3171010101800001 | H7: K/2 | I7: 25000000 | J7: 4000000 | K7: Mandiri 1230000001 | L7: =IF(OR(tblEmployees[[#This Row],[PTKP Status]]="TK/0",tblEmployees[[#This Row],[PTKP Status]]="TK/1",tblEmployees[[#This Row],[PTKP Status]]="K/0"),"A",IF(tblEmployees[[#This Row],[PTKP Status]]="K/3","C","B")) -> B | M7: =SUMIFS(tblPayroll[Gross Salary],tblPayroll[Employee ID],tblEmployees[[#This Row],[Employee ID]],tblPayroll[Period],"<="&CutOff) -> 319000000 | N7: =SUMIFS(tblPayroll[PPh 21],tblPayroll[Employee ID],tblEmployees[[#This Row],[Employee ID]],tblPayroll[Period],"<="&CutOff) -> 43734848
B8: E002 | C8: Siti Rahmawati | D8: Finance Director | E8: G&A | F8: 43222 | G8: 3171010202820002 | H8: K/1 | I8: 20000000 | J8: 3000000 | K8: Mandiri 1230000002 | L8: =IF(OR(tblEmployees[[#This Row],[PTKP Status]]="TK/0",tblEmployees[[#This Row],[PTKP Status]]="TK/1",tblEmployees[[#This Row],[PTKP Status]]="K/0"),"A",IF(tblEmployees[[#This Row],[PTKP Status]]="K/3","C","B")) -> B | M8: =SUMIFS(tblPayroll[Gross Salary],tblPayroll[Employee ID],tblEmployees[[#This Row],[Employee ID]],tblPayroll[Period],"<="&CutOff) -> 253000000 | N8: =SUMIFS(tblPayroll[PPh 21],tblPayroll[Employee ID],tblEmployees[[#This Row],[Employee ID]],tblPayroll[Period],"<="&CutOff) -> 27042116
B9: E003 | C9: Dewi Lestari | D9: Accounting Manager | E9: G&A | F9: 43507 | G9: 3171010303880003 | H9: TK/0 | I9: 15000000 | J9: 2000000 | K9: Mandiri 1230000003 | L9: =IF(OR(tblEmployees[[#This Row],[PTKP Status]]="TK/0",tblEmployees[[#This Row],[PTKP Status]]="TK/1",tblEmployees[[#This Row],[PTKP Status]]="K/0"),"A",IF(tblEmployees[[#This Row],[PTKP Status]]="K/3","C","B")) -> A | M9: =SUMIFS(tblPayroll[Gross Salary],tblPayroll[Employee ID],tblEmployees[[#This Row],[Employee ID]],tblPayroll[Period],"<="&CutOff) -> 187000000 | N9: =SUMIFS(tblPayroll[PPh 21],tblPayroll[Employee ID],tblEmployees[[#This Row],[Employee ID]],tblPayroll[Period],"<="&CutOff) -> 17491748
B10: E004 | C10: Agus Prasetyo | D10: Store Manager | E10: Selling | F10: 43647 | G10: 3171010404850004 | H10: K/1 | I10: 14000000 | J10: 2000000 | K10: Mandiri 1230000004 | L10: =IF(OR(tblEmployees[[#This Row],[PTKP Status]]="TK/0",tblEmployees[[#This Row],[PTKP Status]]="TK/1",tblEmployees[[#This Row],[PTKP Status]]="K/0"),"A",IF(tblEmployees[[#This Row],[PTKP Status]]="K/3","C","B")) -> B | M10: =SUMIFS(tblPayroll[Gross Salary],tblPayroll[Employee ID],tblEmployees[[#This Row],[Employee ID]],tblPayroll[Period],"<="&CutOff) -> 176000000 | N10: =SUMIFS(tblPayroll[PPh 21],tblPayroll[Employee ID],tblEmployees[[#This Row],[Employee ID]],tblPayroll[Period],"<="&CutOff) -> 14670464
B11: E005 | C11: Rina Kartika | D11: Marketing Lead | E11: Selling | F11: 43836 | G11: 3171010505900005 | H11: TK/0 | I11: 12000000 | J11: 1500000 | K11: Mandiri 1230000005 | L11: =IF(OR(tblEmployees[[#This Row],[PTKP Status]]="TK/0",tblEmployees[[#This Row],[PTKP Status]]="TK/1",tblEmployees[[#This Row],[PTKP Status]]="K/0"),"A",IF(tblEmployees[[#This Row],[PTKP Status]]="K/3","C","B")) -> A | M11: =SUMIFS(tblPayroll[Gross Salary],tblPayroll[Employee ID],tblEmployees[[#This Row],[Employee ID]],tblPayroll[Period],"<="&CutOff) -> 148500000 | N11: =SUMIFS(tblPayroll[PPh 21],tblPayroll[Employee ID],tblEmployees[[#This Row],[Employee ID]],tblPayroll[Period],"<="&CutOff) -> 10619385
B12: E006 | C12: Andi Saputra | D12: Tax & Finance Staff | E12: G&A | F12: 44256 | G12: 3171010606950006 | H12: TK/0 | I12: 8500000 | J12: 1000000 | K12: Mandiri 1230000006 | L12: =IF(OR(tblEmployees[[#This Row],[PTKP Status]]="TK/0",tblEmployees[[#This Row],[PTKP Status]]="TK/1",tblEmployees[[#This Row],[PTKP Status]]="K/0"),"A",IF(tblEmployees[[#This Row],[PTKP Status]]="K/3","C","B")) -> A | M12: =SUMIFS(tblPayroll[Gross Salary],tblPayroll[Employee ID],tblEmployees[[#This Row],[Employee ID]],tblPayroll[Period],"<="&CutOff) -> 104500000 | N12: =SUMIFS(tblPayroll[PPh 21],tblPayroll[Employee ID],tblEmployees[[#This Row],[Employee ID]],tblPayroll[Period],"<="&CutOff) -> 3342138
B13: E007 | C13: Fitri Handayani | D13: HR & GA Officer | E13: G&A | F13: 44424 | G13: 3171010707930007 | H13: K/0 | I13: 8000000 | J13: 1000000 | K13: Mandiri 1230000007 | L13: =IF(OR(tblEmployees[[#This Row],[PTKP Status]]="TK/0",tblEmployees[[#This Row],[PTKP Status]]="TK/1",tblEmployees[[#This Row],[PTKP Status]]="K/0"),"A",IF(tblEmployees[[#This Row],[PTKP Status]]="K/3","C","B")) -> A | M13: =SUMIFS(tblPayroll[Gross Salary],tblPayroll[Employee ID],tblEmployees[[#This Row],[Employee ID]],tblPayroll[Period],"<="&CutOff) -> 99000000 | N13: =SUMIFS(tblPayroll[PPh 21],tblPayroll[Employee ID],tblEmployees[[#This Row],[Employee ID]],tblPayroll[Period],"<="&CutOff) -> 2954547
B14: E008 | C14: Rizky Ramadhan | D14: Sales Supervisor | E14: Selling | F14: 44116 | G14: 3171010808910008 | H14: K/0 | I14: 9000000 | J14: 1500000 | K14: Mandiri 1230000008 | L14: =IF(OR(tblEmployees[[#This Row],[PTKP Status]]="TK/0",tblEmployees[[#This Row],[PTKP Status]]="TK/1",tblEmployees[[#This Row],[PTKP Status]]="K/0"),"A",IF(tblEmployees[[#This Row],[PTKP Status]]="K/3","C","B")) -> A | M14: =SUMIFS(tblPayroll[Gross Salary],tblPayroll[Employee ID],tblEmployees[[#This Row],[Employee ID]],tblPayroll[Period],"<="&CutOff) -> 115500000 | N14: =SUMIFS(tblPayroll[PPh 21],tblPayroll[Employee ID],tblEmployees[[#This Row],[Employee ID]],tblPayroll[Period],"<="&CutOff) -> 4896612
B15: E009 | C15: Nadia Putri | D15: Sales Associate | E15: Selling | F15: 44655 | G15: 3171010909990009 | H15: TK/0 | I15: 5800000 | J15: 700000 | K15: Mandiri 1230000009 | L15: =IF(OR(tblEmployees[[#This Row],[PTKP Status]]="TK/0",tblEmployees[[#This Row],[PTKP Status]]="TK/1",tblEmployees[[#This Row],[PTKP Status]]="K/0"),"A",IF(tblEmployees[[#This Row],[PTKP Status]]="K/3","C","B")) -> A | M15: =SUMIFS(tblPayroll[Gross Salary],tblPayroll[Employee ID],tblEmployees[[#This Row],[Employee ID]],tblPayroll[Period],"<="&CutOff) -> 71500000 | N15: =SUMIFS(tblPayroll[PPh 21],tblPayroll[Employee ID],tblEmployees[[#This Row],[Employee ID]],tblPayroll[Period],"<="&CutOff) -> 1429206
B16: E010 | C16: Dimas Pratama | D16: Sales Associate | E16: Selling | F16: 44935 | G16: 3171011010000010 | H16: TK/0 | I16: 5800000 | J16: 700000 | K16: Mandiri 1230000010 | L16: =IF(OR(tblEmployees[[#This Row],[PTKP Status]]="TK/0",tblEmployees[[#This Row],[PTKP Status]]="TK/1",tblEmployees[[#This Row],[PTKP Status]]="K/0"),"A",IF(tblEmployees[[#This Row],[PTKP Status]]="K/3","C","B")) -> A | M16: =SUMIFS(tblPayroll[Gross Salary],tblPayroll[Employee ID],tblEmployees[[#This Row],[Employee ID]],tblPayroll[Period],"<="&CutOff) -> 71500000 | N16: =SUMIFS(tblPayroll[PPh 21],tblPayroll[Employee ID],tblEmployees[[#This Row],[Employee ID]],tblPayroll[Period],"<="&CutOff) -> 1429206
B17: E011 | C17: Yusuf Hidayat | D17: Warehouse Supervisor | E17: Selling | F17: 43787 | G17: 3171011111870011 | H17: K/2 | I17: 7500000 | J17: 1000000 | K17: Mandiri 1230000011 | L17: =IF(OR(tblEmployees[[#This Row],[PTKP Status]]="TK/0",tblEmployees[[#This Row],[PTKP Status]]="TK/1",tblEmployees[[#This Row],[PTKP Status]]="K/0"),"A",IF(tblEmployees[[#This Row],[PTKP Status]]="K/3","C","B")) -> B | M17: =SUMIFS(tblPayroll[Gross Salary],tblPayroll[Employee ID],tblEmployees[[#This Row],[Employee ID]],tblPayroll[Period],"<="&CutOff) -> 93500000 | N17: =SUMIFS(tblPayroll[PPh 21],tblPayroll[Employee ID],tblEmployees[[#This Row],[Employee ID]],tblPayroll[Period],"<="&CutOff) -> 2016744
B18: E012 | C18: Lestari Wulandari | D18: Cashier | E18: Selling | F18: 44725 | G18: 3171011212970012 | H18: TK/1 | I18: 5600000 | J18: 600000 | K18: Mandiri 1230000012 | L18: =IF(OR(tblEmployees[[#This Row],[PTKP Status]]="TK/0",tblEmployees[[#This Row],[PTKP Status]]="TK/1",tblEmployees[[#This Row],[PTKP Status]]="K/0"),"A",IF(tblEmployees[[#This Row],[PTKP Status]]="K/3","C","B")) -> A | M18: =SUMIFS(tblPayroll[Gross Salary],tblPayroll[Employee ID],tblEmployees[[#This Row],[Employee ID]],tblPayroll[Period],"<="&CutOff) -> 68200000 | N18: =SUMIFS(tblPayroll[PPh 21],tblPayroll[Employee ID],tblEmployees[[#This Row],[Employee ID]],tblPayroll[Period],"<="&CutOff) -> 1217409
... B21: E015 | C21: Hendra Wijaya | D21: IT Support | E21: G&A | F21: 44466 | G21: 3171011503940015 | H21: TK/0 | I21: 9500000 | J21: 1000000 | K21: Mandiri 1230000015 | L21: =IF(OR(tblEmployees[[#This Row],[PTKP Status]]="TK/0",tblEmployees[[#This Row],[PTKP Status]]="TK/1",tblEmployees[[#This Row],[PTKP Status]]="K/0"),"A",IF(tblEmployees[[#This Row],[PTKP Status]]="K/3","C","B")) -> A | M21: =SUMIFS(tblPayroll[Gross Salary],tblPayroll[Employee ID],tblEmployees[[#This Row],[Employee ID]],tblPayroll[Period],"<="&CutOff) -> 115500000 | N21: =SUMIFS(tblPayroll[PPh 21],tblPayroll[Employee ID],tblEmployees[[#This Row],[Employee ID]],tblPayroll[Period],"<="&CutOff) -> 4896612

Sheet Products
B2: 🏠 HOME | E2: ◀ PREV | G2: NEXT ▶ | I2: ☰ MENU | K2: Journal | O2: Trial Bal. | R2: Income St. | U2: Balance Sh. | X2: Tax Recon | AA2: Bank Recon | AD2: Controls
B4: PRODUCT / SERVICE MASTER
B5: Names, categories & units follow the selected industry. Prices & unit costs (blue) are editable.
B6: Code | C6: Product / Service Name | D6: Category Group | E6: Category | F6: Unit | G6: Selling Price (excl. VAT) | H6: Unit Cost | I6: Gross Margin % | J6: Qty Sold YTD | K6: Sales YTD | O6: Channel Code | P6: Channel Name
B7: P01 | C7: =_xlfn.XLOOKUP("Product "&tblProducts[[#This Row],[Code]],'Industry Profile'!$B$18:$B$27,'Industry Profile'!$C$18:$C$27) -> Socks & Accessories | D7: 1 | E7: {=INDEX('Industry Profile'!$C$12:$C$14,tblProducts[[#This Row],[Category Group]])} -> Accessories & Basics | F7: =IP_Unit -> pcs | G7: 45000 | H7: 24000 | I7: =IFERROR(1-tblProducts[[#This Row],[Unit Cost]]/tblProducts[[#This Row],[Selling Price (excl. VAT)]],0) -> 0.46666667 | J7: =SUMIFS(tblSales[Qty],tblSales[Product Code],tblProducts[[#This Row],[Code]],tblSales[Date],"<="&PEnd) -> 15222 | K7: =SUMIFS(tblSales[DPP (excl. VAT)],tblSales[Product Code],tblProducts[[#This Row],[Code]],tblSales[Date],"<="&PEnd) -> 684990000 | O7: CH1 | P7: ='Industry Profile'!C15 -> In-store
B8: P02 | C8: =_xlfn.XLOOKUP("Product "&tblProducts[[#This Row],[Code]],'Industry Profile'!$B$18:$B$27,'Industry Profile'!$C$18:$C$27) -> Premium Basic T-shirt | D8: 1 | E8: {=INDEX('Industry Profile'!$C$12:$C$14,tblProducts[[#This Row],[Category Group]])} -> Accessories & Basics | F8: =IP_Unit -> pcs | G8: 65000 | H8: 37000 | I8: =IFERROR(1-tblProducts[[#This Row],[Unit Cost]]/tblProducts[[#This Row],[Selling Price (excl. VAT)]],0) -> 0.43076923 | J8: =SUMIFS(tblSales[Qty],tblSales[Product Code],tblProducts[[#This Row],[Code]],tblSales[Date],"<="&PEnd) -> 13201 | K8: =SUMIFS(tblSales[DPP (excl. VAT)],tblSales[Product Code],tblProducts[[#This Row],[Code]],tblSales[Date],"<="&PEnd) -> 858065000 | O8: CH2 | P8: ='Industry Profile'!C16 -> Marketplace
B9: P03 | C9: =_xlfn.XLOOKUP("Product "&tblProducts[[#This Row],[Code]],'Industry Profile'!$B$18:$B$27,'Industry Profile'!$C$18:$C$27) -> Casual Shorts | D9: 1 | E9: {=INDEX('Industry Profile'!$C$12:$C$14,tblProducts[[#This Row],[Category Group]])} -> Accessories & Basics | F9: =IP_Unit -> pcs | G9: 85000 | H9: 50000 | I9: =IFERROR(1-tblProducts[[#This Row],[Unit Cost]]/tblProducts[[#This Row],[Selling Price (excl. VAT)]],0) -> 0.41176471 | J9: =SUMIFS(tblSales[Qty],tblSales[Product Code],tblProducts[[#This Row],[Code]],tblSales[Date],"<="&PEnd) -> 13718 | K9: =SUMIFS(tblSales[DPP (excl. VAT)],tblSales[Product Code],tblProducts[[#This Row],[Code]],tblSales[Date],"<="&PEnd) -> 1166030000 | O9: CH3 | P9: ='Industry Profile'!C17 -> Website & Social Media
B10: P04 | C10: =_xlfn.XLOOKUP("Product "&tblProducts[[#This Row],[Code]],'Industry Profile'!$B$18:$B$27,'Industry Profile'!$C$18:$C$27) -> Casual Shirt | D10: 2 | E10: {=INDEX('Industry Profile'!$C$12:$C$14,tblProducts[[#This Row],[Category Group]])} -> Apparel & Footwear | F10: =IP_Unit -> pcs | G10: 120000 | H10: 72000 | I10: =IFERROR(1-tblProducts[[#This Row],[Unit Cost]]/tblProducts[[#This Row],[Selling Price (excl. VAT)]],0) -> 0.4 | J10: =SUMIFS(tblSales[Qty],tblSales[Product Code],tblProducts[[#This Row],[Code]],tblSales[Date],"<="&PEnd) -> 11669 | K10: =SUMIFS(tblSales[DPP (excl. VAT)],tblSales[Product Code],tblProducts[[#This Row],[Code]],tblSales[Date],"<="&PEnd) -> 1400280000
B11: P05 | C11: =_xlfn.XLOOKUP("Product "&tblProducts[[#This Row],[Code]],'Industry Profile'!$B$18:$B$27,'Industry Profile'!$C$18:$C$27) -> Chino Pants | D11: 2 | E11: {=INDEX('Industry Profile'!$C$12:$C$14,tblProducts[[#This Row],[Category Group]])} -> Apparel & Footwear | F11: =IP_Unit -> pcs | G11: 150000 | H11: 88000 | I11: =IFERROR(1-tblProducts[[#This Row],[Unit Cost]]/tblProducts[[#This Row],[Selling Price (excl. VAT)]],0) -> 0.41333333 | J11: =SUMIFS(tblSales[Qty],tblSales[Product Code],tblProducts[[#This Row],[Code]],tblSales[Date],"<="&PEnd) -> 9809 | K11: =SUMIFS(tblSales[DPP (excl. VAT)],tblSales[Product Code],tblProducts[[#This Row],[Code]],tblSales[Date],"<="&PEnd) -> 1471350000
B12: P06 | C12: =_xlfn.XLOOKUP("Product "&tblProducts[[#This Row],[Code]],'Industry Profile'!$B$18:$B$27,'Industry Profile'!$C$18:$C$27) -> Sneakers | D12: 2 | E12: {=INDEX('Industry Profile'!$C$12:$C$14,tblProducts[[#This Row],[Category Group]])} -> Apparel & Footwear | F12: =IP_Unit -> pcs | G12: 250000 | H12: 155000 | I12: =IFERROR(1-tblProducts[[#This Row],[Unit Cost]]/tblProducts[[#This Row],[Selling Price (excl. VAT)]],0) -> 0.38 | J12: =SUMIFS(tblSales[Qty],tblSales[Product Code],tblProducts[[#This Row],[Code]],tblSales[Date],"<="&PEnd) -> 4142 | K12: =SUMIFS(tblSales[DPP (excl. VAT)],tblSales[Product Code],tblProducts[[#This Row],[Code]],tblSales[Date],"<="&PEnd) -> 1035500000 | O12: Payment Method | P12: Account Code
B13: P07 | C13: =_xlfn.XLOOKUP("Product "&tblProducts[[#This Row],[Code]],'Industry Profile'!$B$18:$B$27,'Industry Profile'!$C$18:$C$27) -> Bomber Jacket | D13: 2 | E13: {=INDEX('Industry Profile'!$C$12:$C$14,tblProducts[[#This Row],[Category Group]])} -> Apparel & Footwear | F13: =IP_Unit -> pcs | G13: 350000 | H13: 210000 | I13: =IFERROR(1-tblProducts[[#This Row],[Unit Cost]]/tblProducts[[#This Row],[Selling Price (excl. VAT)]],0) -> 0.4 | J13: =SUMIFS(tblSales[Qty],tblSales[Product Code],tblProducts[[#This Row],[Code]],tblSales[Date],"<="&PEnd) -> 3306 | K13: =SUMIFS(tblSales[DPP (excl. VAT)],tblSales[Product Code],tblProducts[[#This Row],[Code]],tblSales[Date],"<="&PEnd) -> 1157100000 | O13: Cash | P13: 1110
B14: P08 | C14: =_xlfn.XLOOKUP("Product "&tblProducts[[#This Row],[Code]],'Industry Profile'!$B$18:$B$27,'Industry Profile'!$C$18:$C$27) -> Backpack | D14: 3 | E14: {=INDEX('Industry Profile'!$C$12:$C$14,tblProducts[[#This Row],[Category Group]])} -> Bags & Gadgets | F14: =IP_Unit -> pcs | G14: 500000 | H14: 290000 | I14: =IFERROR(1-tblProducts[[#This Row],[Unit Cost]]/tblProducts[[#This Row],[Selling Price (excl. VAT)]],0) -> 0.42 | J14: =SUMIFS(tblSales[Qty],tblSales[Product Code],tblProducts[[#This Row],[Code]],tblSales[Date],"<="&PEnd) -> 2531 | K14: =SUMIFS(tblSales[DPP (excl. VAT)],tblSales[Product Code],tblProducts[[#This Row],[Code]],tblSales[Date],"<="&PEnd) -> 1265500000 | O14: QRIS / Transfer | P14: 1120
B15: P09 | C15: =_xlfn.XLOOKUP("Product "&tblProducts[[#This Row],[Code]],'Industry Profile'!$B$18:$B$27,'Industry Profile'!$C$18:$C$27) -> Smartwatch | D15: 3 | E15: {=INDEX('Industry Profile'!$C$12:$C$14,tblProducts[[#This Row],[Category Group]])} -> Bags & Gadgets | F15: =IP_Unit -> pcs | G15: 850000 | H15: 560000 | I15: =IFERROR(1-tblProducts[[#This Row],[Unit Cost]]/tblProducts[[#This Row],[Selling Price (excl. VAT)]],0) -> 0.34117647 | J15: =SUMIFS(tblSales[Qty],tblSales[Product Code],tblProducts[[#This Row],[Code]],tblSales[Date],"<="&PEnd) -> 1080 | K15: =SUMIFS(tblSales[DPP (excl. VAT)],tblSales[Product Code],tblProducts[[#This Row],[Code]],tblSales[Date],"<="&PEnd) -> 918000000 | O15: Credit (Term) | P15: 1210
B16: P10 | C16: =_xlfn.XLOOKUP("Product "&tblProducts[[#This Row],[Code]],'Industry Profile'!$B$18:$B$27,'Industry Profile'!$C$18:$C$27) -> Wireless Earbuds Pro | D16: 3 | E16: {=INDEX('Industry Profile'!$C$12:$C$14,tblProducts[[#This Row],[Category Group]])} -> Bags & Gadgets | F16: =IP_Unit -> pcs | G16: 1250000 | H16: 820000 | I16: =IFERROR(1-tblProducts[[#This Row],[Unit Cost]]/tblProducts[[#This Row],[Selling Price (excl. VAT)]],0) -> 0.344 | J16: =SUMIFS(tblSales[Qty],tblSales[Product Code],tblProducts[[#This Row],[Code]],tblSales[Date],"<="&PEnd) -> 1115 | K16: =SUMIFS(tblSales[DPP (excl. VAT)],tblSales[Product Code],tblProducts[[#This Row],[Code]],tblSales[Date],"<="&PEnd) -> 1393750000

Sheet Sales
B2: 🏠 HOME | D2: ◀ PREV | G2: NEXT ▶ | I2: ☰ MENU | L2: Journal | N2: Trial Bal. | P2: Income St. | S2: Balance Sh. | V2: Tax Recon | Y2: Bank Recon | AB2: Controls
B4: SALES SUB-LEDGER (DAILY INVOICE LINES)
B5: Blue = inputs. Prices, VAT (12% × DPP 11/12) and COGS calculate automatically. Monthly totals post to the General Journal (Source = Auto-Sales).
B6: Date | C6: Invoice No | D6: Customer ID | E6: Customer Name | F6: Product Code | G6: Product / Service | H6: Category | I6: Qty | J6: Unit Price | K6: DPP (excl. VAT) | L6: Output VAT | M6: Total incl. VAT | N6: COGS | O6: Payment Method | P6: Channel Code | Q6: Channel | R6: Month
B7: 46023 | C7: INV-2601-0001 | D7: C000 | E7: =_xlfn.XLOOKUP(tblSales[[#This Row],[Customer ID]],tblCustomers[Customer ID],tblCustomers[Customer Name],"⚠ Unknown") -> Walk-in Customer | F7: P01 | G7: =_xlfn.XLOOKUP(tblSales[[#This Row],[Product Code]],tblProducts[Code],tblProducts[Product / Service Name],"⚠ Unknown") -> Socks & Accessories | H7: =_xlfn.XLOOKUP(tblSales[[#This Row],[Product Code]],tblProducts[Code],tblProducts[Category],"") -> Accessories & Basics | I7: 5 | J7: =_xlfn.XLOOKUP(tblSales[[#This Row],[Product Code]],tblProducts[Code],tblProducts[Selling Price (excl. VAT)],0) -> 45000 | K7: =tblSales[[#This Row],[Qty]]*tblSales[[#This Row],[Unit Price]] -> 225000 | L7: =ROUND(tblSales[[#This Row],[DPP (excl. VAT)]]*VATEff,0) -> 24750 | M7: =tblSales[[#This Row],[DPP (excl. VAT)]]+tblSales[[#This Row],[Output VAT]] -> 249750 | N7: =tblSales[[#This Row],[Qty]]*_xlfn.XLOOKUP(tblSales[[#This Row],[Product Code]],tblProducts[Code],tblProducts[Unit Cost],0) -> 120000 | O7: QRIS / Transfer | P7: CH3 | Q7: =_xlfn.XLOOKUP(tblSales[[#This Row],[Channel Code]],tblChannels[Channel Code],tblChannels[Channel Name],"") -> Website & Social Media | R7: =MONTH(tblSales[[#This Row],[Date]]) -> 1
B8: 46023 | C8: INV-2601-0001 | D8: C000 | E8: =_xlfn.XLOOKUP(tblSales[[#This Row],[Customer ID]],tblCustomers[Customer ID],tblCustomers[Customer Name],"⚠ Unknown") -> Walk-in Customer | F8: P03 | G8: =_xlfn.XLOOKUP(tblSales[[#This Row],[Product Code]],tblProducts[Code],tblProducts[Product / Service Name],"⚠ Unknown") -> Casual Shorts | H8: =_xlfn.XLOOKUP(tblSales[[#This Row],[Product Code]],tblProducts[Code],tblProducts[Category],"") -> Accessories & Basics | I8: 1 | J8: =_xlfn.XLOOKUP(tblSales[[#This Row],[Product Code]],tblProducts[Code],tblProducts[Selling Price (excl. VAT)],0) -> 85000 | K8: =tblSales[[#This Row],[Qty]]*tblSales[[#This Row],[Unit Price]] -> 85000 | L8: =ROUND(tblSales[[#This Row],[DPP (excl. VAT)]]*VATEff,0) -> 9350 | M8: =tblSales[[#This Row],[DPP (excl. VAT)]]+tblSales[[#This Row],[Output VAT]] -> 94350 | N8: =tblSales[[#This Row],[Qty]]*_xlfn.XLOOKUP(tblSales[[#This Row],[Product Code]],tblProducts[Code],tblProducts[Unit Cost],0) -> 50000 | O8: QRIS / Transfer | P8: CH3 | Q8: =_xlfn.XLOOKUP(tblSales[[#This Row],[Channel Code]],tblChannels[Channel Code],tblChannels[Channel Name],"") -> Website & Social Media | R8: =MONTH(tblSales[[#This Row],[Date]]) -> 1
B9: 46023 | C9: INV-2601-0002 | D9: C002 | E9: =_xlfn.XLOOKUP(tblSales[[#This Row],[Customer ID]],tblCustomers[Customer ID],tblCustomers[Customer Name],"⚠ Unknown") -> PT Bintang Timur Sejahtera | F9: P02 | G9: =_xlfn.XLOOKUP(tblSales[[#This Row],[Product Code]],tblProducts[Code],tblProducts[Product / Service Name],"⚠ Unknown") -> Premium Basic T-shirt | H9: =_xlfn.XLOOKUP(tblSales[[#This Row],[Product Code]],tblProducts[Code],tblProducts[Category],"") -> Accessories & Basics | I9: 80 | J9: =_xlfn.XLOOKUP(tblSales[[#This Row],[Product Code]],tblProducts[Code],tblProducts[Selling Price (excl. VAT)],0) -> 65000 | K9: =tblSales[[#This Row],[Qty]]*tblSales[[#This Row],[Unit Price]] -> 5200000 | L9: =ROUND(tblSales[[#This Row],[DPP (excl. VAT)]]*VATEff,0) -> 572000 | M9: =tblSales[[#This Row],[DPP (excl. VAT)]]+tblSales[[#This Row],[Output VAT]] -> 5772000 | N9: =tblSales[[#This Row],[Qty]]*_xlfn.XLOOKUP(tblSales[[#This Row],[Product Code]],tblProducts[Code],tblProducts[Unit Cost],0) -> 2960000 | O9: Credit (Term) | P9: CH1 | Q9: =_xlfn.XLOOKUP(tblSales[[#This Row],[Channel Code]],tblChannels[Channel Code],tblChannels[Channel Name],"") -> In-store | R9: =MONTH(tblSales[[#This Row],[Date]]) -> 1
B10: 46023 | C10: INV-2601-0003 | D10: C004 | E10: =_xlfn.XLOOKUP(tblSales[[#This Row],[Customer ID]],tblCustomers[Customer ID],tblCustomers[Customer Name],"⚠ Unknown") -> PT Graha Nusa Persada | F10: P02 | G10: =_xlfn.XLOOKUP(tblSales[[#This Row],[Product Code]],tblProducts[Code],tblProducts[Product / Service Name],"⚠ Unknown") -> Premium Basic T-shirt | H10: =_xlfn.XLOOKUP(tblSales[[#This Row],[Product Code]],tblProducts[Code],tblProducts[Category],"") -> Accessories & Basics | I10: 96 | J10: =_xlfn.XLOOKUP(tblSales[[#This Row],[Product Code]],tblProducts[Code],tblProducts[Selling Price (excl. VAT)],0) -> 65000 | K10: =tblSales[[#This Row],[Qty]]*tblSales[[#This Row],[Unit Price]] -> 6240000 | L10: =ROUND(tblSales[[#This Row],[DPP (excl. VAT)]]*VATEff,0) -> 686400 | M10: =tblSales[[#This Row],[DPP (excl. VAT)]]+tblSales[[#This Row],[Output VAT]] -> 6926400 | N10: =tblSales[[#This Row],[Qty]]*_xlfn.XLOOKUP(tblSales[[#This Row],[Product Code]],tblProducts[Code],tblProducts[Unit Cost],0) -> 3552000 | O10: Credit (Term) | P10: CH1 | Q10: =_xlfn.XLOOKUP(tblSales[[#This Row],[Channel Code]],tblChannels[Channel Code],tblChannels[Channel Name],"") -> In-store | R10: =MONTH(tblSales[[#This Row],[Date]]) -> 1
B11: 46023 | C11: INV-2601-0003 | D11: C004 | E11: =_xlfn.XLOOKUP(tblSales[[#This Row],[Customer ID]],tblCustomers[Customer ID],tblCustomers[Customer Name],"⚠ Unknown") -> PT Graha Nusa Persada | F11: P03 | G11: =_xlfn.XLOOKUP(tblSales[[#This Row],[Product Code]],tblProducts[Code],tblProducts[Product / Service Name],"⚠ Unknown") -> Casual Shorts | H11: =_xlfn.XLOOKUP(tblSales[[#This Row],[Product Code]],tblProducts[Code],tblProducts[Category],"") -> Accessories & Basics | I11: 80 | J11: =_xlfn.XLOOKUP(tblSales[[#This Row],[Product Code]],tblProducts[Code],tblProducts[Selling Price (excl. VAT)],0) -> 85000 | K11: =tblSales[[#This Row],[Qty]]*tblSales[[#This Row],[Unit Price]] -> 6800000 | L11: =ROUND(tblSales[[#This Row],[DPP (excl. VAT)]]*VATEff,0) -> 748000 | M11: =tblSales[[#This Row],[DPP (excl. VAT)]]+tblSales[[#This Row],[Output VAT]] -> 7548000 | N11: =tblSales[[#This Row],[Qty]]*_xlfn.XLOOKUP(tblSales[[#This Row],[Product Code]],tblProducts[Code],tblProducts[Unit Cost],0) -> 4000000 | O11: Credit (Term) | P11: CH1 | Q11: =_xlfn.XLOOKUP(tblSales[[#This Row],[Channel Code]],tblChannels[Channel Code],tblChannels[Channel Name],"") -> In-store | R11: =MONTH(tblSales[[#This Row],[Date]]) -> 1
B12: 46023 | C12: INV-2601-0004 | D12: C000 | E12: =_xlfn.XLOOKUP(tblSales[[#This Row],[Customer ID]],tblCustomers[Customer ID],tblCustomers[Customer Name],"⚠ Unknown") -> Walk-in Customer | F12: P06 | G12: =_xlfn.XLOOKUP(tblSales[[#This Row],[Product Code]],tblProducts[Code],tblProducts[Product / Service Name],"⚠ Unknown") -> Sneakers | H12: =_xlfn.XLOOKUP(tblSales[[#This Row],[Product Code]],tblProducts[Code],tblProducts[Category],"") -> Apparel & Footwear | I12: 3 | J12: =_xlfn.XLOOKUP(tblSales[[#This Row],[Product Code]],tblProducts[Code],tblProducts[Selling Price (excl. VAT)],0) -> 250000 | K12: =tblSales[[#This Row],[Qty]]*tblSales[[#This Row],[Unit Price]] -> 750000 | L12: =ROUND(tblSales[[#This Row],[DPP (excl. VAT)]]*VATEff,0) -> 82500 | M12: =tblSales[[#This Row],[DPP (excl. VAT)]]+tblSales[[#This Row],[Output VAT]] -> 832500 | N12: =tblSales[[#This Row],[Qty]]*_xlfn.XLOOKUP(tblSales[[#This Row],[Product Code]],tblProducts[Code],tblProducts[Unit Cost],0) -> 465000 | O12: Cash | P12: CH1 | Q12: =_xlfn.XLOOKUP(tblSales[[#This Row],[Channel Code]],tblChannels[Channel Code],tblChannels[Channel Name],"") -> In-store | R12: =MONTH(tblSales[[#This Row],[Date]]) -> 1
B13: 46023 | C13: INV-2601-0005 | D13: C000 | E13: =_xlfn.XLOOKUP(tblSales[[#This Row],[Customer ID]],tblCustomers[Customer ID],tblCustomers[Customer Name],"⚠ Unknown") -> Walk-in Customer | F13: P02 | G13: =_xlfn.XLOOKUP(tblSales[[#This Row],[Product Code]],tblProducts[Code],tblProducts[Product / Service Name],"⚠ Unknown") -> Premium Basic T-shirt | H13: =_xlfn.XLOOKUP(tblSales[[#This Row],[Product Code]],tblProducts[Code],tblProducts[Category],"") -> Accessories & Basics | I13: 4 | J13: =_xlfn.XLOOKUP(tblSales[[#This Row],[Product Code]],tblProducts[Code],tblProducts[Selling Price (excl. VAT)],0) -> 65000 | K13: =tblSales[[#This Row],[Qty]]*tblSales[[#This Row],[Unit Price]] -> 260000 | L13: =ROUND(tblSales[[#This Row],[DPP (excl. VAT)]]*VATEff,0) -> 28600 | M13: =tblSales[[#This Row],[DPP (excl. VAT)]]+tblSales[[#This Row],[Output VAT]] -> 288600 | N13: =tblSales[[#This Row],[Qty]]*_xlfn.XLOOKUP(tblSales[[#This Row],[Product Code]],tblProducts[Code],tblProducts[Unit Cost],0) -> 148000 | O13: Cash | P13: CH1 | Q13: =_xlfn.XLOOKUP(tblSales[[#This Row],[Channel Code]],tblChannels[Channel Code],tblChannels[Channel Name],"") -> In-store | R13: =MONTH(tblSales[[#This Row],[Date]]) -> 1
B14: 46023 | C14: INV-2601-0006 | D14: C000 | E14: =_xlfn.XLOOKUP(tblSales[[#This Row],[Customer ID]],tblCustomers[Customer ID],tblCustomers[Customer Name],"⚠ Unknown") -> Walk-in Customer | F14: P03 | G14: =_xlfn.XLOOKUP(tblSales[[#This Row],[Product Code]],tblProducts[Code],tblProducts[Product / Service Name],"⚠ Unknown") -> Casual Shorts | H14: =_xlfn.XLOOKUP(tblSales[[#This Row],[Product Code]],tblProducts[Code],tblProducts[Category],"") -> Accessories & Basics | I14: 7 | J14: =_xlfn.XLOOKUP(tblSales[[#This Row],[Product Code]],tblProducts[Code],tblProducts[Selling Price (excl. VAT)],0) -> 85000 | K14: =tblSales[[#This Row],[Qty]]*tblSales[[#This Row],[Unit Price]] -> 595000 | L14: =ROUND(tblSales[[#This Row],[DPP (excl. VAT)]]*VATEff,0) -> 65450 | M14: =tblSales[[#This Row],[DPP (excl. VAT)]]+tblSales[[#This Row],[Output VAT]] -> 660450 | N14: =tblSales[[#This Row],[Qty]]*_xlfn.XLOOKUP(tblSales[[#This Row],[Product Code]],tblProducts[Code],tblProducts[Unit Cost],0) -> 350000 | O14: Cash | P14: CH1 | Q14: =_xlfn.XLOOKUP(tblSales[[#This Row],[Channel Code]],tblChannels[Channel Code],tblChannels[Channel Name],"") -> In-store | R14: =MONTH(tblSales[[#This Row],[Date]]) -> 1
B15: 46023 | C15: INV-2601-0007 | D15: C001 | E15: =_xlfn.XLOOKUP(tblSales[[#This Row],[Customer ID]],tblCustomers[Customer ID],tblCustomers[Customer Name],"⚠ Unknown") -> PT Cahaya Abadi Makmur | F15: P03 | G15: =_xlfn.XLOOKUP(tblSales[[#This Row],[Product Code]],tblProducts[Code],tblProducts[Product / Service Name],"⚠ Unknown") -> Casual Shorts | H15: =_xlfn.XLOOKUP(tblSales[[#This Row],[Product Code]],tblProducts[Code],tblProducts[Category],"") -> Accessories & Basics | I15: 32 | J15: =_xlfn.XLOOKUP(tblSales[[#This Row],[Product Code]],tblProducts[Code],tblProducts[Selling Price (excl. VAT)],0) -> 85000 | K15: =tblSales[[#This Row],[Qty]]*tblSales[[#This Row],[Unit Price]] -> 2720000 | L15: =ROUND(tblSales[[#This Row],[DPP (excl. VAT)]]*VATEff,0) -> 299200 | M15: =tblSales[[#This Row],[DPP (excl. VAT)]]+tblSales[[#This Row],[Output VAT]] -> 3019200 | N15: =tblSales[[#This Row],[Qty]]*_xlfn.XLOOKUP(tblSales[[#This Row],[Product Code]],tblProducts[Code],tblProducts[Unit Cost],0) -> 1600000 | O15: Credit (Term) | P15: CH1 | Q15: =_xlfn.XLOOKUP(tblSales[[#This Row],[Channel Code]],tblChannels[Channel Code],tblChannels[Channel Name],"") -> In-store | R15: =MONTH(tblSales[[#This Row],[Date]]) -> 1
B16: 46023 | C16: INV-2601-0007 | D16: C001 | E16: =_xlfn.XLOOKUP(tblSales[[#This Row],[Customer ID]],tblCustomers[Customer ID],tblCustomers[Customer Name],"⚠ Unknown") -> PT Cahaya Abadi Makmur | F16: P01 | G16: =_xlfn.XLOOKUP(tblSales[[#This Row],[Product Code]],tblProducts[Code],tblProducts[Product / Service Name],"⚠ Unknown") -> Socks & Accessories | H16: =_xlfn.XLOOKUP(tblSales[[#This Row],[Product Code]],tblProducts[Code],tblProducts[Category],"") -> Accessories & Basics | I16: 16 | J16: =_xlfn.XLOOKUP(tblSales[[#This Row],[Product Code]],tblProducts[Code],tblProducts[Selling Price (excl. VAT)],0) -> 45000 | K16: =tblSales[[#This Row],[Qty]]*tblSales[[#This Row],[Unit Price]] -> 720000 | L16: =ROUND(tblSales[[#This Row],[DPP (excl. VAT)]]*VATEff,0) -> 79200 | M16: =tblSales[[#This Row],[DPP (excl. VAT)]]+tblSales[[#This Row],[Output VAT]] -> 799200 | N16: =tblSales[[#This Row],[Qty]]*_xlfn.XLOOKUP(tblSales[[#This Row],[Product Code]],tblProducts[Code],tblProducts[Unit Cost],0) -> 384000 | O16: Credit (Term) | P16: CH1 | Q16: =_xlfn.XLOOKUP(tblSales[[#This Row],[Channel Code]],tblChannels[Channel Code],tblChannels[Channel Name],"") -> In-store | R16: =MONTH(tblSales[[#This Row],[Date]]) -> 1
B17: 46023 | C17: INV-2601-0008 | D17: C000 | E17: =_xlfn.XLOOKUP(tblSales[[#This Row],[Customer ID]],tblCustomers[Customer ID],tblCustomers[Customer Name],"⚠ Unknown") -> Walk-in Customer | F17: P08 | G17: =_xlfn.XLOOKUP(tblSales[[#This Row],[Product Code]],tblProducts[Code],tblProducts[Product / Service Name],"⚠ Unknown") -> Backpack | H17: =_xlfn.XLOOKUP(tblSales[[#This Row],[Product Code]],tblProducts[Code],tblProducts[Category],"") -> Bags & Gadgets | I17: 1 | J17: =_xlfn.XLOOKUP(tblSales[[#This Row],[Product Code]],tblProducts[Code],tblProducts[Selling Price (excl. VAT)],0) -> 500000 | K17: =tblSales[[#This Row],[Qty]]*tblSales[[#This Row],[Unit Price]] -> 500000 | L17: =ROUND(tblSales[[#This Row],[DPP (excl. VAT)]]*VATEff,0) -> 55000 | M17: =tblSales[[#This Row],[DPP (excl. VAT)]]+tblSales[[#This Row],[Output VAT]] -> 555000 | N17: =tblSales[[#This Row],[Qty]]*_xlfn.XLOOKUP(tblSales[[#This Row],[Product Code]],tblProducts[Code],tblProducts[Unit Cost],0) -> 290000 | O17: Cash | P17: CH1 | Q17: =_xlfn.XLOOKUP(tblSales[[#This Row],[Channel Code]],tblChannels[Channel Code],tblChannels[Channel Name],"") -> In-store | R17: =MONTH(tblSales[[#This Row],[Date]]) -> 1
B18: 46023 | C18: INV-2601-0009 | D18: C000 | E18: =_xlfn.XLOOKUP(tblSales[[#This Row],[Customer ID]],tblCustomers[Customer ID],tblCustomers[Customer Name],"⚠ Unknown") -> Walk-in Customer | F18: P01 | G18: =_xlfn.XLOOKUP(tblSales[[#This Row],[Product Code]],tblProducts[Code],tblProducts[Product / Service Name],"⚠ Unknown") -> Socks & Accessories | H18: =_xlfn.XLOOKUP(tblSales[[#This Row],[Product Code]],tblProducts[Code],tblProducts[Category],"") -> Accessories & Basics | I18: 3 | J18: =_xlfn.XLOOKUP(tblSales[[#This Row],[Product Code]],tblProducts[Code],tblProducts[Selling Price (excl. VAT)],0) -> 45000 | K18: =tblSales[[#This Row],[Qty]]*tblSales[[#This Row],[Unit Price]] -> 135000 | L18: =ROUND(tblSales[[#This Row],[DPP (excl. VAT)]]*VATEff,0) -> 14850 | M18: =tblSales[[#This Row],[DPP (excl. VAT)]]+tblSales[[#This Row],[Output VAT]] -> 149850 | N18: =tblSales[[#This Row],[Qty]]*_xlfn.XLOOKUP(tblSales[[#This Row],[Product Code]],tblProducts[Code],tblProducts[Unit Cost],0) -> 72000 | O18: Cash | P18: CH1 | Q18: =_xlfn.XLOOKUP(tblSales[[#This Row],[Channel Code]],tblChannels[Channel Code],tblChannels[Channel Name],"") -> In-store | R18: =MONTH(tblSales[[#This Row],[Date]]) -> 1
... B6196: 46387 | C6196: INV-2612-0476 | D6196: C000 | E6196: =_xlfn.XLOOKUP(tblSales[[#This Row],[Customer ID]],tblCustomers[Customer ID],tblCustomers[Customer Name],"⚠ Unknown") -> Walk-in Customer | F6196: P03 | G6196: =_xlfn.XLOOKUP(tblSales[[#This Row],[Product Code]],tblProducts[Code],tblProducts[Product / Service Name],"⚠ Unknown") -> Casual Shorts | H6196: =_xlfn.XLOOKUP(tblSales[[#This Row],[Product Code]],tblProducts[Code],tblProducts[Category],"") -> Accessories & Basics | I6196: 12 | J6196: =_xlfn.XLOOKUP(tblSales[[#This Row],[Product Code]],tblProducts[Code],tblProducts[Selling Price (excl. VAT)],0) -> 85000 | K6196: =tblSales[[#This Row],[Qty]]*tblSales[[#This Row],[Unit Price]] -> 1020000 | L6196: =ROUND(tblSales[[#This Row],[DPP (excl. VAT)]]*VATEff,0) -> 112200 | M6196: =tblSales[[#This Row],[DPP (excl. VAT)]]+tblSales[[#This Row],[Output VAT]] -> 1132200 | N6196: =tblSales[[#This Row],[Qty]]*_xlfn.XLOOKUP(tblSales[[#This Row],[Product Code]],tblProducts[Code],tblProducts[Unit Cost],0) -> 600000 | O6196: Cash | P6196: CH1 | Q6196: =_xlfn.XLOOKUP(tblSales[[#This Row],[Channel Code]],tblChannels[Channel Code],tblChannels[Channel Name],"") -> In-store | R6196: =MONTH(tblSales[[#This Row],[Date]]) -> 12

Sheet Purchases
B2: 🏠 HOME | D2: ◀ PREV | G2: NEXT ▶ | J2: ☰ MENU | L2: Journal | O2: Trial Bal. | Q2: Income St. | T2: Balance Sh. | W2: Tax Recon | Z2: Bank Recon | AC2: Controls
B4: PURCHASES & EXPENSES SUB-LEDGER (VENDOR BILLS)
B5: Input VAT follows vendor VAT status; PPh Unifikasi (Art. 23 / 4(2)) follows vendor WHT type. Bills post monthly (Auto-Purchases); payments post by Pay Month (Auto-Payments).
B6: Date | C6: Bill No | D6: Vendor ID | E6: Vendor Name | F6: Description | G6: Account Code | H6: Account Name | I6: DPP (excl. VAT) | J6: Input VAT | K6: WHT Type | L6: WHT Rate | M6: WHT Amount | N6: Total Payable | O6: Payment Date | P6: Paid From | Q6: Month | R6: Pay Month
B7: 46027 | C7: BILL-2601-001 | D7: V001 | E7: =_xlfn.XLOOKUP(tblPurchases[[#This Row],[Vendor ID]],tblVendors[Vendor ID],tblVendors[Vendor Name],"⚠ Unknown") -> PT Sumber Barang Utama | F7: Merchandise purchase - Jan batch 1 | G7: 1310 | H7: =_xlfn.XLOOKUP(tblPurchases[[#This Row],[Account Code]],tblCOA[Code],tblCOA[Account Name],"⚠ Invalid") -> Merchandise inventory | I7: 323463000 | J7: =IF(_xlfn.XLOOKUP(tblPurchases[[#This Row],[Vendor ID]],tblVendors[Vendor ID],tblVendors[VAT Status],"")="PKP",ROUND(tblPurchases[[#This Row],[DPP (excl. VAT)]]*VATEff,0),0) -> 35580930 | K7: =_xlfn.XLOOKUP(tblPurchases[[#This Row],[Vendor ID]],tblVendors[Vendor ID],tblVendors[WHT Type],"None") -> None | L7: =_xlfn.XLOOKUP(tblPurchases[[#This Row],[WHT Type]],WHTTypes,WHTRates,0) -> 0 | M7: =ROUND(tblPurchases[[#This Row],[DPP (excl. VAT)]]*tblPurchases[[#This Row],[WHT Rate]],0) -> 0 | N7: =tblPurchases[[#This Row],[DPP (excl. VAT)]]+tblPurchases[[#This Row],[Input VAT]]-tblPurchases[[#This Row],[WHT Amount]] -> 359043930 | O7: 46057 | P7: 1120 | Q7: =MONTH(tblPurchases[[#This Row],[Date]]) -> 1 | R7: =IF(tblPurchases[[#This Row],[Payment Date]]="",0,IF(YEAR(tblPurchases[[#This Row],[Payment Date]])=FYear,MONTH(tblPurchases[[#This Row],[Payment Date]]),0)) -> 2
B8: 46027 | C8: BILL-2601-002 | D8: V009 | E8: =_xlfn.XLOOKUP(tblPurchases[[#This Row],[Vendor ID]],tblVendors[Vendor ID],tblVendors[Vendor Name],"⚠ Unknown") -> PT Utilitas Listrik & Telekom | F8: Electricity, water & internet - Jan | G8: 6230 | H8: =_xlfn.XLOOKUP(tblPurchases[[#This Row],[Account Code]],tblCOA[Code],tblCOA[Account Name],"⚠ Invalid") -> Utilities & Telecommunication | I8: 11103000 | J8: =IF(_xlfn.XLOOKUP(tblPurchases[[#This Row],[Vendor ID]],tblVendors[Vendor ID],tblVendors[VAT Status],"")="PKP",ROUND(tblPurchases[[#This Row],[DPP (excl. VAT)]]*VATEff,0),0) -> 1221330 | K8: =_xlfn.XLOOKUP(tblPurchases[[#This Row],[Vendor ID]],tblVendors[Vendor ID],tblVendors[WHT Type],"None") -> None | L8: =_xlfn.XLOOKUP(tblPurchases[[#This Row],[WHT Type]],WHTTypes,WHTRates,0) -> 0 | M8: =ROUND(tblPurchases[[#This Row],[DPP (excl. VAT)]]*tblPurchases[[#This Row],[WHT Rate]],0) -> 0 | N8: =tblPurchases[[#This Row],[DPP (excl. VAT)]]+tblPurchases[[#This Row],[Input VAT]]-tblPurchases[[#This Row],[WHT Amount]] -> 12324330 | O8: 46042 | P8: 1120 | Q8: =MONTH(tblPurchases[[#This Row],[Date]]) -> 1 | R8: =IF(tblPurchases[[#This Row],[Payment Date]]="",0,IF(YEAR(tblPurchases[[#This Row],[Payment Date]])=FYear,MONTH(tblPurchases[[#This Row],[Payment Date]]),0)) -> 1
B9: 46030 | C9: BILL-2601-003 | D9: V006 | E9: =_xlfn.XLOOKUP(tblPurchases[[#This Row],[Vendor ID]],tblVendors[Vendor ID],tblVendors[Vendor Name],"⚠ Unknown") -> PT Cloud Software Indonesia | F9: Microsoft 365 Business - annual subscription (PP-007) | G9: 1430 | H9: =_xlfn.XLOOKUP(tblPurchases[[#This Row],[Account Code]],tblCOA[Code],tblCOA[Account Name],"⚠ Invalid") -> Prepaid Software Subscriptions | I9: 18000000 | J9: =IF(_xlfn.XLOOKUP(tblPurchases[[#This Row],[Vendor ID]],tblVendors[Vendor ID],tblVendors[VAT Status],"")="PKP",ROUND(tblPurchases[[#This Row],[DPP (excl. VAT)]]*VATEff,0),0) -> 1980000 | K9: =_xlfn.XLOOKUP(tblPurchases[[#This Row],[Vendor ID]],tblVendors[Vendor ID],tblVendors[WHT Type],"None") -> Art. 23 - Services | L9: =_xlfn.XLOOKUP(tblPurchases[[#This Row],[WHT Type]],WHTTypes,WHTRates,0) -> 0.02 | M9: =ROUND(tblPurchases[[#This Row],[DPP (excl. VAT)]]*tblPurchases[[#This Row],[WHT Rate]],0) -> 360000 | N9: =tblPurchases[[#This Row],[DPP (excl. VAT)]]+tblPurchases[[#This Row],[Input VAT]]-tblPurchases[[#This Row],[WHT Amount]] -> 19620000 | O9: 46037 | P9: 1120 | Q9: =MONTH(tblPurchases[[#This Row],[Date]]) -> 1 | R9: =IF(tblPurchases[[#This Row],[Payment Date]]="",0,IF(YEAR(tblPurchases[[#This Row],[Payment Date]])=FYear,MONTH(tblPurchases[[#This Row],[Payment Date]]),0)) -> 1
B10: 46032 | C10: BILL-2601-004 | D10: V012 | E10: =_xlfn.XLOOKUP(tblPurchases[[#This Row],[Vendor ID]],tblVendors[Vendor ID],tblVendors[Vendor Name],"⚠ Unknown") -> Toko ATK Sentosa | F10: Office supplies - Jan | G10: 6270 | H10: =_xlfn.XLOOKUP(tblPurchases[[#This Row],[Account Code]],tblCOA[Code],tblCOA[Account Name],"⚠ Invalid") -> Office Supplies | I10: 2692000 | J10: =IF(_xlfn.XLOOKUP(tblPurchases[[#This Row],[Vendor ID]],tblVendors[Vendor ID],tblVendors[VAT Status],"")="PKP",ROUND(tblPurchases[[#This Row],[DPP (excl. VAT)]]*VATEff,0),0) -> 0 | K10: =_xlfn.XLOOKUP(tblPurchases[[#This Row],[Vendor ID]],tblVendors[Vendor ID],tblVendors[WHT Type],"None") -> None | L10: =_xlfn.XLOOKUP(tblPurchases[[#This Row],[WHT Type]],WHTTypes,WHTRates,0) -> 0 | M10: =ROUND(tblPurchases[[#This Row],[DPP (excl. VAT)]]*tblPurchases[[#This Row],[WHT Rate]],0) -> 0 | N10: =tblPurchases[[#This Row],[DPP (excl. VAT)]]+tblPurchases[[#This Row],[Input VAT]]-tblPurchases[[#This Row],[WHT Amount]] -> 2692000 | O10: 46032 | P10: 1120 | Q10: =MONTH(tblPurchases[[#This Row],[Date]]) -> 1 | R10: =IF(tblPurchases[[#This Row],[Payment Date]]="",0,IF(YEAR(tblPurchases[[#This Row],[Payment Date]])=FYear,MONTH(tblPurchases[[#This Row],[Payment Date]]),0)) -> 1
B11: 46034 | C11: BILL-2601-005 | D11: V002 | E11: =_xlfn.XLOOKUP(tblPurchases[[#This Row],[Vendor ID]],tblVendors[Vendor ID],tblVendors[Vendor Name],"⚠ Unknown") -> PT Prima Supply Nusantara | F11: Merchandise purchase - Jan batch 2 | G11: 1310 | H11: =_xlfn.XLOOKUP(tblPurchases[[#This Row],[Account Code]],tblCOA[Code],tblCOA[Account Name],"⚠ Invalid") -> Merchandise inventory | I11: 226424000 | J11: =IF(_xlfn.XLOOKUP(tblPurchases[[#This Row],[Vendor ID]],tblVendors[Vendor ID],tblVendors[VAT Status],"")="PKP",ROUND(tblPurchases[[#This Row],[DPP (excl. VAT)]]*VATEff,0),0) -> 24906640 | K11: =_xlfn.XLOOKUP(tblPurchases[[#This Row],[Vendor ID]],tblVendors[Vendor ID],tblVendors[WHT Type],"None") -> None | L11: =_xlfn.XLOOKUP(tblPurchases[[#This Row],[WHT Type]],WHTTypes,WHTRates,0) -> 0 | M11: =ROUND(tblPurchases[[#This Row],[DPP (excl. VAT)]]*tblPurchases[[#This Row],[WHT Rate]],0) -> 0 | N11: =tblPurchases[[#This Row],[DPP (excl. VAT)]]+tblPurchases[[#This Row],[Input VAT]]-tblPurchases[[#This Row],[WHT Amount]] -> 251330640 | O11: 46064 | P11: 1120 | Q11: =MONTH(tblPurchases[[#This Row],[Date]]) -> 1 | R11: =IF(tblPurchases[[#This Row],[Payment Date]]="",0,IF(YEAR(tblPurchases[[#This Row],[Payment Date]])=FYear,MONTH(tblPurchases[[#This Row],[Payment Date]]),0)) -> 2
B12: 46037 | C12: BILL-2601-006 | D12: V011 | E12: =_xlfn.XLOOKUP(tblPurchases[[#This Row],[Vendor ID]],tblVendors[Vendor ID],tblVendors[Vendor Name],"⚠ Unknown") -> CV Teknik Servis Mandiri | F12: AC & equipment maintenance - Jan | G12: 6295 | H12: =_xlfn.XLOOKUP(tblPurchases[[#This Row],[Account Code]],tblCOA[Code],tblCOA[Account Name],"⚠ Invalid") -> Repairs & Maintenance | I12: 3685000 | J12: =IF(_xlfn.XLOOKUP(tblPurchases[[#This Row],[Vendor ID]],tblVendors[Vendor ID],tblVendors[VAT Status],"")="PKP",ROUND(tblPurchases[[#This Row],[DPP (excl. VAT)]]*VATEff,0),0) -> 0 | K12: =_xlfn.XLOOKUP(tblPurchases[[#This Row],[Vendor ID]],tblVendors[Vendor ID],tblVendors[WHT Type],"None") -> Art. 23 - Services | L12: =_xlfn.XLOOKUP(tblPurchases[[#This Row],[WHT Type]],WHTTypes,WHTRates,0) -> 0.02 | M12: =ROUND(tblPurchases[[#This Row],[DPP (excl. VAT)]]*tblPurchases[[#This Row],[WHT Rate]],0) -> 73700 | N12: =tblPurchases[[#This Row],[DPP (excl. VAT)]]+tblPurchases[[#This Row],[Input VAT]]-tblPurchases[[#This Row],[WHT Amount]] -> 3611300 | O12: 46044 | P12: 1120 | Q12: =MONTH(tblPurchases[[#This Row],[Date]]) -> 1 | R12: =IF(tblPurchases[[#This Row],[Payment Date]]="",0,IF(YEAR(tblPurchases[[#This Row],[Payment Date]])=FYear,MONTH(tblPurchases[[#This Row],[Payment Date]]),0)) -> 1
B13: 46040 | C13: BILL-2601-007 | D13: V017 | E13: =_xlfn.XLOOKUP(tblPurchases[[#This Row],[Vendor ID]],tblVendors[Vendor ID],tblVendors[Vendor Name],"⚠ Unknown") -> Various Restaurants & Donations | F13: Client entertainment & donations - Jan | G13: 6296 | H13: =_xlfn.XLOOKUP(tblPurchases[[#This Row],[Account Code]],tblCOA[Code],tblCOA[Account Name],"⚠ Invalid") -> Entertainment & Donations | I13: 2449000 | J13: =IF(_xlfn.XLOOKUP(tblPurchases[[#This Row],[Vendor ID]],tblVendors[Vendor ID],tblVendors[VAT Status],"")="PKP",ROUND(tblPurchases[[#This Row],[DPP (excl. VAT)]]*VATEff,0),0) -> 0 | K13: =_xlfn.XLOOKUP(tblPurchases[[#This Row],[Vendor ID]],tblVendors[Vendor ID],tblVendors[WHT Type],"None") -> None | L13: =_xlfn.XLOOKUP(tblPurchases[[#This Row],[WHT Type]],WHTTypes,WHTRates,0) -> 0 | M13: =ROUND(tblPurchases[[#This Row],[DPP (excl. VAT)]]*tblPurchases[[#This Row],[WHT Rate]],0) -> 0 | N13: =tblPurchases[[#This Row],[DPP (excl. VAT)]]+tblPurchases[[#This Row],[Input VAT]]-tblPurchases[[#This Row],[WHT Amount]] -> 2449000 | O13: 46040 | P13: 1120 | Q13: =MONTH(tblPurchases[[#This Row],[Date]]) -> 1 | R13: =IF(tblPurchases[[#This Row],[Payment Date]]="",0,IF(YEAR(tblPurchases[[#This Row],[Payment Date]])=FYear,MONTH(tblPurchases[[#This Row],[Payment Date]]),0)) -> 1
B14: 46042 | C14: BILL-2601-008 | D14: V003 | E14: =_xlfn.XLOOKUP(tblPurchases[[#This Row],[Vendor ID]],tblVendors[Vendor ID],tblVendors[Vendor Name],"⚠ Unknown") -> CV Aneka Grosir Jaya | F14: Merchandise purchase - Jan (local) | G14: 1310 | H14: =_xlfn.XLOOKUP(tblPurchases[[#This Row],[Account Code]],tblCOA[Code],tblCOA[Account Name],"⚠ Invalid") -> Merchandise inventory | I14: 97039000 | J14: =IF(_xlfn.XLOOKUP(tblPurchases[[#This Row],[Vendor ID]],tblVendors[Vendor ID],tblVendors[VAT Status],"")="PKP",ROUND(tblPurchases[[#This Row],[DPP (excl. VAT)]]*VATEff,0),0) -> 0 | K14: =_xlfn.XLOOKUP(tblPurchases[[#This Row],[Vendor ID]],tblVendors[Vendor ID],tblVendors[WHT Type],"None") -> None | L14: =_xlfn.XLOOKUP(tblPurchases[[#This Row],[WHT Type]],WHTTypes,WHTRates,0) -> 0 | M14: =ROUND(tblPurchases[[#This Row],[DPP (excl. VAT)]]*tblPurchases[[#This Row],[WHT Rate]],0) -> 0 | N14: =tblPurchases[[#This Row],[DPP (excl. VAT)]]+tblPurchases[[#This Row],[Input VAT]]-tblPurchases[[#This Row],[WHT Amount]] -> 97039000 | O14: 46049 | P14: 1120 | Q14: =MONTH(tblPurchases[[#This Row],[Date]]) -> 1 | R14: =IF(tblPurchases[[#This Row],[Payment Date]]="",0,IF(YEAR(tblPurchases[[#This Row],[Payment Date]])=FYear,MONTH(tblPurchases[[#This Row],[Payment Date]]),0)) -> 1
B15: 46049 | C15: BILL-2601-009 | D15: V008 | E15: =_xlfn.XLOOKUP(tblPurchases[[#This Row],[Vendor ID]],tblVendors[Vendor ID],tblVendors[Vendor Name],"⚠ Unknown") -> PT Ekspedisi Cepat Nusantara | F15: Courier & delivery services - Jan | G15: 6140 | H15: =_xlfn.XLOOKUP(tblPurchases[[#This Row],[Account Code]],tblCOA[Code],tblCOA[Account Name],"⚠ Invalid") -> Shipping & Delivery | I15: 9657000 | J15: =IF(_xlfn.XLOOKUP(tblPurchases[[#This Row],[Vendor ID]],tblVendors[Vendor ID],tblVendors[VAT Status],"")="PKP",ROUND(tblPurchases[[#This Row],[DPP (excl. VAT)]]*VATEff,0),0) -> 1062270 | K15: =_xlfn.XLOOKUP(tblPurchases[[#This Row],[Vendor ID]],tblVendors[Vendor ID],tblVendors[WHT Type],"None") -> Art. 23 - Services | L15: =_xlfn.XLOOKUP(tblPurchases[[#This Row],[WHT Type]],WHTTypes,WHTRates,0) -> 0.02 | M15: =ROUND(tblPurchases[[#This Row],[DPP (excl. VAT)]]*tblPurchases[[#This Row],[WHT Rate]],0) -> 193140 | N15: =tblPurchases[[#This Row],[DPP (excl. VAT)]]+tblPurchases[[#This Row],[Input VAT]]-tblPurchases[[#This Row],[WHT Amount]] -> 10526130 | O15: 46063 | P15: 1120 | Q15: =MONTH(tblPurchases[[#This Row],[Date]]) -> 1 | R15: =IF(tblPurchases[[#This Row],[Payment Date]]="",0,IF(YEAR(tblPurchases[[#This Row],[Payment Date]])=FYear,MONTH(tblPurchases[[#This Row],[Payment Date]]),0)) -> 2
B16: 46050 | C16: BILL-2601-010 | D16: V007 | E16: =_xlfn.XLOOKUP(tblPurchases[[#This Row],[Vendor ID]],tblVendors[Vendor ID],tblVendors[Vendor Name],"⚠ Unknown") -> PT Kreasi Iklan Digital | F16: Digital advertising campaign - Jan | G16: 6120 | H16: =_xlfn.XLOOKUP(tblPurchases[[#This Row],[Account Code]],tblCOA[Code],tblCOA[Account Name],"⚠ Invalid") -> Advertising & Promotion | I16: 11803000 | J16: =IF(_xlfn.XLOOKUP(tblPurchases[[#This Row],[Vendor ID]],tblVendors[Vendor ID],tblVendors[VAT Status],"")="PKP",ROUND(tblPurchases[[#This Row],[DPP (excl. VAT)]]*VATEff,0),0) -> 1298330 | K16: =_xlfn.XLOOKUP(tblPurchases[[#This Row],[Vendor ID]],tblVendors[Vendor ID],tblVendors[WHT Type],"None") -> Art. 23 - Services | L16: =_xlfn.XLOOKUP(tblPurchases[[#This Row],[WHT Type]],WHTTypes,WHTRates,0) -> 0.02 | M16: =ROUND(tblPurchases[[#This Row],[DPP (excl. VAT)]]*tblPurchases[[#This Row],[WHT Rate]],0) -> 236060 | N16: =tblPurchases[[#This Row],[DPP (excl. VAT)]]+tblPurchases[[#This Row],[Input VAT]]-tblPurchases[[#This Row],[WHT Amount]] -> 12865270 | O16: 46080 | P16: 1120 | Q16: =MONTH(tblPurchases[[#This Row],[Date]]) -> 1 | R16: =IF(tblPurchases[[#This Row],[Payment Date]]="",0,IF(YEAR(tblPurchases[[#This Row],[Payment Date]])=FYear,MONTH(tblPurchases[[#This Row],[Payment Date]]),0)) -> 2
B17: 46053 | C17: BILL-2601-011 | D17: V013 | E17: =_xlfn.XLOOKUP(tblPurchases[[#This Row],[Vendor ID]],tblVendors[Vendor ID],tblVendors[Vendor Name],"⚠ Unknown") -> PT Marketplace Niaga Online | F17: Marketplace commission & fees - Jan | G17: 6130 | H17: =_xlfn.XLOOKUP(tblPurchases[[#This Row],[Account Code]],tblCOA[Code],tblCOA[Account Name],"⚠ Invalid") -> Marketplace & Sales Commissions | I17: 2560000 | J17: =IF(_xlfn.XLOOKUP(tblPurchases[[#This Row],[Vendor ID]],tblVendors[Vendor ID],tblVendors[VAT Status],"")="PKP",ROUND(tblPurchases[[#This Row],[DPP (excl. VAT)]]*VATEff,0),0) -> 281600 | K17: =_xlfn.XLOOKUP(tblPurchases[[#This Row],[Vendor ID]],tblVendors[Vendor ID],tblVendors[WHT Type],"None") -> Art. 23 - Services | L17: =_xlfn.XLOOKUP(tblPurchases[[#This Row],[WHT Type]],WHTTypes,WHTRates,0) -> 0.02 | M17: =ROUND(tblPurchases[[#This Row],[DPP (excl. VAT)]]*tblPurchases[[#This Row],[WHT Rate]],0) -> 51200 | N17: =tblPurchases[[#This Row],[DPP (excl. VAT)]]+tblPurchases[[#This Row],[Input VAT]]-tblPurchases[[#This Row],[WHT Amount]] -> 2790400 | O17: 46063 | P17: 1120 | Q17: =MONTH(tblPurchases[[#This Row],[Date]]) -> 1 | R17: =IF(tblPurchases[[#This Row],[Payment Date]]="",0,IF(YEAR(tblPurchases[[#This Row],[Payment Date]])=FYear,MONTH(tblPurchases[[#This Row],[Payment Date]]),0)) -> 2
B18: 46058 | C18: BILL-2602-001 | D18: V001 | E18: =_xlfn.XLOOKUP(tblPurchases[[#This Row],[Vendor ID]],tblVendors[Vendor ID],tblVendors[Vendor Name],"⚠ Unknown") -> PT Sumber Barang Utama | F18: Merchandise purchase - Feb batch 1 | G18: 1310 | H18: =_xlfn.XLOOKUP(tblPurchases[[#This Row],[Account Code]],tblCOA[Code],tblCOA[Account Name],"⚠ Invalid") -> Merchandise inventory | I18: 287374000 | J18: =IF(_xlfn.XLOOKUP(tblPurchases[[#This Row],[Vendor ID]],tblVendors[Vendor ID],tblVendors[VAT Status],"")="PKP",ROUND(tblPurchases[[#This Row],[DPP (excl. VAT)]]*VATEff,0),0) -> 31611140 | K18: =_xlfn.XLOOKUP(tblPurchases[[#This Row],[Vendor ID]],tblVendors[Vendor ID],tblVendors[WHT Type],"None") -> None | L18: =_xlfn.XLOOKUP(tblPurchases[[#This Row],[WHT Type]],WHTTypes,WHTRates,0) -> 0 | M18: =ROUND(tblPurchases[[#This Row],[DPP (excl. VAT)]]*tblPurchases[[#This Row],[WHT Rate]],0) -> 0 | N18: =tblPurchases[[#This Row],[DPP (excl. VAT)]]+tblPurchases[[#This Row],[Input VAT]]-tblPurchases[[#This Row],[WHT Amount]] -> 318985140 | O18: 46088 | P18: 1120 | Q18: =MONTH(tblPurchases[[#This Row],[Date]]) -> 2 | R18: =IF(tblPurchases[[#This Row],[Payment Date]]="",0,IF(YEAR(tblPurchases[[#This Row],[Payment Date]])=FYear,MONTH(tblPurchases[[#This Row],[Payment Date]]),0)) -> 3
... B139: 46387 | C139: BILL-2612-012 | D139: V013 | E139: =_xlfn.XLOOKUP(tblPurchases[[#This Row],[Vendor ID]],tblVendors[Vendor ID],tblVendors[Vendor Name],"⚠ Unknown") -> PT Marketplace Niaga Online | F139: Marketplace commission & fees - Dec | G139: 6130 | H139: =_xlfn.XLOOKUP(tblPurchases[[#This Row],[Account Code]],tblCOA[Code],tblCOA[Account Name],"⚠ Invalid") -> Marketplace & Sales Commissions | I139: 3707000 | J139: =IF(_xlfn.XLOOKUP(tblPurchases[[#This Row],[Vendor ID]],tblVendors[Vendor ID],tblVendors[VAT Status],"")="PKP",ROUND(tblPurchases[[#This Row],[DPP (excl. VAT)]]*VATEff,0),0) -> 407770 | K139: =_xlfn.XLOOKUP(tblPurchases[[#This Row],[Vendor ID]],tblVendors[Vendor ID],tblVendors[WHT Type],"None") -> Art. 23 - Services | L139: =_xlfn.XLOOKUP(tblPurchases[[#This Row],[WHT Type]],WHTTypes,WHTRates,0) -> 0.02 | M139: =ROUND(tblPurchases[[#This Row],[DPP (excl. VAT)]]*tblPurchases[[#This Row],[WHT Rate]],0) -> 74140 | N139: =tblPurchases[[#This Row],[DPP (excl. VAT)]]+tblPurchases[[#This Row],[Input VAT]]-tblPurchases[[#This Row],[WHT Amount]] -> 4040630 | O139: 46397 | P139: 1120 | Q139: =MONTH(tblPurchases[[#This Row],[Date]]) -> 12 | R139: =IF(tblPurchases[[#This Row],[Payment Date]]="",0,IF(YEAR(tblPurchases[[#This Row],[Payment Date]])=FYear,MONTH(tblPurchases[[#This Row],[Payment Date]]),0)) -> 0

Sheet Payroll
B2: 🏠 HOME | E2: ◀ PREV | G2: NEXT ▶ | J2: ☰ MENU | L2: Journal | N2: Trial Bal. | P2: Income St. | R2: Balance Sh. | T2: Tax Recon | V2: Bank Recon | X2: Controls
B4: PAYROLL REGISTER – PPh 21 (TER) & BPJS
B5: Salary, PTKP & department link from Employees. Monthly totals post to the General Journal (Auto-Payroll); PPh 21 & BPJS are paid on the 10th of the following month. December annualisation (Art. 17) not modelled.
B6: Period | C6: Pay Date | D6: Employee ID | E6: Employee Name | F6: Department | G6: TER Cat | H6: Basic Salary | I6: Fixed Allowance | J6: THR / Bonus | K6: Gross Salary | L6: BPJS Health (Er) | M6: JKK (Er) | N6: JKM (Er) | O6: JHT (Er) | P6: JP (Er) | Q6: Employer BPJS Total | R6: PPh 21 Base | S6: TER Rate | T6: PPh 21 | U6: BPJS Health (Ee) | V6: JHT (Ee) | W6: JP (Ee) | X6: Employee BPJS Total | Y6: Net Pay | Z6: BPJS Payable | AA6: Total Employer Cost | AB6: Paid From | AD6: BPJS Contribution | AE6: Rate
B7: 1 | C7: 46047 | D7: E001 | E7: =_xlfn.XLOOKUP(tblPayroll[[#This Row],[Employee ID]],tblEmployees[Employee ID],tblEmployees[Full Name],"") -> Budi Santoso | F7: =_xlfn.XLOOKUP(tblPayroll[[#This Row],[Employee ID]],tblEmployees[Employee ID],tblEmployees[Department],"") -> G&A | G7: =_xlfn.XLOOKUP(tblPayroll[[#This Row],[Employee ID]],tblEmployees[Employee ID],tblEmployees[TER Category],"") -> B | H7: =_xlfn.XLOOKUP(tblPayroll[[#This Row],[Employee ID]],tblEmployees[Employee ID],tblEmployees[Basic Salary],"") -> 25000000 | I7: =_xlfn.XLOOKUP(tblPayroll[[#This Row],[Employee ID]],tblEmployees[Employee ID],tblEmployees[Fixed Allowance],"") -> 4000000 | J7: 0 | K7: =tblPayroll[[#This Row],[Basic Salary]]+tblPayroll[[#This Row],[Fixed Allowance]]+tblPayroll[[#This Row],[THR / Bonus]] -> 29000000 | L7: =ROUND(MIN(tblPayroll[[#This Row],[Basic Salary]]+tblPayroll[[#This Row],[Fixed Allowance]],BPJSKesCap)*R_KesEr,0) -> 480000 | M7: =ROUND((tblPayroll[[#This Row],[Basic Salary]]+tblPayroll[[#This Row],[Fixed Allowance]])*R_JKK,0) -> 69600 | N7: =ROUND((tblPayroll[[#This Row],[Basic Salary]]+tblPayroll[[#This Row],[Fixed Allowance]])*R_JKM,0) -> 87000 | O7: =ROUND((tblPayroll[[#This Row],[Basic Salary]]+tblPayroll[[#This Row],[Fixed Allowance]])*R_JHTEr,0) -> 1073000 | P7: =ROUND(MIN(tblPayroll[[#This Row],[Basic Salary]]+tblPayroll[[#This Row],[Fixed Allowance]],JPCap)*R_JPEr,0) -> 210948 | Q7: =SUM(tblPayroll[[#This Row],[BPJS Health (Er)]:[JP (Er)]]) -> 1920548 | R7: =tblPayroll[[#This Row],[Gross Salary]]+tblPayroll[[#This Row],[BPJS Health (Er)]]+tblPayroll[[#This Row],[JKK (Er)]]+tblPayroll[[#This Row],[JKM (Er)]] -> 29636600 | S7: =IF(tblPayroll[[#This Row],[TER Cat]]="A",_xlfn.XLOOKUP(tblPayroll[[#This Row],[PPh 21 Base]],TerA_L,TerA_R,0,-1),IF(tblPayroll[[#This Row],[TER Cat]]="B",_xlfn.XLOOKUP(tblPayroll[[#This Row],[PPh 21 Base]],TerB_L,TerB_R,0,-1),_xlfn.XLOOKUP(tblPayroll[[#This Row],[PPh 21 Base]],TerC_L,TerC_R,0,-1))) -> 0.12 | T7: =ROUND(tblPayroll[[#This Row],[PPh 21 Base]]*tblPayroll[[#This Row],[TER Rate]],0) -> 3556392 | U7: =ROUND(MIN(tblPayroll[[#This Row],[Basic Salary]]+tblPayroll[[#This Row],[Fixed Allowance]],BPJSKesCap)*R_KesEe,0) -> 120000 | V7: =ROUND((tblPayroll[[#This Row],[Basic Salary]]+tblPayroll[[#This Row],[Fixed Allowance]])*R_JHTEe,0) -> 580000 | W7: =ROUND(MIN(tblPayroll[[#This Row],[Basic Salary]]+tblPayroll[[#This Row],[Fixed Allowance]],JPCap)*R_JPEe,0) -> 105474 | X7: =tblPayroll[[#This Row],[BPJS Health (Ee)]]+tblPayroll[[#This Row],[JHT (Ee)]]+tblPayroll[[#This Row],[JP (Ee)]] -> 805474 | Y7: =tblPayroll[[#This Row],[Gross Salary]]-tblPayroll[[#This Row],[PPh 21]]-tblPayroll[[#This Row],[Employee BPJS Total]] -> 24638134 | Z7: =tblPayroll[[#This Row],[Employer BPJS Total]]+tblPayroll[[#This Row],[Employee BPJS Total]] -> 2726022 | AA7: =tblPayroll[[#This Row],[Gross Salary]]+tblPayroll[[#This Row],[Employer BPJS Total]] -> 30920548 | AB7: 1130 | AD7: BPJS Health - Employer | AE7: 0.04
B8: 1 | C8: 46047 | D8: E002 | E8: =_xlfn.XLOOKUP(tblPayroll[[#This Row],[Employee ID]],tblEmployees[Employee ID],tblEmployees[Full Name],"") -> Siti Rahmawati | F8: =_xlfn.XLOOKUP(tblPayroll[[#This Row],[Employee ID]],tblEmployees[Employee ID],tblEmployees[Department],"") -> G&A | G8: =_xlfn.XLOOKUP(tblPayroll[[#This Row],[Employee ID]],tblEmployees[Employee ID],tblEmployees[TER Category],"") -> B | H8: =_xlfn.XLOOKUP(tblPayroll[[#This Row],[Employee ID]],tblEmployees[Employee ID],tblEmployees[Basic Salary],"") -> 20000000 | I8: =_xlfn.XLOOKUP(tblPayroll[[#This Row],[Employee ID]],tblEmployees[Employee ID],tblEmployees[Fixed Allowance],"") -> 3000000 | J8: 0 | K8: =tblPayroll[[#This Row],[Basic Salary]]+tblPayroll[[#This Row],[Fixed Allowance]]+tblPayroll[[#This Row],[THR / Bonus]] -> 23000000 | L8: =ROUND(MIN(tblPayroll[[#This Row],[Basic Salary]]+tblPayroll[[#This Row],[Fixed Allowance]],BPJSKesCap)*R_KesEr,0) -> 480000 | M8: =ROUND((tblPayroll[[#This Row],[Basic Salary]]+tblPayroll[[#This Row],[Fixed Allowance]])*R_JKK,0) -> 55200 | N8: =ROUND((tblPayroll[[#This Row],[Basic Salary]]+tblPayroll[[#This Row],[Fixed Allowance]])*R_JKM,0) -> 69000 | O8: =ROUND((tblPayroll[[#This Row],[Basic Salary]]+tblPayroll[[#This Row],[Fixed Allowance]])*R_JHTEr,0) -> 851000 | P8: =ROUND(MIN(tblPayroll[[#This Row],[Basic Salary]]+tblPayroll[[#This Row],[Fixed Allowance]],JPCap)*R_JPEr,0) -> 210948 | Q8: =SUM(tblPayroll[[#This Row],[BPJS Health (Er)]:[JP (Er)]]) -> 1666148 | R8: =tblPayroll[[#This Row],[Gross Salary]]+tblPayroll[[#This Row],[BPJS Health (Er)]]+tblPayroll[[#This Row],[JKK (Er)]]+tblPayroll[[#This Row],[JKM (Er)]] -> 23604200 | S8: =IF(tblPayroll[[#This Row],[TER Cat]]="A",_xlfn.XLOOKUP(tblPayroll[[#This Row],[PPh 21 Base]],TerA_L,TerA_R,0,-1),IF(tblPayroll[[#This Row],[TER Cat]]="B",_xlfn.XLOOKUP(tblPayroll[[#This Row],[PPh 21 Base]],TerB_L,TerB_R,0,-1),_xlfn.XLOOKUP(tblPayroll[[#This Row],[PPh 21 Base]],TerC_L,TerC_R,0,-1))) -> 0.09 | T8: =ROUND(tblPayroll[[#This Row],[PPh 21 Base]]*tblPayroll[[#This Row],[TER Rate]],0) -> 2124378 | U8: =ROUND(MIN(tblPayroll[[#This Row],[Basic Salary]]+tblPayroll[[#This Row],[Fixed Allowance]],BPJSKesCap)*R_KesEe,0) -> 120000 | V8: =ROUND((tblPayroll[[#This Row],[Basic Salary]]+tblPayroll[[#This Row],[Fixed Allowance]])*R_JHTEe,0) -> 460000 | W8: =ROUND(MIN(tblPayroll[[#This Row],[Basic Salary]]+tblPayroll[[#This Row],[Fixed Allowance]],JPCap)*R_JPEe,0) -> 105474 | X8: =tblPayroll[[#This Row],[BPJS Health (Ee)]]+tblPayroll[[#This Row],[JHT (Ee)]]+tblPayroll[[#This Row],[JP (Ee)]] -> 685474 | Y8: =tblPayroll[[#This Row],[Gross Salary]]-tblPayroll[[#This Row],[PPh 21]]-tblPayroll[[#This Row],[Employee BPJS Total]] -> 20190148 | Z8: =tblPayroll[[#This Row],[Employer BPJS Total]]+tblPayroll[[#This Row],[Employee BPJS Total]] -> 2351622 | AA8: =tblPayroll[[#This Row],[Gross Salary]]+tblPayroll[[#This Row],[Employer BPJS Total]] -> 24666148 | AB8: 1130 | AD8: BPJS Health - Employee | AE8: 0.01
B9: 1 | C9: 46047 | D9: E003 | E9: =_xlfn.XLOOKUP(tblPayroll[[#This Row],[Employee ID]],tblEmployees[Employee ID],tblEmployees[Full Name],"") -> Dewi Lestari | F9: =_xlfn.XLOOKUP(tblPayroll[[#This Row],[Employee ID]],tblEmployees[Employee ID],tblEmployees[Department],"") -> G&A | G9: =_xlfn.XLOOKUP(tblPayroll[[#This Row],[Employee ID]],tblEmployees[Employee ID],tblEmployees[TER Category],"") -> A | H9: =_xlfn.XLOOKUP(tblPayroll[[#This Row],[Employee ID]],tblEmployees[Employee ID],tblEmployees[Basic Salary],"") -> 15000000 | I9: =_xlfn.XLOOKUP(tblPayroll[[#This Row],[Employee ID]],tblEmployees[Employee ID],tblEmployees[Fixed Allowance],"") -> 2000000 | J9: 0 | K9: =tblPayroll[[#This Row],[Basic Salary]]+tblPayroll[[#This Row],[Fixed Allowance]]+tblPayroll[[#This Row],[THR / Bonus]] -> 17000000 | L9: =ROUND(MIN(tblPayroll[[#This Row],[Basic Salary]]+tblPayroll[[#This Row],[Fixed Allowance]],BPJSKesCap)*R_KesEr,0) -> 480000 | M9: =ROUND((tblPayroll[[#This Row],[Basic Salary]]+tblPayroll[[#This Row],[Fixed Allowance]])*R_JKK,0) -> 40800 | N9: =ROUND((tblPayroll[[#This Row],[Basic Salary]]+tblPayroll[[#This Row],[Fixed Allowance]])*R_JKM,0) -> 51000 | O9: =ROUND((tblPayroll[[#This Row],[Basic Salary]]+tblPayroll[[#This Row],[Fixed Allowance]])*R_JHTEr,0) -> 629000 | P9: =ROUND(MIN(tblPayroll[[#This Row],[Basic Salary]]+tblPayroll[[#This Row],[Fixed Allowance]],JPCap)*R_JPEr,0) -> 210948 | Q9: =SUM(tblPayroll[[#This Row],[BPJS Health (Er)]:[JP (Er)]]) -> 1411748 | R9: =tblPayroll[[#This Row],[Gross Salary]]+tblPayroll[[#This Row],[BPJS Health (Er)]]+tblPayroll[[#This Row],[JKK (Er)]]+tblPayroll[[#This Row],[JKM (Er)]] -> 17571800 | S9: =IF(tblPayroll[[#This Row],[TER Cat]]="A",_xlfn.XLOOKUP(tblPayroll[[#This Row],[PPh 21 Base]],TerA_L,TerA_R,0,-1),IF(tblPayroll[[#This Row],[TER Cat]]="B",_xlfn.XLOOKUP(tblPayroll[[#This Row],[PPh 21 Base]],TerB_L,TerB_R,0,-1),_xlfn.XLOOKUP(tblPayroll[[#This Row],[PPh 21 Base]],TerC_L,TerC_R,0,-1))) -> 0.08 | T9: =ROUND(tblPayroll[[#This Row],[PPh 21 Base]]*tblPayroll[[#This Row],[TER Rate]],0) -> 1405744 | U9: =ROUND(MIN(tblPayroll[[#This Row],[Basic Salary]]+tblPayroll[[#This Row],[Fixed Allowance]],BPJSKesCap)*R_KesEe,0) -> 120000 | V9: =ROUND((tblPayroll[[#This Row],[Basic Salary]]+tblPayroll[[#This Row],[Fixed Allowance]])*R_JHTEe,0) -> 340000 | W9: =ROUND(MIN(tblPayroll[[#This Row],[Basic Salary]]+tblPayroll[[#This Row],[Fixed Allowance]],JPCap)*R_JPEe,0) -> 105474 | X9: =tblPayroll[[#This Row],[BPJS Health (Ee)]]+tblPayroll[[#This Row],[JHT (Ee)]]+tblPayroll[[#This Row],[JP (Ee)]] -> 565474 | Y9: =tblPayroll[[#This Row],[Gross Salary]]-tblPayroll[[#This Row],[PPh 21]]-tblPayroll[[#This Row],[Employee BPJS Total]] -> 15028782 | Z9: =tblPayroll[[#This Row],[Employer BPJS Total]]+tblPayroll[[#This Row],[Employee BPJS Total]] -> 1977222 | AA9: =tblPayroll[[#This Row],[Gross Salary]]+tblPayroll[[#This Row],[Employer BPJS Total]] -> 18411748 | AB9: 1130 | AD9: JKK (work accident) - Employer | AE9: 0.0024
B10: 1 | C10: 46047 | D10: E004 | E10: =_xlfn.XLOOKUP(tblPayroll[[#This Row],[Employee ID]],tblEmployees[Employee ID],tblEmployees[Full Name],"") -> Agus Prasetyo | F10: =_xlfn.XLOOKUP(tblPayroll[[#This Row],[Employee ID]],tblEmployees[Employee ID],tblEmployees[Department],"") -> Selling | G10: =_xlfn.XLOOKUP(tblPayroll[[#This Row],[Employee ID]],tblEmployees[Employee ID],tblEmployees[TER Category],"") -> B | H10: =_xlfn.XLOOKUP(tblPayroll[[#This Row],[Employee ID]],tblEmployees[Employee ID],tblEmployees[Basic Salary],"") -> 14000000 | I10: =_xlfn.XLOOKUP(tblPayroll[[#This Row],[Employee ID]],tblEmployees[Employee ID],tblEmployees[Fixed Allowance],"") -> 2000000 | J10: 0 | K10: =tblPayroll[[#This Row],[Basic Salary]]+tblPayroll[[#This Row],[Fixed Allowance]]+tblPayroll[[#This Row],[THR / Bonus]] -> 16000000 | L10: =ROUND(MIN(tblPayroll[[#This Row],[Basic Salary]]+tblPayroll[[#This Row],[Fixed Allowance]],BPJSKesCap)*R_KesEr,0) -> 480000 | M10: =ROUND((tblPayroll[[#This Row],[Basic Salary]]+tblPayroll[[#This Row],[Fixed Allowance]])*R_JKK,0) -> 38400 | N10: =ROUND((tblPayroll[[#This Row],[Basic Salary]]+tblPayroll[[#This Row],[Fixed Allowance]])*R_JKM,0) -> 48000 | O10: =ROUND((tblPayroll[[#This Row],[Basic Salary]]+tblPayroll[[#This Row],[Fixed Allowance]])*R_JHTEr,0) -> 592000 | P10: =ROUND(MIN(tblPayroll[[#This Row],[Basic Salary]]+tblPayroll[[#This Row],[Fixed Allowance]],JPCap)*R_JPEr,0) -> 210948 | Q10: =SUM(tblPayroll[[#This Row],[BPJS Health (Er)]:[JP (Er)]]) -> 1369348 | R10: =tblPayroll[[#This Row],[Gross Salary]]+tblPayroll[[#This Row],[BPJS Health (Er)]]+tblPayroll[[#This Row],[JKK (Er)]]+tblPayroll[[#This Row],[JKM (Er)]] -> 16566400 | S10: =IF(tblPayroll[[#This Row],[TER Cat]]="A",_xlfn.XLOOKUP(tblPayroll[[#This Row],[PPh 21 Base]],TerA_L,TerA_R,0,-1),IF(tblPayroll[[#This Row],[TER Cat]]="B",_xlfn.XLOOKUP(tblPayroll[[#This Row],[PPh 21 Base]],TerB_L,TerB_R,0,-1),_xlfn.XLOOKUP(tblPayroll[[#This Row],[PPh 21 Base]],TerC_L,TerC_R,0,-1))) -> 0.07 | T10: =ROUND(tblPayroll[[#This Row],[PPh 21 Base]]*tblPayroll[[#This Row],[TER Rate]],0) -> 1159648 | U10: =ROUND(MIN(tblPayroll[[#This Row],[Basic Salary]]+tblPayroll[[#This Row],[Fixed Allowance]],BPJSKesCap)*R_KesEe,0) -> 120000 | V10: =ROUND((tblPayroll[[#This Row],[Basic Salary]]+tblPayroll[[#This Row],[Fixed Allowance]])*R_JHTEe,0) -> 320000 | W10: =ROUND(MIN(tblPayroll[[#This Row],[Basic Salary]]+tblPayroll[[#This Row],[Fixed Allowance]],JPCap)*R_JPEe,0) -> 105474 | X10: =tblPayroll[[#This Row],[BPJS Health (Ee)]]+tblPayroll[[#This Row],[JHT (Ee)]]+tblPayroll[[#This Row],[JP (Ee)]] -> 545474 | Y10: =tblPayroll[[#This Row],[Gross Salary]]-tblPayroll[[#This Row],[PPh 21]]-tblPayroll[[#This Row],[Employee BPJS Total]] -> 14294878 | Z10: =tblPayroll[[#This Row],[Employer BPJS Total]]+tblPayroll[[#This Row],[Employee BPJS Total]] -> 1914822 | AA10: =tblPayroll[[#This Row],[Gross Salary]]+tblPayroll[[#This Row],[Employer BPJS Total]] -> 17369348 | AB10: 1130 | AD10: JKM (death) - Employer | AE10: 0.003
B11: 1 | C11: 46047 | D11: E005 | E11: =_xlfn.XLOOKUP(tblPayroll[[#This Row],[Employee ID]],tblEmployees[Employee ID],tblEmployees[Full Name],"") -> Rina Kartika | F11: =_xlfn.XLOOKUP(tblPayroll[[#This Row],[Employee ID]],tblEmployees[Employee ID],tblEmployees[Department],"") -> Selling | G11: =_xlfn.XLOOKUP(tblPayroll[[#This Row],[Employee ID]],tblEmployees[Employee ID],tblEmployees[TER Category],"") -> A | H11: =_xlfn.XLOOKUP(tblPayroll[[#This Row],[Employee ID]],tblEmployees[Employee ID],tblEmployees[Basic Salary],"") -> 12000000 | I11: =_xlfn.XLOOKUP(tblPayroll[[#This Row],[Employee ID]],tblEmployees[Employee ID],tblEmployees[Fixed Allowance],"") -> 1500000 | J11: 0 | K11: =tblPayroll[[#This Row],[Basic Salary]]+tblPayroll[[#This Row],[Fixed Allowance]]+tblPayroll[[#This Row],[THR / Bonus]] -> 13500000 | L11: =ROUND(MIN(tblPayroll[[#This Row],[Basic Salary]]+tblPayroll[[#This Row],[Fixed Allowance]],BPJSKesCap)*R_KesEr,0) -> 480000 | M11: =ROUND((tblPayroll[[#This Row],[Basic Salary]]+tblPayroll[[#This Row],[Fixed Allowance]])*R_JKK,0) -> 32400 | N11: =ROUND((tblPayroll[[#This Row],[Basic Salary]]+tblPayroll[[#This Row],[Fixed Allowance]])*R_JKM,0) -> 40500 | O11: =ROUND((tblPayroll[[#This Row],[Basic Salary]]+tblPayroll[[#This Row],[Fixed Allowance]])*R_JHTEr,0) -> 499500 | P11: =ROUND(MIN(tblPayroll[[#This Row],[Basic Salary]]+tblPayroll[[#This Row],[Fixed Allowance]],JPCap)*R_JPEr,0) -> 210948 | Q11: =SUM(tblPayroll[[#This Row],[BPJS Health (Er)]:[JP (Er)]]) -> 1263348 | R11: =tblPayroll[[#This Row],[Gross Salary]]+tblPayroll[[#This Row],[BPJS Health (Er)]]+tblPayroll[[#This Row],[JKK (Er)]]+tblPayroll[[#This Row],[JKM (Er)]] -> 14052900 | S11: =IF(tblPayroll[[#This Row],[TER Cat]]="A",_xlfn.XLOOKUP(tblPayroll[[#This Row],[PPh 21 Base]],TerA_L,TerA_R,0,-1),IF(tblPayroll[[#This Row],[TER Cat]]="B",_xlfn.XLOOKUP(tblPayroll[[#This Row],[PPh 21 Base]],TerB_L,TerB_R,0,-1),_xlfn.XLOOKUP(tblPayroll[[#This Row],[PPh 21 Base]],TerC_L,TerC_R,0,-1))) -> 0.06 | T11: =ROUND(tblPayroll[[#This Row],[PPh 21 Base]]*tblPayroll[[#This Row],[TER Rate]],0) -> 843174 | U11: =ROUND(MIN(tblPayroll[[#This Row],[Basic Salary]]+tblPayroll[[#This Row],[Fixed Allowance]],BPJSKesCap)*R_KesEe,0) -> 120000 | V11: =ROUND((tblPayroll[[#This Row],[Basic Salary]]+tblPayroll[[#This Row],[Fixed Allowance]])*R_JHTEe,0) -> 270000 | W11: =ROUND(MIN(tblPayroll[[#This Row],[Basic Salary]]+tblPayroll[[#This Row],[Fixed Allowance]],JPCap)*R_JPEe,0) -> 105474 | X11: =tblPayroll[[#This Row],[BPJS Health (Ee)]]+tblPayroll[[#This Row],[JHT (Ee)]]+tblPayroll[[#This Row],[JP (Ee)]] -> 495474 | Y11: =tblPayroll[[#This Row],[Gross Salary]]-tblPayroll[[#This Row],[PPh 21]]-tblPayroll[[#This Row],[Employee BPJS Total]] -> 12161352 | Z11: =tblPayroll[[#This Row],[Employer BPJS Total]]+tblPayroll[[#This Row],[Employee BPJS Total]] -> 1758822 | AA11: =tblPayroll[[#This Row],[Gross Salary]]+tblPayroll[[#This Row],[Employer BPJS Total]] -> 14763348 | AB11: 1130 | AD11: JHT (old age) - Employer | AE11: 0.037
B12: 1 | C12: 46047 | D12: E006 | E12: =_xlfn.XLOOKUP(tblPayroll[[#This Row],[Employee ID]],tblEmployees[Employee ID],tblEmployees[Full Name],"") -> Andi Saputra | F12: =_xlfn.XLOOKUP(tblPayroll[[#This Row],[Employee ID]],tblEmployees[Employee ID],tblEmployees[Department],"") -> G&A | G12: =_xlfn.XLOOKUP(tblPayroll[[#This Row],[Employee ID]],tblEmployees[Employee ID],tblEmployees[TER Category],"") -> A | H12: =_xlfn.XLOOKUP(tblPayroll[[#This Row],[Employee ID]],tblEmployees[Employee ID],tblEmployees[Basic Salary],"") -> 8500000 | I12: =_xlfn.XLOOKUP(tblPayroll[[#This Row],[Employee ID]],tblEmployees[Employee ID],tblEmployees[Fixed Allowance],"") -> 1000000 | J12: 0 | K12: =tblPayroll[[#This Row],[Basic Salary]]+tblPayroll[[#This Row],[Fixed Allowance]]+tblPayroll[[#This Row],[THR / Bonus]] -> 9500000 | L12: =ROUND(MIN(tblPayroll[[#This Row],[Basic Salary]]+tblPayroll[[#This Row],[Fixed Allowance]],BPJSKesCap)*R_KesEr,0) -> 380000 | M12: =ROUND((tblPayroll[[#This Row],[Basic Salary]]+tblPayroll[[#This Row],[Fixed Allowance]])*R_JKK,0) -> 22800 | N12: =ROUND((tblPayroll[[#This Row],[Basic Salary]]+tblPayroll[[#This Row],[Fixed Allowance]])*R_JKM,0) -> 28500 | O12: =ROUND((tblPayroll[[#This Row],[Basic Salary]]+tblPayroll[[#This Row],[Fixed Allowance]])*R_JHTEr,0) -> 351500 | P12: =ROUND(MIN(tblPayroll[[#This Row],[Basic Salary]]+tblPayroll[[#This Row],[Fixed Allowance]],JPCap)*R_JPEr,0) -> 190000 | Q12: =SUM(tblPayroll[[#This Row],[BPJS Health (Er)]:[JP (Er)]]) -> 972800 | R12: =tblPayroll[[#This Row],[Gross Salary]]+tblPayroll[[#This Row],[BPJS Health (Er)]]+tblPayroll[[#This Row],[JKK (Er)]]+tblPayroll[[#This Row],[JKM (Er)]] -> 9931300 | S12: =IF(tblPayroll[[#This Row],[TER Cat]]="A",_xlfn.XLOOKUP(tblPayroll[[#This Row],[PPh 21 Base]],TerA_L,TerA_R,0,-1),IF(tblPayroll[[#This Row],[TER Cat]]="B",_xlfn.XLOOKUP(tblPayroll[[#This Row],[PPh 21 Base]],TerB_L,TerB_R,0,-1),_xlfn.XLOOKUP(tblPayroll[[#This Row],[PPh 21 Base]],TerC_L,TerC_R,0,-1))) -> 0.02 | T12: =ROUND(tblPayroll[[#This Row],[PPh 21 Base]]*tblPayroll[[#This Row],[TER Rate]],0) -> 198626 | U12: =ROUND(MIN(tblPayroll[[#This Row],[Basic Salary]]+tblPayroll[[#This Row],[Fixed Allowance]],BPJSKesCap)*R_KesEe,0) -> 95000 | V12: =ROUND((tblPayroll[[#This Row],[Basic Salary]]+tblPayroll[[#This Row],[Fixed Allowance]])*R_JHTEe,0) -> 190000 | W12: =ROUND(MIN(tblPayroll[[#This Row],[Basic Salary]]+tblPayroll[[#This Row],[Fixed Allowance]],JPCap)*R_JPEe,0) -> 95000 | X12: =tblPayroll[[#This Row],[BPJS Health (Ee)]]+tblPayroll[[#This Row],[JHT (Ee)]]+tblPayroll[[#This Row],[JP (Ee)]] -> 380000 | Y12: =tblPayroll[[#This Row],[Gross Salary]]-tblPayroll[[#This Row],[PPh 21]]-tblPayroll[[#This Row],[Employee BPJS Total]] -> 8921374 | Z12: =tblPayroll[[#This Row],[Employer BPJS Total]]+tblPayroll[[#This Row],[Employee BPJS Total]] -> 1352800 | AA12: =tblPayroll[[#This Row],[Gross Salary]]+tblPayroll[[#This Row],[Employer BPJS Total]] -> 10472800 | AB12: 1130 | AD12: JHT (old age) - Employee | AE12: 0.02
B13: 1 | C13: 46047 | D13: E007 | E13: =_xlfn.XLOOKUP(tblPayroll[[#This Row],[Employee ID]],tblEmployees[Employee ID],tblEmployees[Full Name],"") -> Fitri Handayani | F13: =_xlfn.XLOOKUP(tblPayroll[[#This Row],[Employee ID]],tblEmployees[Employee ID],tblEmployees[Department],"") -> G&A | G13: =_xlfn.XLOOKUP(tblPayroll[[#This Row],[Employee ID]],tblEmployees[Employee ID],tblEmployees[TER Category],"") -> A | H13: =_xlfn.XLOOKUP(tblPayroll[[#This Row],[Employee ID]],tblEmployees[Employee ID],tblEmployees[Basic Salary],"") -> 8000000 | I13: =_xlfn.XLOOKUP(tblPayroll[[#This Row],[Employee ID]],tblEmployees[Employee ID],tblEmployees[Fixed Allowance],"") -> 1000000 | J13: 0 | K13: =tblPayroll[[#This Row],[Basic Salary]]+tblPayroll[[#This Row],[Fixed Allowance]]+tblPayroll[[#This Row],[THR / Bonus]] -> 9000000 | L13: =ROUND(MIN(tblPayroll[[#This Row],[Basic Salary]]+tblPayroll[[#This Row],[Fixed Allowance]],BPJSKesCap)*R_KesEr,0) -> 360000 | M13: =ROUND((tblPayroll[[#This Row],[Basic Salary]]+tblPayroll[[#This Row],[Fixed Allowance]])*R_JKK,0) -> 21600 | N13: =ROUND((tblPayroll[[#This Row],[Basic Salary]]+tblPayroll[[#This Row],[Fixed Allowance]])*R_JKM,0) -> 27000 | O13: =ROUND((tblPayroll[[#This Row],[Basic Salary]]+tblPayroll[[#This Row],[Fixed Allowance]])*R_JHTEr,0) -> 333000 | P13: =ROUND(MIN(tblPayroll[[#This Row],[Basic Salary]]+tblPayroll[[#This Row],[Fixed Allowance]],JPCap)*R_JPEr,0) -> 180000 | Q13: =SUM(tblPayroll[[#This Row],[BPJS Health (Er)]:[JP (Er)]]) -> 921600 | R13: =tblPayroll[[#This Row],[Gross Salary]]+tblPayroll[[#This Row],[BPJS Health (Er)]]+tblPayroll[[#This Row],[JKK (Er)]]+tblPayroll[[#This Row],[JKM (Er)]] -> 9408600 | S13: =IF(tblPayroll[[#This Row],[TER Cat]]="A",_xlfn.XLOOKUP(tblPayroll[[#This Row],[PPh 21 Base]],TerA_L,TerA_R,0,-1),IF(tblPayroll[[#This Row],[TER Cat]]="B",_xlfn.XLOOKUP(tblPayroll[[#This Row],[PPh 21 Base]],TerB_L,TerB_R,0,-1),_xlfn.XLOOKUP(tblPayroll[[#This Row],[PPh 21 Base]],TerC_L,TerC_R,0,-1))) -> 0.0175 | T13: =ROUND(tblPayroll[[#This Row],[PPh 21 Base]]*tblPayroll[[#This Row],[TER Rate]],0) -> 164651 | U13: =ROUND(MIN(tblPayroll[[#This Row],[Basic Salary]]+tblPayroll[[#This Row],[Fixed Allowance]],BPJSKesCap)*R_KesEe,0) -> 90000 | V13: =ROUND((tblPayroll[[#This Row],[Basic Salary]]+tblPayroll[[#This Row],[Fixed Allowance]])*R_JHTEe,0) -> 180000 | W13: =ROUND(MIN(tblPayroll[[#This Row],[Basic Salary]]+tblPayroll[[#This Row],[Fixed Allowance]],JPCap)*R_JPEe,0) -> 90000 | X13: =tblPayroll[[#This Row],[BPJS Health (Ee)]]+tblPayroll[[#This Row],[JHT (Ee)]]+tblPayroll[[#This Row],[JP (Ee)]] -> 360000 | Y13: =tblPayroll[[#This Row],[Gross Salary]]-tblPayroll[[#This Row],[PPh 21]]-tblPayroll[[#This Row],[Employee BPJS Total]] -> 8475349 | Z13: =tblPayroll[[#This Row],[Employer BPJS Total]]+tblPayroll[[#This Row],[Employee BPJS Total]] -> 1281600 | AA13: =tblPayroll[[#This Row],[Gross Salary]]+tblPayroll[[#This Row],[Employer BPJS Total]] -> 9921600 | AB13: 1130 | AD13: JP (pension) - Employer | AE13: 0.02
B14: 1 | C14: 46047 | D14: E008 | E14: =_xlfn.XLOOKUP(tblPayroll[[#This Row],[Employee ID]],tblEmployees[Employee ID],tblEmployees[Full Name],"") -> Rizky Ramadhan | F14: =_xlfn.XLOOKUP(tblPayroll[[#This Row],[Employee ID]],tblEmployees[Employee ID],tblEmployees[Department],"") -> Selling | G14: =_xlfn.XLOOKUP(tblPayroll[[#This Row],[Employee ID]],tblEmployees[Employee ID],tblEmployees[TER Category],"") -> A | H14: =_xlfn.XLOOKUP(tblPayroll[[#This Row],[Employee ID]],tblEmployees[Employee ID],tblEmployees[Basic Salary],"") -> 9000000 | I14: =_xlfn.XLOOKUP(tblPayroll[[#This Row],[Employee ID]],tblEmployees[Employee ID],tblEmployees[Fixed Allowance],"") -> 1500000 | J14: 0 | K14: =tblPayroll[[#This Row],[Basic Salary]]+tblPayroll[[#This Row],[Fixed Allowance]]+tblPayroll[[#This Row],[THR / Bonus]] -> 10500000 | L14: =ROUND(MIN(tblPayroll[[#This Row],[Basic Salary]]+tblPayroll[[#This Row],[Fixed Allowance]],BPJSKesCap)*R_KesEr,0) -> 420000 | M14: =ROUND((tblPayroll[[#This Row],[Basic Salary]]+tblPayroll[[#This Row],[Fixed Allowance]])*R_JKK,0) -> 25200 | N14: =ROUND((tblPayroll[[#This Row],[Basic Salary]]+tblPayroll[[#This Row],[Fixed Allowance]])*R_JKM,0) -> 31500 | O14: =ROUND((tblPayroll[[#This Row],[Basic Salary]]+tblPayroll[[#This Row],[Fixed Allowance]])*R_JHTEr,0) -> 388500 | P14: =ROUND(MIN(tblPayroll[[#This Row],[Basic Salary]]+tblPayroll[[#This Row],[Fixed Allowance]],JPCap)*R_JPEr,0) -> 210000 | Q14: =SUM(tblPayroll[[#This Row],[BPJS Health (Er)]:[JP (Er)]]) -> 1075200 | R14: =tblPayroll[[#This Row],[Gross Salary]]+tblPayroll[[#This Row],[BPJS Health (Er)]]+tblPayroll[[#This Row],[JKK (Er)]]+tblPayroll[[#This Row],[JKM (Er)]] -> 10976700 | S14: =IF(tblPayroll[[#This Row],[TER Cat]]="A",_xlfn.XLOOKUP(tblPayroll[[#This Row],[PPh 21 Base]],TerA_L,TerA_R,0,-1),IF(tblPayroll[[#This Row],[TER Cat]]="B",_xlfn.XLOOKUP(tblPayroll[[#This Row],[PPh 21 Base]],TerB_L,TerB_R,0,-1),_xlfn.XLOOKUP(tblPayroll[[#This Row],[PPh 21 Base]],TerC_L,TerC_R,0,-1))) -> 0.03 | T14: =ROUND(tblPayroll[[#This Row],[PPh 21 Base]]*tblPayroll[[#This Row],[TER Rate]],0) -> 329301 | U14: =ROUND(MIN(tblPayroll[[#This Row],[Basic Salary]]+tblPayroll[[#This Row],[Fixed Allowance]],BPJSKesCap)*R_KesEe,0) -> 105000 | V14: =ROUND((tblPayroll[[#This Row],[Basic Salary]]+tblPayroll[[#This Row],[Fixed Allowance]])*R_JHTEe,0) -> 210000 | W14: =ROUND(MIN(tblPayroll[[#This Row],[Basic Salary]]+tblPayroll[[#This Row],[Fixed Allowance]],JPCap)*R_JPEe,0) -> 105000 | X14: =tblPayroll[[#This Row],[BPJS Health (Ee)]]+tblPayroll[[#This Row],[JHT (Ee)]]+tblPayroll[[#This Row],[JP (Ee)]] -> 420000 | Y14: =tblPayroll[[#This Row],[Gross Salary]]-tblPayroll[[#This Row],[PPh 21]]-tblPayroll[[#This Row],[Employee BPJS Total]] -> 9750699 | Z14: =tblPayroll[[#This Row],[Employer BPJS Total]]+tblPayroll[[#This Row],[Employee BPJS Total]] -> 1495200 | AA14: =tblPayroll[[#This Row],[Gross Salary]]+tblPayroll[[#This Row],[Employer BPJS Total]] -> 11575200 | AB14: 1130 | AD14: JP (pension) - Employee | AE14: 0.01
B15: 1 | C15: 46047 | D15: E009 | E15: =_xlfn.XLOOKUP(tblPayroll[[#This Row],[Employee ID]],tblEmployees[Employee ID],tblEmployees[Full Name],"") -> Nadia Putri | F15: =_xlfn.XLOOKUP(tblPayroll[[#This Row],[Employee ID]],tblEmployees[Employee ID],tblEmployees[Department],"") -> Selling | G15: =_xlfn.XLOOKUP(tblPayroll[[#This Row],[Employee ID]],tblEmployees[Employee ID],tblEmployees[TER Category],"") -> A | H15: =_xlfn.XLOOKUP(tblPayroll[[#This Row],[Employee ID]],tblEmployees[Employee ID],tblEmployees[Basic Salary],"") -> 5800000 | I15: =_xlfn.XLOOKUP(tblPayroll[[#This Row],[Employee ID]],tblEmployees[Employee ID],tblEmployees[Fixed Allowance],"") -> 700000 | J15: 0 | K15: =tblPayroll[[#This Row],[Basic Salary]]+tblPayroll[[#This Row],[Fixed Allowance]]+tblPayroll[[#This Row],[THR / Bonus]] -> 6500000 | L15: =ROUND(MIN(tblPayroll[[#This Row],[Basic Salary]]+tblPayroll[[#This Row],[Fixed Allowance]],BPJSKesCap)*R_KesEr,0) -> 260000 | M15: =ROUND((tblPayroll[[#This Row],[Basic Salary]]+tblPayroll[[#This Row],[Fixed Allowance]])*R_JKK,0) -> 15600 | N15: =ROUND((tblPayroll[[#This Row],[Basic Salary]]+tblPayroll[[#This Row],[Fixed Allowance]])*R_JKM,0) -> 19500 | O15: =ROUND((tblPayroll[[#This Row],[Basic Salary]]+tblPayroll[[#This Row],[Fixed Allowance]])*R_JHTEr,0) -> 240500 | P15: =ROUND(MIN(tblPayroll[[#This Row],[Basic Salary]]+tblPayroll[[#This Row],[Fixed Allowance]],JPCap)*R_JPEr,0) -> 130000 | Q15: =SUM(tblPayroll[[#This Row],[BPJS Health (Er)]:[JP (Er)]]) -> 665600 | R15: =tblPayroll[[#This Row],[Gross Salary]]+tblPayroll[[#This Row],[BPJS Health (Er)]]+tblPayroll[[#This Row],[JKK (Er)]]+tblPayroll[[#This Row],[JKM (Er)]] -> 6795100 | S15: =IF(tblPayroll[[#This Row],[TER Cat]]="A",_xlfn.XLOOKUP(tblPayroll[[#This Row],[PPh 21 Base]],TerA_L,TerA_R,0,-1),IF(tblPayroll[[#This Row],[TER Cat]]="B",_xlfn.XLOOKUP(tblPayroll[[#This Row],[PPh 21 Base]],TerB_L,TerB_R,0,-1),_xlfn.XLOOKUP(tblPayroll[[#This Row],[PPh 21 Base]],TerC_L,TerC_R,0,-1))) -> 0.0125 | T15: =ROUND(tblPayroll[[#This Row],[PPh 21 Base]]*tblPayroll[[#This Row],[TER Rate]],0) -> 84939 | U15: =ROUND(MIN(tblPayroll[[#This Row],[Basic Salary]]+tblPayroll[[#This Row],[Fixed Allowance]],BPJSKesCap)*R_KesEe,0) -> 65000 | V15: =ROUND((tblPayroll[[#This Row],[Basic Salary]]+tblPayroll[[#This Row],[Fixed Allowance]])*R_JHTEe,0) -> 130000 | W15: =ROUND(MIN(tblPayroll[[#This Row],[Basic Salary]]+tblPayroll[[#This Row],[Fixed Allowance]],JPCap)*R_JPEe,0) -> 65000 | X15: =tblPayroll[[#This Row],[BPJS Health (Ee)]]+tblPayroll[[#This Row],[JHT (Ee)]]+tblPayroll[[#This Row],[JP (Ee)]] -> 260000 | Y15: =tblPayroll[[#This Row],[Gross Salary]]-tblPayroll[[#This Row],[PPh 21]]-tblPayroll[[#This Row],[Employee BPJS Total]] -> 6155061 | Z15: =tblPayroll[[#This Row],[Employer BPJS Total]]+tblPayroll[[#This Row],[Employee BPJS Total]] -> 925600 | AA15: =tblPayroll[[#This Row],[Gross Salary]]+tblPayroll[[#This Row],[Employer BPJS Total]] -> 7165600 | AB15: 1130
B16: 1 | C16: 46047 | D16: E010 | E16: =_xlfn.XLOOKUP(tblPayroll[[#This Row],[Employee ID]],tblEmployees[Employee ID],tblEmployees[Full Name],"") -> Dimas Pratama | F16: =_xlfn.XLOOKUP(tblPayroll[[#This Row],[Employee ID]],tblEmployees[Employee ID],tblEmployees[Department],"") -> Selling | G16: =_xlfn.XLOOKUP(tblPayroll[[#This Row],[Employee ID]],tblEmployees[Employee ID],tblEmployees[TER Category],"") -> A | H16: =_xlfn.XLOOKUP(tblPayroll[[#This Row],[Employee ID]],tblEmployees[Employee ID],tblEmployees[Basic Salary],"") -> 5800000 | I16: =_xlfn.XLOOKUP(tblPayroll[[#This Row],[Employee ID]],tblEmployees[Employee ID],tblEmployees[Fixed Allowance],"") -> 700000 | J16: 0 | K16: =tblPayroll[[#This Row],[Basic Salary]]+tblPayroll[[#This Row],[Fixed Allowance]]+tblPayroll[[#This Row],[THR / Bonus]] -> 6500000 | L16: =ROUND(MIN(tblPayroll[[#This Row],[Basic Salary]]+tblPayroll[[#This Row],[Fixed Allowance]],BPJSKesCap)*R_KesEr,0) -> 260000 | M16: =ROUND((tblPayroll[[#This Row],[Basic Salary]]+tblPayroll[[#This Row],[Fixed Allowance]])*R_JKK,0) -> 15600 | N16: =ROUND((tblPayroll[[#This Row],[Basic Salary]]+tblPayroll[[#This Row],[Fixed Allowance]])*R_JKM,0) -> 19500 | O16: =ROUND((tblPayroll[[#This Row],[Basic Salary]]+tblPayroll[[#This Row],[Fixed Allowance]])*R_JHTEr,0) -> 240500 | P16: =ROUND(MIN(tblPayroll[[#This Row],[Basic Salary]]+tblPayroll[[#This Row],[Fixed Allowance]],JPCap)*R_JPEr,0) -> 130000 | Q16: =SUM(tblPayroll[[#This Row],[BPJS Health (Er)]:[JP (Er)]]) -> 665600 | R16: =tblPayroll[[#This Row],[Gross Salary]]+tblPayroll[[#This Row],[BPJS Health (Er)]]+tblPayroll[[#This Row],[JKK (Er)]]+tblPayroll[[#This Row],[JKM (Er)]] -> 6795100 | S16: =IF(tblPayroll[[#This Row],[TER Cat]]="A",_xlfn.XLOOKUP(tblPayroll[[#This Row],[PPh 21 Base]],TerA_L,TerA_R,0,-1),IF(tblPayroll[[#This Row],[TER Cat]]="B",_xlfn.XLOOKUP(tblPayroll[[#This Row],[PPh 21 Base]],TerB_L,TerB_R,0,-1),_xlfn.XLOOKUP(tblPayroll[[#This Row],[PPh 21 Base]],TerC_L,TerC_R,0,-1))) -> 0.0125 | T16: =ROUND(tblPayroll[[#This Row],[PPh 21 Base]]*tblPayroll[[#This Row],[TER Rate]],0) -> 84939 | U16: =ROUND(MIN(tblPayroll[[#This Row],[Basic Salary]]+tblPayroll[[#This Row],[Fixed Allowance]],BPJSKesCap)*R_KesEe,0) -> 65000 | V16: =ROUND((tblPayroll[[#This Row],[Basic Salary]]+tblPayroll[[#This Row],[Fixed Allowance]])*R_JHTEe,0) -> 130000 | W16: =ROUND(MIN(tblPayroll[[#This Row],[Basic Salary]]+tblPayroll[[#This Row],[Fixed Allowance]],JPCap)*R_JPEe,0) -> 65000 | X16: =tblPayroll[[#This Row],[BPJS Health (Ee)]]+tblPayroll[[#This Row],[JHT (Ee)]]+tblPayroll[[#This Row],[JP (Ee)]] -> 260000 | Y16: =tblPayroll[[#This Row],[Gross Salary]]-tblPayroll[[#This Row],[PPh 21]]-tblPayroll[[#This Row],[Employee BPJS Total]] -> 6155061 | Z16: =tblPayroll[[#This Row],[Employer BPJS Total]]+tblPayroll[[#This Row],[Employee BPJS Total]] -> 925600 | AA16: =tblPayroll[[#This Row],[Gross Salary]]+tblPayroll[[#This Row],[Employer BPJS Total]] -> 7165600 | AB16: 1130 | AD16: PPh 21 TER MONTHLY RATES (PP 58/2023) – verify against latest regulation
B17: 1 | C17: 46047 | D17: E011 | E17: =_xlfn.XLOOKUP(tblPayroll[[#This Row],[Employee ID]],tblEmployees[Employee ID],tblEmployees[Full Name],"") -> Yusuf Hidayat | F17: =_xlfn.XLOOKUP(tblPayroll[[#This Row],[Employee ID]],tblEmployees[Employee ID],tblEmployees[Department],"") -> Selling | G17: =_xlfn.XLOOKUP(tblPayroll[[#This Row],[Employee ID]],tblEmployees[Employee ID],tblEmployees[TER Category],"") -> B | H17: =_xlfn.XLOOKUP(tblPayroll[[#This Row],[Employee ID]],tblEmployees[Employee ID],tblEmployees[Basic Salary],"") -> 7500000 | I17: =_xlfn.XLOOKUP(tblPayroll[[#This Row],[Employee ID]],tblEmployees[Employee ID],tblEmployees[Fixed Allowance],"") -> 1000000 | J17: 0 | K17: =tblPayroll[[#This Row],[Basic Salary]]+tblPayroll[[#This Row],[Fixed Allowance]]+tblPayroll[[#This Row],[THR / Bonus]] -> 8500000 | L17: =ROUND(MIN(tblPayroll[[#This Row],[Basic Salary]]+tblPayroll[[#This Row],[Fixed Allowance]],BPJSKesCap)*R_KesEr,0) -> 340000 | M17: =ROUND((tblPayroll[[#This Row],[Basic Salary]]+tblPayroll[[#This Row],[Fixed Allowance]])*R_JKK,0) -> 20400 | N17: =ROUND((tblPayroll[[#This Row],[Basic Salary]]+tblPayroll[[#This Row],[Fixed Allowance]])*R_JKM,0) -> 25500 | O17: =ROUND((tblPayroll[[#This Row],[Basic Salary]]+tblPayroll[[#This Row],[Fixed Allowance]])*R_JHTEr,0) -> 314500 | P17: =ROUND(MIN(tblPayroll[[#This Row],[Basic Salary]]+tblPayroll[[#This Row],[Fixed Allowance]],JPCap)*R_JPEr,0) -> 170000 | Q17: =SUM(tblPayroll[[#This Row],[BPJS Health (Er)]:[JP (Er)]]) -> 870400 | R17: =tblPayroll[[#This Row],[Gross Salary]]+tblPayroll[[#This Row],[BPJS Health (Er)]]+tblPayroll[[#This Row],[JKK (Er)]]+tblPayroll[[#This Row],[JKM (Er)]] -> 8885900 | S17: =IF(tblPayroll[[#This Row],[TER Cat]]="A",_xlfn.XLOOKUP(tblPayroll[[#This Row],[PPh 21 Base]],TerA_L,TerA_R,0,-1),IF(tblPayroll[[#This Row],[TER Cat]]="B",_xlfn.XLOOKUP(tblPayroll[[#This Row],[PPh 21 Base]],TerB_L,TerB_R,0,-1),_xlfn.XLOOKUP(tblPayroll[[#This Row],[PPh 21 Base]],TerC_L,TerC_R,0,-1))) -> 0.01 | T17: =ROUND(tblPayroll[[#This Row],[PPh 21 Base]]*tblPayroll[[#This Row],[TER Rate]],0) -> 88859 | U17: =ROUND(MIN(tblPayroll[[#This Row],[Basic Salary]]+tblPayroll[[#This Row],[Fixed Allowance]],BPJSKesCap)*R_KesEe,0) -> 85000 | V17: =ROUND((tblPayroll[[#This Row],[Basic Salary]]+tblPayroll[[#This Row],[Fixed Allowance]])*R_JHTEe,0) -> 170000 | W17: =ROUND(MIN(tblPayroll[[#This Row],[Basic Salary]]+tblPayroll[[#This Row],[Fixed Allowance]],JPCap)*R_JPEe,0) -> 85000 | X17: =tblPayroll[[#This Row],[BPJS Health (Ee)]]+tblPayroll[[#This Row],[JHT (Ee)]]+tblPayroll[[#This Row],[JP (Ee)]] -> 340000 | Y17: =tblPayroll[[#This Row],[Gross Salary]]-tblPayroll[[#This Row],[PPh 21]]-tblPayroll[[#This Row],[Employee BPJS Total]] -> 8071141 | Z17: =tblPayroll[[#This Row],[Employer BPJS Total]]+tblPayroll[[#This Row],[Employee BPJS Total]] -> 1210400 | AA17: =tblPayroll[[#This Row],[Gross Salary]]+tblPayroll[[#This Row],[Employer BPJS Total]] -> 9370400 | AB17: 1130 | AD17: TER A - Lower | AE17: Rate A | AF17: TER B - Lower | AG17: Rate B | AH17: TER C - Lower | AI17: Rate C
B18: 1 | C18: 46047 | D18: E012 | E18: =_xlfn.XLOOKUP(tblPayroll[[#This Row],[Employee ID]],tblEmployees[Employee ID],tblEmployees[Full Name],"") -> Lestari Wulandari | F18: =_xlfn.XLOOKUP(tblPayroll[[#This Row],[Employee ID]],tblEmployees[Employee ID],tblEmployees[Department],"") -> Selling | G18: =_xlfn.XLOOKUP(tblPayroll[[#This Row],[Employee ID]],tblEmployees[Employee ID],tblEmployees[TER Category],"") -> A | H18: =_xlfn.XLOOKUP(tblPayroll[[#This Row],[Employee ID]],tblEmployees[Employee ID],tblEmployees[Basic Salary],"") -> 5600000 | I18: =_xlfn.XLOOKUP(tblPayroll[[#This Row],[Employee ID]],tblEmployees[Employee ID],tblEmployees[Fixed Allowance],"") -> 600000 | J18: 0 | K18: =tblPayroll[[#This Row],[Basic Salary]]+tblPayroll[[#This Row],[Fixed Allowance]]+tblPayroll[[#This Row],[THR / Bonus]] -> 6200000 | L18: =ROUND(MIN(tblPayroll[[#This Row],[Basic Salary]]+tblPayroll[[#This Row],[Fixed Allowance]],BPJSKesCap)*R_KesEr,0) -> 248000 | M18: =ROUND((tblPayroll[[#This Row],[Basic Salary]]+tblPayroll[[#This Row],[Fixed Allowance]])*R_JKK,0) -> 14880 | N18: =ROUND((tblPayroll[[#This Row],[Basic Salary]]+tblPayroll[[#This Row],[Fixed Allowance]])*R_JKM,0) -> 18600 | O18: =ROUND((tblPayroll[[#This Row],[Basic Salary]]+tblPayroll[[#This Row],[Fixed Allowance]])*R_JHTEr,0) -> 229400 | P18: =ROUND(MIN(tblPayroll[[#This Row],[Basic Salary]]+tblPayroll[[#This Row],[Fixed Allowance]],JPCap)*R_JPEr,0) -> 124000 | Q18: =SUM(tblPayroll[[#This Row],[BPJS Health (Er)]:[JP (Er)]]) -> 634880 | R18: =tblPayroll[[#This Row],[Gross Salary]]+tblPayroll[[#This Row],[BPJS Health (Er)]]+tblPayroll[[#This Row],[JKK (Er)]]+tblPayroll[[#This Row],[JKM (Er)]] -> 6481480 | S18: =IF(tblPayroll[[#This Row],[TER Cat]]="A",_xlfn.XLOOKUP(tblPayroll[[#This Row],[PPh 21 Base]],TerA_L,TerA_R,0,-1),IF(tblPayroll[[#This Row],[TER Cat]]="B",_xlfn.XLOOKUP(tblPayroll[[#This Row],[PPh 21 Base]],TerB_L,TerB_R,0,-1),_xlfn.XLOOKUP(tblPayroll[[#This Row],[PPh 21 Base]],TerC_L,TerC_R,0,-1))) -> 0.01 | T18: =ROUND(tblPayroll[[#This Row],[PPh 21 Base]]*tblPayroll[[#This Row],[TER Rate]],0) -> 64815 | U18: =ROUND(MIN(tblPayroll[[#This Row],[Basic Salary]]+tblPayroll[[#This Row],[Fixed Allowance]],BPJSKesCap)*R_KesEe,0) -> 62000 | V18: =ROUND((tblPayroll[[#This Row],[Basic Salary]]+tblPayroll[[#This Row],[Fixed Allowance]])*R_JHTEe,0) -> 124000 | W18: =ROUND(MIN(tblPayroll[[#This Row],[Basic Salary]]+tblPayroll[[#This Row],[Fixed Allowance]],JPCap)*R_JPEe,0) -> 62000 | X18: =tblPayroll[[#This Row],[BPJS Health (Ee)]]+tblPayroll[[#This Row],[JHT (Ee)]]+tblPayroll[[#This Row],[JP (Ee)]] -> 248000 | Y18: =tblPayroll[[#This Row],[Gross Salary]]-tblPayroll[[#This Row],[PPh 21]]-tblPayroll[[#This Row],[Employee BPJS Total]] -> 5887185 | Z18: =tblPayroll[[#This Row],[Employer BPJS Total]]+tblPayroll[[#This Row],[Employee BPJS Total]] -> 882880 | AA18: =tblPayroll[[#This Row],[Gross Salary]]+tblPayroll[[#This Row],[Employer BPJS Total]] -> 6834880 | AB18: 1130 | AD18: 0 | AE18: 0 | AF18: 0 | AG18: 0 | AH18: 0 | AI18: 0
B19: 1 | C19: 46047 | D19: E013 | E19: =_xlfn.XLOOKUP(tblPayroll[[#This Row],[Employee ID]],tblEmployees[Employee ID],tblEmployees[Full Name],"") -> Bayu Nugroho | F19: =_xlfn.XLOOKUP(tblPayroll[[#This Row],[Employee ID]],tblEmployees[Employee ID],tblEmployees[Department],"") -> Selling | G19: =_xlfn.XLOOKUP(tblPayroll[[#This Row],[Employee ID]],tblEmployees[Employee ID],tblEmployees[TER Category],"") -> B | H19: =_xlfn.XLOOKUP(tblPayroll[[#This Row],[Employee ID]],tblEmployees[Employee ID],tblEmployees[Basic Salary],"") -> 5600000 | I19: =_xlfn.XLOOKUP(tblPayroll[[#This Row],[Employee ID]],tblEmployees[Employee ID],tblEmployees[Fixed Allowance],"") -> 600000 | J19: 0 | K19: =tblPayroll[[#This Row],[Basic Salary]]+tblPayroll[[#This Row],[Fixed Allowance]]+tblPayroll[[#This Row],[THR / Bonus]] -> 6200000 | L19: =ROUND(MIN(tblPayroll[[#This Row],[Basic Salary]]+tblPayroll[[#This Row],[Fixed Allowance]],BPJSKesCap)*R_KesEr,0) -> 248000 | M19: =ROUND((tblPayroll[[#This Row],[Basic Salary]]+tblPayroll[[#This Row],[Fixed Allowance]])*R_JKK,0) -> 14880 | N19: =ROUND((tblPayroll[[#This Row],[Basic Salary]]+tblPayroll[[#This Row],[Fixed Allowance]])*R_JKM,0) -> 18600 | O19: =ROUND((tblPayroll[[#This Row],[Basic Salary]]+tblPayroll[[#This Row],[Fixed Allowance]])*R_JHTEr,0) -> 229400 | P19: =ROUND(MIN(tblPayroll[[#This Row],[Basic Salary]]+tblPayroll[[#This Row],[Fixed Allowance]],JPCap)*R_JPEr,0) -> 124000 | Q19: =SUM(tblPayroll[[#This Row],[BPJS Health (Er)]:[JP (Er)]]) -> 634880 | R19: =tblPayroll[[#This Row],[Gross Salary]]+tblPayroll[[#This Row],[BPJS Health (Er)]]+tblPayroll[[#This Row],[JKK (Er)]]+tblPayroll[[#This Row],[JKM (Er)]] -> 6481480 | S19: =IF(tblPayroll[[#This Row],[TER Cat]]="A",_xlfn.XLOOKUP(tblPayroll[[#This Row],[PPh 21 Base]],TerA_L,TerA_R,0,-1),IF(tblPayroll[[#This Row],[TER Cat]]="B",_xlfn.XLOOKUP(tblPayroll[[#This Row],[PPh 21 Base]],TerB_L,TerB_R,0,-1),_xlfn.XLOOKUP(tblPayroll[[#This Row],[PPh 21 Base]],TerC_L,TerC_R,0,-1))) -> 0.0025 | T19: =ROUND(tblPayroll[[#This Row],[PPh 21 Base]]*tblPayroll[[#This Row],[TER Rate]],0) -> 16204 | U19: =ROUND(MIN(tblPayroll[[#This Row],[Basic Salary]]+tblPayroll[[#This Row],[Fixed Allowance]],BPJSKesCap)*R_KesEe,0) -> 62000 | V19: =ROUND((tblPayroll[[#This Row],[Basic Salary]]+tblPayroll[[#This Row],[Fixed Allowance]])*R_JHTEe,0) -> 124000 | W19: =ROUND(MIN(tblPayroll[[#This Row],[Basic Salary]]+tblPayroll[[#This Row],[Fixed Allowance]],JPCap)*R_JPEe,0) -> 62000 | X19: =tblPayroll[[#This Row],[BPJS Health (Ee)]]+tblPayroll[[#This Row],[JHT (Ee)]]+tblPayroll[[#This Row],[JP (Ee)]] -> 248000 | Y19: =tblPayroll[[#This Row],[Gross Salary]]-tblPayroll[[#This Row],[PPh 21]]-tblPayroll[[#This Row],[Employee BPJS Total]] -> 5935796 | Z19: =tblPayroll[[#This Row],[Employer BPJS Total]]+tblPayroll[[#This Row],[Employee BPJS Total]] -> 882880 | AA19: =tblPayroll[[#This Row],[Gross Salary]]+tblPayroll[[#This Row],[Employer BPJS Total]] -> 6834880 | AB19: 1130 | AD19: 5400001 | AE19: 0.0025 | AF19: 6200001 | AG19: 0.0025 | AH19: 6600001 | AI19: 0.0025
B20: 1 | C20: 46047 | D20: E014 | E20: =_xlfn.XLOOKUP(tblPayroll[[#This Row],[Employee ID]],tblEmployees[Employee ID],tblEmployees[Full Name],"") -> Maya Sari | F20: =_xlfn.XLOOKUP(tblPayroll[[#This Row],[Employee ID]],tblEmployees[Employee ID],tblEmployees[Department],"") -> Selling | G20: =_xlfn.XLOOKUP(tblPayroll[[#This Row],[Employee ID]],tblEmployees[Employee ID],tblEmployees[TER Category],"") -> A | H20: =_xlfn.XLOOKUP(tblPayroll[[#This Row],[Employee ID]],tblEmployees[Employee ID],tblEmployees[Basic Salary],"") -> 5700000 | I20: =_xlfn.XLOOKUP(tblPayroll[[#This Row],[Employee ID]],tblEmployees[Employee ID],tblEmployees[Fixed Allowance],"") -> 600000 | J20: 0 | K20: =tblPayroll[[#This Row],[Basic Salary]]+tblPayroll[[#This Row],[Fixed Allowance]]+tblPayroll[[#This Row],[THR / Bonus]] -> 6300000 | L20: =ROUND(MIN(tblPayroll[[#This Row],[Basic Salary]]+tblPayroll[[#This Row],[Fixed Allowance]],BPJSKesCap)*R_KesEr,0) -> 252000 | M20: =ROUND((tblPayroll[[#This Row],[Basic Salary]]+tblPayroll[[#This Row],[Fixed Allowance]])*R_JKK,0) -> 15120 | N20: =ROUND((tblPayroll[[#This Row],[Basic Salary]]+tblPayroll[[#This Row],[Fixed Allowance]])*R_JKM,0) -> 18900 | O20: =ROUND((tblPayroll[[#This Row],[Basic Salary]]+tblPayroll[[#This Row],[Fixed Allowance]])*R_JHTEr,0) -> 233100 | P20: =ROUND(MIN(tblPayroll[[#This Row],[Basic Salary]]+tblPayroll[[#This Row],[Fixed Allowance]],JPCap)*R_JPEr,0) -> 126000 | Q20: =SUM(tblPayroll[[#This Row],[BPJS Health (Er)]:[JP (Er)]]) -> 645120 | R20: =tblPayroll[[#This Row],[Gross Salary]]+tblPayroll[[#This Row],[BPJS Health (Er)]]+tblPayroll[[#This Row],[JKK (Er)]]+tblPayroll[[#This Row],[JKM (Er)]] -> 6586020 | S20: =IF(tblPayroll[[#This Row],[TER Cat]]="A",_xlfn.XLOOKUP(tblPayroll[[#This Row],[PPh 21 Base]],TerA_L,TerA_R,0,-1),IF(tblPayroll[[#This Row],[TER Cat]]="B",_xlfn.XLOOKUP(tblPayroll[[#This Row],[PPh 21 Base]],TerB_L,TerB_R,0,-1),_xlfn.XLOOKUP(tblPayroll[[#This Row],[PPh 21 Base]],TerC_L,TerC_R,0,-1))) -> 0.01 | T20: =ROUND(tblPayroll[[#This Row],[PPh 21 Base]]*tblPayroll[[#This Row],[TER Rate]],0) -> 65860 | U20: =ROUND(MIN(tblPayroll[[#This Row],[Basic Salary]]+tblPayroll[[#This Row],[Fixed Allowance]],BPJSKesCap)*R_KesEe,0) -> 63000 | V20: =ROUND((tblPayroll[[#This Row],[Basic Salary]]+tblPayroll[[#This Row],[Fixed Allowance]])*R_JHTEe,0) -> 126000 | W20: =ROUND(MIN(tblPayroll[[#This Row],[Basic Salary]]+tblPayroll[[#This Row],[Fixed Allowance]],JPCap)*R_JPEe,0) -> 63000 | X20: =tblPayroll[[#This Row],[BPJS Health (Ee)]]+tblPayroll[[#This Row],[JHT (Ee)]]+tblPayroll[[#This Row],[JP (Ee)]] -> 252000 | Y20: =tblPayroll[[#This Row],[Gross Salary]]-tblPayroll[[#This Row],[PPh 21]]-tblPayroll[[#This Row],[Employee BPJS Total]] -> 5982140 | Z20: =tblPayroll[[#This Row],[Employer BPJS Total]]+tblPayroll[[#This Row],[Employee BPJS Total]] -> 897120 | AA20: =tblPayroll[[#This Row],[Gross Salary]]+tblPayroll[[#This Row],[Employer BPJS Total]] -> 6945120 | AB20: 1130 | AD20: 5650001 | AE20: 0.005 | AF20: 6500001 | AG20: 0.005 | AH20: 6950001 | AI20: 0.005
B21: 1 | C21: 46047 | D21: E015 | E21: =_xlfn.XLOOKUP(tblPayroll[[#This Row],[Employee ID]],tblEmployees[Employee ID],tblEmployees[Full Name],"") -> Hendra Wijaya | F21: =_xlfn.XLOOKUP(tblPayroll[[#This Row],[Employee ID]],tblEmployees[Employee ID],tblEmployees[Department],"") -> G&A | G21: =_xlfn.XLOOKUP(tblPayroll[[#This Row],[Employee ID]],tblEmployees[Employee ID],tblEmployees[TER Category],"") -> A | H21: =_xlfn.XLOOKUP(tblPayroll[[#This Row],[Employee ID]],tblEmployees[Employee ID],tblEmployees[Basic Salary],"") -> 9500000 | I21: =_xlfn.XLOOKUP(tblPayroll[[#This Row],[Employee ID]],tblEmployees[Employee ID],tblEmployees[Fixed Allowance],"") -> 1000000 | J21: 0 | K21: =tblPayroll[[#This Row],[Basic Salary]]+tblPayroll[[#This Row],[Fixed Allowance]]+tblPayroll[[#This Row],[THR / Bonus]] -> 10500000 | L21: =ROUND(MIN(tblPayroll[[#This Row],[Basic Salary]]+tblPayroll[[#This Row],[Fixed Allowance]],BPJSKesCap)*R_KesEr,0) -> 420000 | M21: =ROUND((tblPayroll[[#This Row],[Basic Salary]]+tblPayroll[[#This Row],[Fixed Allowance]])*R_JKK,0) -> 25200 | N21: =ROUND((tblPayroll[[#This Row],[Basic Salary]]+tblPayroll[[#This Row],[Fixed Allowance]])*R_JKM,0) -> 31500 | O21: =ROUND((tblPayroll[[#This Row],[Basic Salary]]+tblPayroll[[#This Row],[Fixed Allowance]])*R_JHTEr,0) -> 388500 | P21: =ROUND(MIN(tblPayroll[[#This Row],[Basic Salary]]+tblPayroll[[#This Row],[Fixed Allowance]],JPCap)*R_JPEr,0) -> 210000 | Q21: =SUM(tblPayroll[[#This Row],[BPJS Health (Er)]:[JP (Er)]]) -> 1075200 | R21: =tblPayroll[[#This Row],[Gross Salary]]+tblPayroll[[#This Row],[BPJS Health (Er)]]+tblPayroll[[#This Row],[JKK (Er)]]+tblPayroll[[#This Row],[JKM (Er)]] -> 10976700 | S21: =IF(tblPayroll[[#This Row],[TER Cat]]="A",_xlfn.XLOOKUP(tblPayroll[[#This Row],[PPh 21 Base]],TerA_L,TerA_R,0,-1),IF(tblPayroll[[#This Row],[TER Cat]]="B",_xlfn.XLOOKUP(tblPayroll[[#This Row],[PPh 21 Base]],TerB_L,TerB_R,0,-1),_xlfn.XLOOKUP(tblPayroll[[#This Row],[PPh 21 Base]],TerC_L,TerC_R,0,-1))) -> 0.03 | T21: =ROUND(tblPayroll[[#This Row],[PPh 21 Base]]*tblPayroll[[#This Row],[TER Rate]],0) -> 329301 | U21: =ROUND(MIN(tblPayroll[[#This Row],[Basic Salary]]+tblPayroll[[#This Row],[Fixed Allowance]],BPJSKesCap)*R_KesEe,0) -> 105000 | V21: =ROUND((tblPayroll[[#This Row],[Basic Salary]]+tblPayroll[[#This Row],[Fixed Allowance]])*R_JHTEe,0) -> 210000 | W21: =ROUND(MIN(tblPayroll[[#This Row],[Basic Salary]]+tblPayroll[[#This Row],[Fixed Allowance]],JPCap)*R_JPEe,0) -> 105000 | X21: =tblPayroll[[#This Row],[BPJS Health (Ee)]]+tblPayroll[[#This Row],[JHT (Ee)]]+tblPayroll[[#This Row],[JP (Ee)]] -> 420000 | Y21: =tblPayroll[[#This Row],[Gross Salary]]-tblPayroll[[#This Row],[PPh 21]]-tblPayroll[[#This Row],[Employee BPJS Total]] -> 9750699 | Z21: =tblPayroll[[#This Row],[Employer BPJS Total]]+tblPayroll[[#This Row],[Employee BPJS Total]] -> 1495200 | AA21: =tblPayroll[[#This Row],[Gross Salary]]+tblPayroll[[#This Row],[Employer BPJS Total]] -> 11575200 | AB21: 1130 | AD21: 5950001 | AE21: 0.0075 | AF21: 6850001 | AG21: 0.0075 | AH21: 7350001 | AI21: 0.0075
B22: 2 | C22: 46078 | D22: E001 | E22: =_xlfn.XLOOKUP(tblPayroll[[#This Row],[Employee ID]],tblEmployees[Employee ID],tblEmployees[Full Name],"") -> Budi Santoso | F22: =_xlfn.XLOOKUP(tblPayroll[[#This Row],[Employee ID]],tblEmployees[Employee ID],tblEmployees[Department],"") -> G&A | G22: =_xlfn.XLOOKUP(tblPayroll[[#This Row],[Employee ID]],tblEmployees[Employee ID],tblEmployees[TER Category],"") -> B | H22: =_xlfn.XLOOKUP(tblPayroll[[#This Row],[Employee ID]],tblEmployees[Employee ID],tblEmployees[Basic Salary],"") -> 25000000 | I22: =_xlfn.XLOOKUP(tblPayroll[[#This Row],[Employee ID]],tblEmployees[Employee ID],tblEmployees[Fixed Allowance],"") -> 4000000 | J22: 0 | K22: =tblPayroll[[#This Row],[Basic Salary]]+tblPayroll[[#This Row],[Fixed Allowance]]+tblPayroll[[#This Row],[THR / Bonus]] -> 29000000 | L22: =ROUND(MIN(tblPayroll[[#This Row],[Basic Salary]]+tblPayroll[[#This Row],[Fixed Allowance]],BPJSKesCap)*R_KesEr,0) -> 480000 | M22: =ROUND((tblPayroll[[#This Row],[Basic Salary]]+tblPayroll[[#This Row],[Fixed Allowance]])*R_JKK,0) -> 69600 | N22: =ROUND((tblPayroll[[#This Row],[Basic Salary]]+tblPayroll[[#This Row],[Fixed Allowance]])*R_JKM,0) -> 87000 | O22: =ROUND((tblPayroll[[#This Row],[Basic Salary]]+tblPayroll[[#This Row],[Fixed Allowance]])*R_JHTEr,0) -> 1073000 | P22: =ROUND(MIN(tblPayroll[[#This Row],[Basic Salary]]+tblPayroll[[#This Row],[Fixed Allowance]],JPCap)*R_JPEr,0) -> 210948 | Q22: =SUM(tblPayroll[[#This Row],[BPJS Health (Er)]:[JP (Er)]]) -> 1920548 | R22: =tblPayroll[[#This Row],[Gross Salary]]+tblPayroll[[#This Row],[BPJS Health (Er)]]+tblPayroll[[#This Row],[JKK (Er)]]+tblPayroll[[#This Row],[JKM (Er)]] -> 29636600 | S22: =IF(tblPayroll[[#This Row],[TER Cat]]="A",_xlfn.XLOOKUP(tblPayroll[[#This Row],[PPh 21 Base]],TerA_L,TerA_R,0,-1),IF(tblPayroll[[#This Row],[TER Cat]]="B",_xlfn.XLOOKUP(tblPayroll[[#This Row],[PPh 21 Base]],TerB_L,TerB_R,0,-1),_xlfn.XLOOKUP(tblPayroll[[#This Row],[PPh 21 Base]],TerC_L,TerC_R,0,-1))) -> 0.12 | T22: =ROUND(tblPayroll[[#This Row],[PPh 21 Base]]*tblPayroll[[#This Row],[TER Rate]],0) -> 3556392 | U22: =ROUND(MIN(tblPayroll[[#This Row],[Basic Salary]]+tblPayroll[[#This Row],[Fixed Allowance]],BPJSKesCap)*R_KesEe,0) -> 120000 | V22: =ROUND((tblPayroll[[#This Row],[Basic Salary]]+tblPayroll[[#This Row],[Fixed Allowance]])*R_JHTEe,0) -> 580000 | W22: =ROUND(MIN(tblPayroll[[#This Row],[Basic Salary]]+tblPayroll[[#This Row],[Fixed Allowance]],JPCap)*R_JPEe,0) -> 105474 | X22: =tblPayroll[[#This Row],[BPJS Health (Ee)]]+tblPayroll[[#This Row],[JHT (Ee)]]+tblPayroll[[#This Row],[JP (Ee)]] -> 805474 | Y22: =tblPayroll[[#This Row],[Gross Salary]]-tblPayroll[[#This Row],[PPh 21]]-tblPayroll[[#This Row],[Employee BPJS Total]] -> 24638134 | Z22: =tblPayroll[[#This Row],[Employer BPJS Total]]+tblPayroll[[#This Row],[Employee BPJS Total]] -> 2726022 | AA22: =tblPayroll[[#This Row],[Gross Salary]]+tblPayroll[[#This Row],[Employer BPJS Total]] -> 30920548 | AB22: 1130 | AD22: 6300001 | AE22: 0.01 | AF22: 7300001 | AG22: 0.01 | AH22: 7800001 | AI22: 0.01
B23: 2 | C23: 46078 | D23: E002 | E23: =_xlfn.XLOOKUP(tblPayroll[[#This Row],[Employee ID]],tblEmployees[Employee ID],tblEmployees[Full Name],"") -> Siti Rahmawati | F23: =_xlfn.XLOOKUP(tblPayroll[[#This Row],[Employee ID]],tblEmployees[Employee ID],tblEmployees[Department],"") -> G&A | G23: =_xlfn.XLOOKUP(tblPayroll[[#This Row],[Employee ID]],tblEmployees[Employee ID],tblEmployees[TER Category],"") -> B | H23: =_xlfn.XLOOKUP(tblPayroll[[#This Row],[Employee ID]],tblEmployees[Employee ID],tblEmployees[Basic Salary],"") -> 20000000 | I23: =_xlfn.XLOOKUP(tblPayroll[[#This Row],[Employee ID]],tblEmployees[Employee ID],tblEmployees[Fixed Allowance],"") -> 3000000 | J23: 0 | K23: =tblPayroll[[#This Row],[Basic Salary]]+tblPayroll[[#This Row],[Fixed Allowance]]+tblPayroll[[#This Row],[THR / Bonus]] -> 23000000 | L23: =ROUND(MIN(tblPayroll[[#This Row],[Basic Salary]]+tblPayroll[[#This Row],[Fixed Allowance]],BPJSKesCap)*R_KesEr,0) -> 480000 | M23: =ROUND((tblPayroll[[#This Row],[Basic Salary]]+tblPayroll[[#This Row],[Fixed Allowance]])*R_JKK,0) -> 55200 | N23: =ROUND((tblPayroll[[#This Row],[Basic Salary]]+tblPayroll[[#This Row],[Fixed Allowance]])*R_JKM,0) -> 69000 | O23: =ROUND((tblPayroll[[#This Row],[Basic Salary]]+tblPayroll[[#This Row],[Fixed Allowance]])*R_JHTEr,0) -> 851000 | P23: =ROUND(MIN(tblPayroll[[#This Row],[Basic Salary]]+tblPayroll[[#This Row],[Fixed Allowance]],JPCap)*R_JPEr,0) -> 210948 | Q23: =SUM(tblPayroll[[#This Row],[BPJS Health (Er)]:[JP (Er)]]) -> 1666148 | R23: =tblPayroll[[#This Row],[Gross Salary]]+tblPayroll[[#This Row],[BPJS Health (Er)]]+tblPayroll[[#This Row],[JKK (Er)]]+tblPayroll[[#This Row],[JKM (Er)]] -> 23604200 | S23: =IF(tblPayroll[[#This Row],[TER Cat]]="A",_xlfn.XLOOKUP(tblPayroll[[#This Row],[PPh 21 Base]],TerA_L,TerA_R,0,-1),IF(tblPayroll[[#This Row],[TER Cat]]="B",_xlfn.XLOOKUP(tblPayroll[[#This Row],[PPh 21 Base]],TerB_L,TerB_R,0,-1),_xlfn.XLOOKUP(tblPayroll[[#This Row],[PPh 21 Base]],TerC_L,TerC_R,0,-1))) -> 0.09 | T23: =ROUND(tblPayroll[[#This Row],[PPh 21 Base]]*tblPayroll[[#This Row],[TER Rate]],0) -> 2124378 | U23: =ROUND(MIN(tblPayroll[[#This Row],[Basic Salary]]+tblPayroll[[#This Row],[Fixed Allowance]],BPJSKesCap)*R_KesEe,0) -> 120000 | V23: =ROUND((tblPayroll[[#This Row],[Basic Salary]]+tblPayroll[[#This Row],[Fixed Allowance]])*R_JHTEe,0) -> 460000 | W23: =ROUND(MIN(tblPayroll[[#This Row],[Basic Salary]]+tblPayroll[[#This Row],[Fixed Allowance]],JPCap)*R_JPEe,0) -> 105474 | X23: =tblPayroll[[#This Row],[BPJS Health (Ee)]]+tblPayroll[[#This Row],[JHT (Ee)]]+tblPayroll[[#This Row],[JP (Ee)]] -> 685474 | Y23: =tblPayroll[[#This Row],[Gross Salary]]-tblPayroll[[#This Row],[PPh 21]]-tblPayroll[[#This Row],[Employee BPJS Total]] -> 20190148 | Z23: =tblPayroll[[#This Row],[Employer BPJS Total]]+tblPayroll[[#This Row],[Employee BPJS Total]] -> 2351622 | AA23: =tblPayroll[[#This Row],[Gross Salary]]+tblPayroll[[#This Row],[Employer BPJS Total]] -> 24666148 | AB23: 1130 | AD23: 6750001 | AE23: 0.0125 | AF23: 9200001 | AG23: 0.015 | AH23: 8850001 | AI23: 0.0125
B24: 2 | C24: 46078 | D24: E003 | E24: =_xlfn.XLOOKUP(tblPayroll[[#This Row],[Employee ID]],tblEmployees[Employee ID],tblEmployees[Full Name],"") -> Dewi Lestari | F24: =_xlfn.XLOOKUP(tblPayroll[[#This Row],[Employee ID]],tblEmployees[Employee ID],tblEmployees[Department],"") -> G&A | G24: =_xlfn.XLOOKUP(tblPayroll[[#This Row],[Employee ID]],tblEmployees[Employee ID],tblEmployees[TER Category],"") -> A | H24: =_xlfn.XLOOKUP(tblPayroll[[#This Row],[Employee ID]],tblEmployees[Employee ID],tblEmployees[Basic Salary],"") -> 15000000 | I24: =_xlfn.XLOOKUP(tblPayroll[[#This Row],[Employee ID]],tblEmployees[Employee ID],tblEmployees[Fixed Allowance],"") -> 2000000 | J24: 0 | K24: =tblPayroll[[#This Row],[Basic Salary]]+tblPayroll[[#This Row],[Fixed Allowance]]+tblPayroll[[#This Row],[THR / Bonus]] -> 17000000 | L24: =ROUND(MIN(tblPayroll[[#This Row],[Basic Salary]]+tblPayroll[[#This Row],[Fixed Allowance]],BPJSKesCap)*R_KesEr,0) -> 480000 | M24: =ROUND((tblPayroll[[#This Row],[Basic Salary]]+tblPayroll[[#This Row],[Fixed Allowance]])*R_JKK,0) -> 40800 | N24: =ROUND((tblPayroll[[#This Row],[Basic Salary]]+tblPayroll[[#This Row],[Fixed Allowance]])*R_JKM,0) -> 51000 | O24: =ROUND((tblPayroll[[#This Row],[Basic Salary]]+tblPayroll[[#This Row],[Fixed Allowance]])*R_JHTEr,0) -> 629000 | P24: =ROUND(MIN(tblPayroll[[#This Row],[Basic Salary]]+tblPayroll[[#This Row],[Fixed Allowance]],JPCap)*R_JPEr,0) -> 210948 | Q24: =SUM(tblPayroll[[#This Row],[BPJS Health (Er)]:[JP (Er)]]) -> 1411748 | R24: =tblPayroll[[#This Row],[Gross Salary]]+tblPayroll[[#This Row],[BPJS Health (Er)]]+tblPayroll[[#This Row],[JKK (Er)]]+tblPayroll[[#This Row],[JKM (Er)]] -> 17571800 | S24: =IF(tblPayroll[[#This Row],[TER Cat]]="A",_xlfn.XLOOKUP(tblPayroll[[#This Row],[PPh 21 Base]],TerA_L,TerA_R,0,-1),IF(tblPayroll[[#This Row],[TER Cat]]="B",_xlfn.XLOOKUP(tblPayroll[[#This Row],[PPh 21 Base]],TerB_L,TerB_R,0,-1),_xlfn.XLOOKUP(tblPayroll[[#This Row],[PPh 21 Base]],TerC_L,TerC_R,0,-1))) -> 0.08 | T24: =ROUND(tblPayroll[[#This Row],[PPh 21 Base]]*tblPayroll[[#This Row],[TER Rate]],0) -> 1405744 | U24: =ROUND(MIN(tblPayroll[[#This Row],[Basic Salary]]+tblPayroll[[#This Row],[Fixed Allowance]],BPJSKesCap)*R_KesEe,0) -> 120000 | V24: =ROUND((tblPayroll[[#This Row],[Basic Salary]]+tblPayroll[[#This Row],[Fixed Allowance]])*R_JHTEe,0) -> 340000 | W24: =ROUND(MIN(tblPayroll[[#This Row],[Basic Salary]]+tblPayroll[[#This Row],[Fixed Allowance]],JPCap)*R_JPEe,0) -> 105474 | X24: =tblPayroll[[#This Row],[BPJS Health (Ee)]]+tblPayroll[[#This Row],[JHT (Ee)]]+tblPayroll[[#This Row],[JP (Ee)]] -> 565474 | Y24: =tblPayroll[[#This Row],[Gross Salary]]-tblPayroll[[#This Row],[PPh 21]]-tblPayroll[[#This Row],[Employee BPJS Total]] -> 15028782 | Z24: =tblPayroll[[#This Row],[Employer BPJS Total]]+tblPayroll[[#This Row],[Employee BPJS Total]] -> 1977222 | AA24: =tblPayroll[[#This Row],[Gross Salary]]+tblPayroll[[#This Row],[Employer BPJS Total]] -> 18411748 | AB24: 1130 | AD24: 7500001 | AE24: 0.015 | AF24: 10750001 | AG24: 0.02 | AH24: 9800001 | AI24: 0.015
B25: 2 | C25: 46078 | D25: E004 | E25: =_xlfn.XLOOKUP(tblPayroll[[#This Row],[Employee ID]],tblEmployees[Employee ID],tblEmployees[Full Name],"") -> Agus Prasetyo | F25: =_xlfn.XLOOKUP(tblPayroll[[#This Row],[Employee ID]],tblEmployees[Employee ID],tblEmployees[Department],"") -> Selling | G25: =_xlfn.XLOOKUP(tblPayroll[[#This Row],[Employee ID]],tblEmployees[Employee ID],tblEmployees[TER Category],"") -> B | H25: =_xlfn.XLOOKUP(tblPayroll[[#This Row],[Employee ID]],tblEmployees[Employee ID],tblEmployees[Basic Salary],"") -> 14000000 | I25: =_xlfn.XLOOKUP(tblPayroll[[#This Row],[Employee ID]],tblEmployees[Employee ID],tblEmployees[Fixed Allowance],"") -> 2000000 | J25: 0 | K25: =tblPayroll[[#This Row],[Basic Salary]]+tblPayroll[[#This Row],[Fixed Allowance]]+tblPayroll[[#This Row],[THR / Bonus]] -> 16000000 | L25: =ROUND(MIN(tblPayroll[[#This Row],[Basic Salary]]+tblPayroll[[#This Row],[Fixed Allowance]],BPJSKesCap)*R_KesEr,0) -> 480000 | M25: =ROUND((tblPayroll[[#This Row],[Basic Salary]]+tblPayroll[[#This Row],[Fixed Allowance]])*R_JKK,0) -> 38400 | N25: =ROUND((tblPayroll[[#This Row],[Basic Salary]]+tblPayroll[[#This Row],[Fixed Allowance]])*R_JKM,0) -> 48000 | O25: =ROUND((tblPayroll[[#This Row],[Basic Salary]]+tblPayroll[[#This Row],[Fixed Allowance]])*R_JHTEr,0) -> 592000 | P25: =ROUND(MIN(tblPayroll[[#This Row],[Basic Salary]]+tblPayroll[[#This Row],[Fixed Allowance]],JPCap)*R_JPEr,0) -> 210948 | Q25: =SUM(tblPayroll[[#This Row],[BPJS Health (Er)]:[JP (Er)]]) -> 1369348 | R25: =tblPayroll[[#This Row],[Gross Salary]]+tblPayroll[[#This Row],[BPJS Health (Er)]]+tblPayroll[[#This Row],[JKK (Er)]]+tblPayroll[[#This Row],[JKM (Er)]] -> 16566400 | S25: =IF(tblPayroll[[#This Row],[TER Cat]]="A",_xlfn.XLOOKUP(tblPayroll[[#This Row],[PPh 21 Base]],TerA_L,TerA_R,0,-1),IF(tblPayroll[[#This Row],[TER Cat]]="B",_xlfn.XLOOKUP(tblPayroll[[#This Row],[PPh 21 Base]],TerB_L,TerB_R,0,-1),_xlfn.XLOOKUP(tblPayroll[[#This Row],[PPh 21 Base]],TerC_L,TerC_R,0,-1))) -> 0.07 | T25: =ROUND(tblPayroll[[#This Row],[PPh 21 Base]]*tblPayroll[[#This Row],[TER Rate]],0) -> 1159648 | U25: =ROUND(MIN(tblPayroll[[#This Row],[Basic Salary]]+tblPayroll[[#This Row],[Fixed Allowance]],BPJSKesCap)*R_KesEe,0) -> 120000 | V25: =ROUND((tblPayroll[[#This Row],[Basic Salary]]+tblPayroll[[#This Row],[Fixed Allowance]])*R_JHTEe,0) -> 320000 | W25: =ROUND(MIN(tblPayroll[[#This Row],[Basic Salary]]+tblPayroll[[#This Row],[Fixed Allowance]],JPCap)*R_JPEe,0) -> 105474 | X25: =tblPayroll[[#This Row],[BPJS Health (Ee)]]+tblPayroll[[#This Row],[JHT (Ee)]]+tblPayroll[[#This Row],[JP (Ee)]] -> 545474 | Y25: =tblPayroll[[#This Row],[Gross Salary]]-tblPayroll[[#This Row],[PPh 21]]-tblPayroll[[#This Row],[Employee BPJS Total]] -> 14294878 | Z25: =tblPayroll[[#This Row],[Employer BPJS Total]]+tblPayroll[[#This Row],[Employee BPJS Total]] -> 1914822 | AA25: =tblPayroll[[#This Row],[Gross Salary]]+tblPayroll[[#This Row],[Employer BPJS Total]] -> 17369348 | AB25: 1130 | AD25: 8550001 | AE25: 0.0175 | AF25: 11250001 | AG25: 0.025 | AH25: 10950001 | AI25: 0.0175
B26: 2 | C26: 46078 | D26: E005 | E26: =_xlfn.XLOOKUP(tblPayroll[[#This Row],[Employee ID]],tblEmployees[Employee ID],tblEmployees[Full Name],"") -> Rina Kartika | F26: =_xlfn.XLOOKUP(tblPayroll[[#This Row],[Employee ID]],tblEmployees[Employee ID],tblEmployees[Department],"") -> Selling | G26: =_xlfn.XLOOKUP(tblPayroll[[#This Row],[Employee ID]],tblEmployees[Employee ID],tblEmployees[TER Category],"") -> A | H26: =_xlfn.XLOOKUP(tblPayroll[[#This Row],[Employee ID]],tblEmployees[Employee ID],tblEmployees[Basic Salary],"") -> 12000000 | I26: =_xlfn.XLOOKUP(tblPayroll[[#This Row],[Employee ID]],tblEmployees[Employee ID],tblEmployees[Fixed Allowance],"") -> 1500000 | J26: 0 | K26: =tblPayroll[[#This Row],[Basic Salary]]+tblPayroll[[#This Row],[Fixed Allowance]]+tblPayroll[[#This Row],[THR / Bonus]] -> 13500000 | L26: =ROUND(MIN(tblPayroll[[#This Row],[Basic Salary]]+tblPayroll[[#This Row],[Fixed Allowance]],BPJSKesCap)*R_KesEr,0) -> 480000 | M26: =ROUND((tblPayroll[[#This Row],[Basic Salary]]+tblPayroll[[#This Row],[Fixed Allowance]])*R_JKK,0) -> 32400 | N26: =ROUND((tblPayroll[[#This Row],[Basic Salary]]+tblPayroll[[#This Row],[Fixed Allowance]])*R_JKM,0) -> 40500 | O26: =ROUND((tblPayroll[[#This Row],[Basic Salary]]+tblPayroll[[#This Row],[Fixed Allowance]])*R_JHTEr,0) -> 499500 | P26: =ROUND(MIN(tblPayroll[[#This Row],[Basic Salary]]+tblPayroll[[#This Row],[Fixed Allowance]],JPCap)*R_JPEr,0) -> 210948 | Q26: =SUM(tblPayroll[[#This Row],[BPJS Health (Er)]:[JP (Er)]]) -> 1263348 | R26: =tblPayroll[[#This Row],[Gross Salary]]+tblPayroll[[#This Row],[BPJS Health (Er)]]+tblPayroll[[#This Row],[JKK (Er)]]+tblPayroll[[#This Row],[JKM (Er)]] -> 14052900 | S26: =IF(tblPayroll[[#This Row],[TER Cat]]="A",_xlfn.XLOOKUP(tblPayroll[[#This Row],[PPh 21 Base]],TerA_L,TerA_R,0,-1),IF(tblPayroll[[#This Row],[TER Cat]]="B",_xlfn.XLOOKUP(tblPayroll[[#This Row],[PPh 21 Base]],TerB_L,TerB_R,0,-1),_xlfn.XLOOKUP(tblPayroll[[#This Row],[PPh 21 Base]],TerC_L,TerC_R,0,-1))) -> 0.06 | T26: =ROUND(tblPayroll[[#This Row],[PPh 21 Base]]*tblPayroll[[#This Row],[TER Rate]],0) -> 843174 | U26: =ROUND(MIN(tblPayroll[[#This Row],[Basic Salary]]+tblPayroll[[#This Row],[Fixed Allowance]],BPJSKesCap)*R_KesEe,0) -> 120000 | V26: =ROUND((tblPayroll[[#This Row],[Basic Salary]]+tblPayroll[[#This Row],[Fixed Allowance]])*R_JHTEe,0) -> 270000 | W26: =ROUND(MIN(tblPayroll[[#This Row],[Basic Salary]]+tblPayroll[[#This Row],[Fixed Allowance]],JPCap)*R_JPEe,0) -> 105474 | X26: =tblPayroll[[#This Row],[BPJS Health (Ee)]]+tblPayroll[[#This Row],[JHT (Ee)]]+tblPayroll[[#This Row],[JP (Ee)]] -> 495474 | Y26: =tblPayroll[[#This Row],[Gross Salary]]-tblPayroll[[#This Row],[PPh 21]]-tblPayroll[[#This Row],[Employee BPJS Total]] -> 12161352 | Z26: =tblPayroll[[#This Row],[Employer BPJS Total]]+tblPayroll[[#This Row],[Employee BPJS Total]] -> 1758822 | AA26: =tblPayroll[[#This Row],[Gross Salary]]+tblPayroll[[#This Row],[Employer BPJS Total]] -> 14763348 | AB26: 1130 | AD26: 9650001 | AE26: 0.02 | AF26: 11600001 | AG26: 0.03 | AH26: 11200001 | AI26: 0.02
B27: 2 | C27: 46078 | D27: E006 | E27: =_xlfn.XLOOKUP(tblPayroll[[#This Row],[Employee ID]],tblEmployees[Employee ID],tblEmployees[Full Name],"") -> Andi Saputra | F27: =_xlfn.XLOOKUP(tblPayroll[[#This Row],[Employee ID]],tblEmployees[Employee ID],tblEmployees[Department],"") -> G&A | G27: =_xlfn.XLOOKUP(tblPayroll[[#This Row],[Employee ID]],tblEmployees[Employee ID],tblEmployees[TER Category],"") -> A | H27: =_xlfn.XLOOKUP(tblPayroll[[#This Row],[Employee ID]],tblEmployees[Employee ID],tblEmployees[Basic Salary],"") -> 8500000 | I27: =_xlfn.XLOOKUP(tblPayroll[[#This Row],[Employee ID]],tblEmployees[Employee ID],tblEmployees[Fixed Allowance],"") -> 1000000 | J27: 0 | K27: =tblPayroll[[#This Row],[Basic Salary]]+tblPayroll[[#This Row],[Fixed Allowance]]+tblPayroll[[#This Row],[THR / Bonus]] -> 9500000 | L27: =ROUND(MIN(tblPayroll[[#This Row],[Basic Salary]]+tblPayroll[[#This Row],[Fixed Allowance]],BPJSKesCap)*R_KesEr,0) -> 380000 | M27: =ROUND((tblPayroll[[#This Row],[Basic Salary]]+tblPayroll[[#This Row],[Fixed Allowance]])*R_JKK,0) -> 22800 | N27: =ROUND((tblPayroll[[#This Row],[Basic Salary]]+tblPayroll[[#This Row],[Fixed Allowance]])*R_JKM,0) -> 28500 | O27: =ROUND((tblPayroll[[#This Row],[Basic Salary]]+tblPayroll[[#This Row],[Fixed Allowance]])*R_JHTEr,0) -> 351500 | P27: =ROUND(MIN(tblPayroll[[#This Row],[Basic Salary]]+tblPayroll[[#This Row],[Fixed Allowance]],JPCap)*R_JPEr,0) -> 190000 | Q27: =SUM(tblPayroll[[#This Row],[BPJS Health (Er)]:[JP (Er)]]) -> 972800 | R27: =tblPayroll[[#This Row],[Gross Salary]]+tblPayroll[[#This Row],[BPJS Health (Er)]]+tblPayroll[[#This Row],[JKK (Er)]]+tblPayroll[[#This Row],[JKM (Er)]] -> 9931300 | S27: =IF(tblPayroll[[#This Row],[TER Cat]]="A",_xlfn.XLOOKUP(tblPayroll[[#This Row],[PPh 21 Base]],TerA_L,TerA_R,0,-1),IF(tblPayroll[[#This Row],[TER Cat]]="B",_xlfn.XLOOKUP(tblPayroll[[#This Row],[PPh 21 Base]],TerB_L,TerB_R,0,-1),_xlfn.XLOOKUP(tblPayroll[[#This Row],[PPh 21 Base]],TerC_L,TerC_R,0,-1))) -> 0.02 | T27: =ROUND(tblPayroll[[#This Row],[PPh 21 Base]]*tblPayroll[[#This Row],[TER Rate]],0) -> 198626 | U27: =ROUND(MIN(tblPayroll[[#This Row],[Basic Salary]]+tblPayroll[[#This Row],[Fixed Allowance]],BPJSKesCap)*R_KesEe,0) -> 95000 | V27: =ROUND((tblPayroll[[#This Row],[Basic Salary]]+tblPayroll[[#This Row],[Fixed Allowance]])*R_JHTEe,0) -> 190000 | W27: =ROUND(MIN(tblPayroll[[#This Row],[Basic Salary]]+tblPayroll[[#This Row],[Fixed Allowance]],JPCap)*R_JPEe,0) -> 95000 | X27: =tblPayroll[[#This Row],[BPJS Health (Ee)]]+tblPayroll[[#This Row],[JHT (Ee)]]+tblPayroll[[#This Row],[JP (Ee)]] -> 380000 | Y27: =tblPayroll[[#This Row],[Gross Salary]]-tblPayroll[[#This Row],[PPh 21]]-tblPayroll[[#This Row],[Employee BPJS Total]] -> 8921374 | Z27: =tblPayroll[[#This Row],[Employer BPJS Total]]+tblPayroll[[#This Row],[Employee BPJS Total]] -> 1352800 | AA27: =tblPayroll[[#This Row],[Gross Salary]]+tblPayroll[[#This Row],[Employer BPJS Total]] -> 10472800 | AB27: 1130 | AD27: 10050001 | AE27: 0.0225 | AF27: 12600001 | AG27: 0.04 | AH27: 12050001 | AI27: 0.03
B28: 2 | C28: 46078 | D28: E007 | E28: =_xlfn.XLOOKUP(tblPayroll[[#This Row],[Employee ID]],tblEmployees[Employee ID],tblEmployees[Full Name],"") -> Fitri Handayani | F28: =_xlfn.XLOOKUP(tblPayroll[[#This Row],[Employee ID]],tblEmployees[Employee ID],tblEmployees[Department],"") -> G&A | G28: =_xlfn.XLOOKUP(tblPayroll[[#This Row],[Employee ID]],tblEmployees[Employee ID],tblEmployees[TER Category],"") -> A | H28: =_xlfn.XLOOKUP(tblPayroll[[#This Row],[Employee ID]],tblEmployees[Employee ID],tblEmployees[Basic Salary],"") -> 8000000 | I28: =_xlfn.XLOOKUP(tblPayroll[[#This Row],[Employee ID]],tblEmployees[Employee ID],tblEmployees[Fixed Allowance],"") -> 1000000 | J28: 0 | K28: =tblPayroll[[#This Row],[Basic Salary]]+tblPayroll[[#This Row],[Fixed Allowance]]+tblPayroll[[#This Row],[THR / Bonus]] -> 9000000 | L28: =ROUND(MIN(tblPayroll[[#This Row],[Basic Salary]]+tblPayroll[[#This Row],[Fixed Allowance]],BPJSKesCap)*R_KesEr,0) -> 360000 | M28: =ROUND((tblPayroll[[#This Row],[Basic Salary]]+tblPayroll[[#This Row],[Fixed Allowance]])*R_JKK,0) -> 21600 | N28: =ROUND((tblPayroll[[#This Row],[Basic Salary]]+tblPayroll[[#This Row],[Fixed Allowance]])*R_JKM,0) -> 27000 | O28: =ROUND((tblPayroll[[#This Row],[Basic Salary]]+tblPayroll[[#This Row],[Fixed Allowance]])*R_JHTEr,0) -> 333000 | P28: =ROUND(MIN(tblPayroll[[#This Row],[Basic Salary]]+tblPayroll[[#This Row],[Fixed Allowance]],JPCap)*R_JPEr,0) -> 180000 | Q28: =SUM(tblPayroll[[#This Row],[BPJS Health (Er)]:[JP (Er)]]) -> 921600 | R28: =tblPayroll[[#This Row],[Gross Salary]]+tblPayroll[[#This Row],[BPJS Health (Er)]]+tblPayroll[[#This Row],[JKK (Er)]]+tblPayroll[[#This Row],[JKM (Er)]] -> 9408600 | S28: =IF(tblPayroll[[#This Row],[TER Cat]]="A",_xlfn.XLOOKUP(tblPayroll[[#This Row],[PPh 21 Base]],TerA_L,TerA_R,0,-1),IF(tblPayroll[[#This Row],[TER Cat]]="B",_xlfn.XLOOKUP(tblPayroll[[#This Row],[PPh 21 Base]],TerB_L,TerB_R,0,-1),_xlfn.XLOOKUP(tblPayroll[[#This Row],[PPh 21 Base]],TerC_L,TerC_R,0,-1))) -> 0.0175 | T28: =ROUND(tblPayroll[[#This Row],[PPh 21 Base]]*tblPayroll[[#This Row],[TER Rate]],0) -> 164651 | U28: =ROUND(MIN(tblPayroll[[#This Row],[Basic Salary]]+tblPayroll[[#This Row],[Fixed Allowance]],BPJSKesCap)*R_KesEe,0) -> 90000 | V28: =ROUND((tblPayroll[[#This Row],[Basic Salary]]+tblPayroll[[#This Row],[Fixed Allowance]])*R_JHTEe,0) -> 180000 | W28: =ROUND(MIN(tblPayroll[[#This Row],[Basic Salary]]+tblPayroll[[#This Row],[Fixed Allowance]],JPCap)*R_JPEe,0) -> 90000 | X28: =tblPayroll[[#This Row],[BPJS Health (Ee)]]+tblPayroll[[#This Row],[JHT (Ee)]]+tblPayroll[[#This Row],[JP (Ee)]] -> 360000 | Y28: =tblPayroll[[#This Row],[Gross Salary]]-tblPayroll[[#This Row],[PPh 21]]-tblPayroll[[#This Row],[Employee BPJS Total]] -> 8475349 | Z28: =tblPayroll[[#This Row],[Employer BPJS Total]]+tblPayroll[[#This Row],[Employee BPJS Total]] -> 1281600 | AA28: =tblPayroll[[#This Row],[Gross Salary]]+tblPayroll[[#This Row],[Employer BPJS Total]] -> 9921600 | AB28: 1130 | AD28: 10350001 | AE28: 0.025 | AF28: 13600001 | AG28: 0.05 | AH28: 12950001 | AI28: 0.04
B29: 2 | C29: 46078 | D29: E008 | E29: =_xlfn.XLOOKUP(tblPayroll[[#This Row],[Employee ID]],tblEmployees[Employee ID],tblEmployees[Full Name],"") -> Rizky Ramadhan | F29: =_xlfn.XLOOKUP(tblPayroll[[#This Row],[Employee ID]],tblEmployees[Employee ID],tblEmployees[Department],"") -> Selling | G29: =_xlfn.XLOOKUP(tblPayroll[[#This Row],[Employee ID]],tblEmployees[Employee ID],tblEmployees[TER Category],"") -> A | H29: =_xlfn.XLOOKUP(tblPayroll[[#This Row],[Employee ID]],tblEmployees[Employee ID],tblEmployees[Basic Salary],"") -> 9000000 | I29: =_xlfn.XLOOKUP(tblPayroll[[#This Row],[Employee ID]],tblEmployees[Employee ID],tblEmployees[Fixed Allowance],"") -> 1500000 | J29: 0 | K29: =tblPayroll[[#This Row],[Basic Salary]]+tblPayroll[[#This Row],[Fixed Allowance]]+tblPayroll[[#This Row],[THR / Bonus]] -> 10500000 | L29: =ROUND(MIN(tblPayroll[[#This Row],[Basic Salary]]+tblPayroll[[#This Row],[Fixed Allowance]],BPJSKesCap)*R_KesEr,0) -> 420000 | M29: =ROUND((tblPayroll[[#This Row],[Basic Salary]]+tblPayroll[[#This Row],[Fixed Allowance]])*R_JKK,0) -> 25200 | N29: =ROUND((tblPayroll[[#This Row],[Basic Salary]]+tblPayroll[[#This Row],[Fixed Allowance]])*R_JKM,0) -> 31500 | O29: =ROUND((tblPayroll[[#This Row],[Basic Salary]]+tblPayroll[[#This Row],[Fixed Allowance]])*R_JHTEr,0) -> 388500 | P29: =ROUND(MIN(tblPayroll[[#This Row],[Basic Salary]]+tblPayroll[[#This Row],[Fixed Allowance]],JPCap)*R_JPEr,0) -> 210000 | Q29: =SUM(tblPayroll[[#This Row],[BPJS Health (Er)]:[JP (Er)]]) -> 1075200 | R29: =tblPayroll[[#This Row],[Gross Salary]]+tblPayroll[[#This Row],[BPJS Health (Er)]]+tblPayroll[[#This Row],[JKK (Er)]]+tblPayroll[[#This Row],[JKM (Er)]] -> 10976700 | S29: =IF(tblPayroll[[#This Row],[TER Cat]]="A",_xlfn.XLOOKUP(tblPayroll[[#This Row],[PPh 21 Base]],TerA_L,TerA_R,0,-1),IF(tblPayroll[[#This Row],[TER Cat]]="B",_xlfn.XLOOKUP(tblPayroll[[#This Row],[PPh 21 Base]],TerB_L,TerB_R,0,-1),_xlfn.XLOOKUP(tblPayroll[[#This Row],[PPh 21 Base]],TerC_L,TerC_R,0,-1))) -> 0.03 | T29: =ROUND(tblPayroll[[#This Row],[PPh 21 Base]]*tblPayroll[[#This Row],[TER Rate]],0) -> 329301 | U29: =ROUND(MIN(tblPayroll[[#This Row],[Basic Salary]]+tblPayroll[[#This Row],[Fixed Allowance]],BPJSKesCap)*R_KesEe,0) -> 105000 | V29: =ROUND((tblPayroll[[#This Row],[Basic Salary]]+tblPayroll[[#This Row],[Fixed Allowance]])*R_JHTEe,0) -> 210000 | W29: =ROUND(MIN(tblPayroll[[#This Row],[Basic Salary]]+tblPayroll[[#This Row],[Fixed Allowance]],JPCap)*R_JPEe,0) -> 105000 | X29: =tblPayroll[[#This Row],[BPJS Health (Ee)]]+tblPayroll[[#This Row],[JHT (Ee)]]+tblPayroll[[#This Row],[JP (Ee)]] -> 420000 | Y29: =tblPayroll[[#This Row],[Gross Salary]]-tblPayroll[[#This Row],[PPh 21]]-tblPayroll[[#This Row],[Employee BPJS Total]] -> 9750699 | Z29: =tblPayroll[[#This Row],[Employer BPJS Total]]+tblPayroll[[#This Row],[Employee BPJS Total]] -> 1495200 | AA29: =tblPayroll[[#This Row],[Gross Salary]]+tblPayroll[[#This Row],[Employer BPJS Total]] -> 11575200 | AB29: 1130 | AD29: 10700001 | AE29: 0.03 | AF29: 14950001 | AG29: 0.06 | AH29: 14150001 | AI29: 0.05
... B57: 4 | C57: 46137 | D57: E006 | E57: =_xlfn.XLOOKUP(tblPayroll[[#This Row],[Employee ID]],tblEmployees[Employee ID],tblEmployees[Full Name],"") -> Andi Saputra | F57: =_xlfn.XLOOKUP(tblPayroll[[#This Row],[Employee ID]],tblEmployees[Employee ID],tblEmployees[Department],"") -> G&A | G57: =_xlfn.XLOOKUP(tblPayroll[[#This Row],[Employee ID]],tblEmployees[Employee ID],tblEmployees[TER Category],"") -> A | H57: =_xlfn.XLOOKUP(tblPayroll[[#This Row],[Employee ID]],tblEmployees[Employee ID],tblEmployees[Basic Salary],"") -> 8500000 | I57: =_xlfn.XLOOKUP(tblPayroll[[#This Row],[Employee ID]],tblEmployees[Employee ID],tblEmployees[Fixed Allowance],"") -> 1000000 | J57: 0 | K57: =tblPayroll[[#This Row],[Basic Salary]]+tblPayroll[[#This Row],[Fixed Allowance]]+tblPayroll[[#This Row],[THR / Bonus]] -> 9500000 | L57: =ROUND(MIN(tblPayroll[[#This Row],[Basic Salary]]+tblPayroll[[#This Row],[Fixed Allowance]],BPJSKesCap)*R_KesEr,0) -> 380000 | M57: =ROUND((tblPayroll[[#This Row],[Basic Salary]]+tblPayroll[[#This Row],[Fixed Allowance]])*R_JKK,0) -> 22800 | N57: =ROUND((tblPayroll[[#This Row],[Basic Salary]]+tblPayroll[[#This Row],[Fixed Allowance]])*R_JKM,0) -> 28500 | O57: =ROUND((tblPayroll[[#This Row],[Basic Salary]]+tblPayroll[[#This Row],[Fixed Allowance]])*R_JHTEr,0) -> 351500 | P57: =ROUND(MIN(tblPayroll[[#This Row],[Basic Salary]]+tblPayroll[[#This Row],[Fixed Allowance]],JPCap)*R_JPEr,0) -> 190000 | Q57: =SUM(tblPayroll[[#This Row],[BPJS Health (Er)]:[JP (Er)]]) -> 972800 | R57: =tblPayroll[[#This Row],[Gross Salary]]+tblPayroll[[#This Row],[BPJS Health (Er)]]+tblPayroll[[#This Row],[JKK (Er)]]+tblPayroll[[#This Row],[JKM (Er)]] -> 9931300 | S57: =IF(tblPayroll[[#This Row],[TER Cat]]="A",_xlfn.XLOOKUP(tblPayroll[[#This Row],[PPh 21 Base]],TerA_L,TerA_R,0,-1),IF(tblPayroll[[#This Row],[TER Cat]]="B",_xlfn.XLOOKUP(tblPayroll[[#This Row],[PPh 21 Base]],TerB_L,TerB_R,0,-1),_xlfn.XLOOKUP(tblPayroll[[#This Row],[PPh 21 Base]],TerC_L,TerC_R,0,-1))) -> 0.02 | T57: =ROUND(tblPayroll[[#This Row],[PPh 21 Base]]*tblPayroll[[#This Row],[TER Rate]],0) -> 198626 | U57: =ROUND(MIN(tblPayroll[[#This Row],[Basic Salary]]+tblPayroll[[#This Row],[Fixed Allowance]],BPJSKesCap)*R_KesEe,0) -> 95000 | V57: =ROUND((tblPayroll[[#This Row],[Basic Salary]]+tblPayroll[[#This Row],[Fixed Allowance]])*R_JHTEe,0) -> 190000 | W57: =ROUND(MIN(tblPayroll[[#This Row],[Basic Salary]]+tblPayroll[[#This Row],[Fixed Allowance]],JPCap)*R_JPEe,0) -> 95000 | X57: =tblPayroll[[#This Row],[BPJS Health (Ee)]]+tblPayroll[[#This Row],[JHT (Ee)]]+tblPayroll[[#This Row],[JP (Ee)]] -> 380000 | Y57: =tblPayroll[[#This Row],[Gross Salary]]-tblPayroll[[#This Row],[PPh 21]]-tblPayroll[[#This Row],[Employee BPJS Total]] -> 8921374 | Z57: =tblPayroll[[#This Row],[Employer BPJS Total]]+tblPayroll[[#This Row],[Employee BPJS Total]] -> 1352800 | AA57: =tblPayroll[[#This Row],[Gross Salary]]+tblPayroll[[#This Row],[Employer BPJS Total]] -> 10472800 | AB57: 1130 | AD57: 454000001 | AE57: 0.3 | AF57: 1405000001 | AG57: 0.34 | AH57: 965000001 | AI57: 0.33
B58: 4 | C58: 46137 | D58: E007 | E58: =_xlfn.XLOOKUP(tblPayroll[[#This Row],[Employee ID]],tblEmployees[Employee ID],tblEmployees[Full Name],"") -> Fitri Handayani | F58: =_xlfn.XLOOKUP(tblPayroll[[#This Row],[Employee ID]],tblEmployees[Employee ID],tblEmployees[Department],"") -> G&A | G58: =_xlfn.XLOOKUP(tblPayroll[[#This Row],[Employee ID]],tblEmployees[Employee ID],tblEmployees[TER Category],"") -> A | H58: =_xlfn.XLOOKUP(tblPayroll[[#This Row],[Employee ID]],tblEmployees[Employee ID],tblEmployees[Basic Salary],"") -> 8000000 | I58: =_xlfn.XLOOKUP(tblPayroll[[#This Row],[Employee ID]],tblEmployees[Employee ID],tblEmployees[Fixed Allowance],"") -> 1000000 | J58: 0 | K58: =tblPayroll[[#This Row],[Basic Salary]]+tblPayroll[[#This Row],[Fixed Allowance]]+tblPayroll[[#This Row],[THR / Bonus]] -> 9000000 | L58: =ROUND(MIN(tblPayroll[[#This Row],[Basic Salary]]+tblPayroll[[#This Row],[Fixed Allowance]],BPJSKesCap)*R_KesEr,0) -> 360000 | M58: =ROUND((tblPayroll[[#This Row],[Basic Salary]]+tblPayroll[[#This Row],[Fixed Allowance]])*R_JKK,0) -> 21600 | N58: =ROUND((tblPayroll[[#This Row],[Basic Salary]]+tblPayroll[[#This Row],[Fixed Allowance]])*R_JKM,0) -> 27000 | O58: =ROUND((tblPayroll[[#This Row],[Basic Salary]]+tblPayroll[[#This Row],[Fixed Allowance]])*R_JHTEr,0) -> 333000 | P58: =ROUND(MIN(tblPayroll[[#This Row],[Basic Salary]]+tblPayroll[[#This Row],[Fixed Allowance]],JPCap)*R_JPEr,0) -> 180000 | Q58: =SUM(tblPayroll[[#This Row],[BPJS Health (Er)]:[JP (Er)]]) -> 921600 | R58: =tblPayroll[[#This Row],[Gross Salary]]+tblPayroll[[#This Row],[BPJS Health (Er)]]+tblPayroll[[#This Row],[JKK (Er)]]+tblPayroll[[#This Row],[JKM (Er)]] -> 9408600 | S58: =IF(tblPayroll[[#This Row],[TER Cat]]="A",_xlfn.XLOOKUP(tblPayroll[[#This Row],[PPh 21 Base]],TerA_L,TerA_R,0,-1),IF(tblPayroll[[#This Row],[TER Cat]]="B",_xlfn.XLOOKUP(tblPayroll[[#This Row],[PPh 21 Base]],TerB_L,TerB_R,0,-1),_xlfn.XLOOKUP(tblPayroll[[#This Row],[PPh 21 Base]],TerC_L,TerC_R,0,-1))) -> 0.0175 | T58: =ROUND(tblPayroll[[#This Row],[PPh 21 Base]]*tblPayroll[[#This Row],[TER Rate]],0) -> 164651 | U58: =ROUND(MIN(tblPayroll[[#This Row],[Basic Salary]]+tblPayroll[[#This Row],[Fixed Allowance]],BPJSKesCap)*R_KesEe,0) -> 90000 | V58: =ROUND((tblPayroll[[#This Row],[Basic Salary]]+tblPayroll[[#This Row],[Fixed Allowance]])*R_JHTEe,0) -> 180000 | W58: =ROUND(MIN(tblPayroll[[#This Row],[Basic Salary]]+tblPayroll[[#This Row],[Fixed Allowance]],JPCap)*R_JPEe,0) -> 90000 | X58: =tblPayroll[[#This Row],[BPJS Health (Ee)]]+tblPayroll[[#This Row],[JHT (Ee)]]+tblPayroll[[#This Row],[JP (Ee)]] -> 360000 | Y58: =tblPayroll[[#This Row],[Gross Salary]]-tblPayroll[[#This Row],[PPh 21]]-tblPayroll[[#This Row],[Employee BPJS Total]] -> 8475349 | Z58: =tblPayroll[[#This Row],[Employer BPJS Total]]+tblPayroll[[#This Row],[Employee BPJS Total]] -> 1281600 | AA58: =tblPayroll[[#This Row],[Gross Salary]]+tblPayroll[[#This Row],[Employer BPJS Total]] -> 9921600 | AB58: 1130 | AD58: 550000001 | AE58: 0.31 | AH58: 1419000001 | AI58: 0.34
B59: 4 | C59: 46137 | D59: E008 | E59: =_xlfn.XLOOKUP(tblPayroll[[#This Row],[Employee ID]],tblEmployees[Employee ID],tblEmployees[Full Name],"") -> Rizky Ramadhan | F59: =_xlfn.XLOOKUP(tblPayroll[[#This Row],[Employee ID]],tblEmployees[Employee ID],tblEmployees[Department],"") -> Selling | G59: =_xlfn.XLOOKUP(tblPayroll[[#This Row],[Employee ID]],tblEmployees[Employee ID],tblEmployees[TER Category],"") -> A | H59: =_xlfn.XLOOKUP(tblPayroll[[#This Row],[Employee ID]],tblEmployees[Employee ID],tblEmployees[Basic Salary],"") -> 9000000 | I59: =_xlfn.XLOOKUP(tblPayroll[[#This Row],[Employee ID]],tblEmployees[Employee ID],tblEmployees[Fixed Allowance],"") -> 1500000 | J59: 0 | K59: =tblPayroll[[#This Row],[Basic Salary]]+tblPayroll[[#This Row],[Fixed Allowance]]+tblPayroll[[#This Row],[THR / Bonus]] -> 10500000 | L59: =ROUND(MIN(tblPayroll[[#This Row],[Basic Salary]]+tblPayroll[[#This Row],[Fixed Allowance]],BPJSKesCap)*R_KesEr,0) -> 420000 | M59: =ROUND((tblPayroll[[#This Row],[Basic Salary]]+tblPayroll[[#This Row],[Fixed Allowance]])*R_JKK,0) -> 25200 | N59: =ROUND((tblPayroll[[#This Row],[Basic Salary]]+tblPayroll[[#This Row],[Fixed Allowance]])*R_JKM,0) -> 31500 | O59: =ROUND((tblPayroll[[#This Row],[Basic Salary]]+tblPayroll[[#This Row],[Fixed Allowance]])*R_JHTEr,0) -> 388500 | P59: =ROUND(MIN(tblPayroll[[#This Row],[Basic Salary]]+tblPayroll[[#This Row],[Fixed Allowance]],JPCap)*R_JPEr,0) -> 210000 | Q59: =SUM(tblPayroll[[#This Row],[BPJS Health (Er)]:[JP (Er)]]) -> 1075200 | R59: =tblPayroll[[#This Row],[Gross Salary]]+tblPayroll[[#This Row],[BPJS Health (Er)]]+tblPayroll[[#This Row],[JKK (Er)]]+tblPayroll[[#This Row],[JKM (Er)]] -> 10976700 | S59: =IF(tblPayroll[[#This Row],[TER Cat]]="A",_xlfn.XLOOKUP(tblPayroll[[#This Row],[PPh 21 Base]],TerA_L,TerA_R,0,-1),IF(tblPayroll[[#This Row],[TER Cat]]="B",_xlfn.XLOOKUP(tblPayroll[[#This Row],[PPh 21 Base]],TerB_L,TerB_R,0,-1),_xlfn.XLOOKUP(tblPayroll[[#This Row],[PPh 21 Base]],TerC_L,TerC_R,0,-1))) -> 0.03 | T59: =ROUND(tblPayroll[[#This Row],[PPh 21 Base]]*tblPayroll[[#This Row],[TER Rate]],0) -> 329301 | U59: =ROUND(MIN(tblPayroll[[#This Row],[Basic Salary]]+tblPayroll[[#This Row],[Fixed Allowance]],BPJSKesCap)*R_KesEe,0) -> 105000 | V59: =ROUND((tblPayroll[[#This Row],[Basic Salary]]+tblPayroll[[#This Row],[Fixed Allowance]])*R_JHTEe,0) -> 210000 | W59: =ROUND(MIN(tblPayroll[[#This Row],[Basic Salary]]+tblPayroll[[#This Row],[Fixed Allowance]],JPCap)*R_JPEe,0) -> 105000 | X59: =tblPayroll[[#This Row],[BPJS Health (Ee)]]+tblPayroll[[#This Row],[JHT (Ee)]]+tblPayroll[[#This Row],[JP (Ee)]] -> 420000 | Y59: =tblPayroll[[#This Row],[Gross Salary]]-tblPayroll[[#This Row],[PPh 21]]-tblPayroll[[#This Row],[Employee BPJS Total]] -> 9750699 | Z59: =tblPayroll[[#This Row],[Employer BPJS Total]]+tblPayroll[[#This Row],[Employee BPJS Total]] -> 1495200 | AA59: =tblPayroll[[#This Row],[Gross Salary]]+tblPayroll[[#This Row],[Employer BPJS Total]] -> 11575200 | AB59: 1130 | AD59: 695000001 | AE59: 0.32
B60: 4 | C60: 46137 | D60: E009 | E60: =_xlfn.XLOOKUP(tblPayroll[[#This Row],[Employee ID]],tblEmployees[Employee ID],tblEmployees[Full Name],"") -> Nadia Putri | F60: =_xlfn.XLOOKUP(tblPayroll[[#This Row],[Employee ID]],tblEmployees[Employee ID],tblEmployees[Department],"") -> Selling | G60: =_xlfn.XLOOKUP(tblPayroll[[#This Row],[Employee ID]],tblEmployees[Employee ID],tblEmployees[TER Category],"") -> A | H60: =_xlfn.XLOOKUP(tblPayroll[[#This Row],[Employee ID]],tblEmployees[Employee ID],tblEmployees[Basic Salary],"") -> 5800000 | I60: =_xlfn.XLOOKUP(tblPayroll[[#This Row],[Employee ID]],tblEmployees[Employee ID],tblEmployees[Fixed Allowance],"") -> 700000 | J60: 0 | K60: =tblPayroll[[#This Row],[Basic Salary]]+tblPayroll[[#This Row],[Fixed Allowance]]+tblPayroll[[#This Row],[THR / Bonus]] -> 6500000 | L60: =ROUND(MIN(tblPayroll[[#This Row],[Basic Salary]]+tblPayroll[[#This Row],[Fixed Allowance]],BPJSKesCap)*R_KesEr,0) -> 260000 | M60: =ROUND((tblPayroll[[#This Row],[Basic Salary]]+tblPayroll[[#This Row],[Fixed Allowance]])*R_JKK,0) -> 15600 | N60: =ROUND((tblPayroll[[#This Row],[Basic Salary]]+tblPayroll[[#This Row],[Fixed Allowance]])*R_JKM,0) -> 19500 | O60: =ROUND((tblPayroll[[#This Row],[Basic Salary]]+tblPayroll[[#This Row],[Fixed Allowance]])*R_JHTEr,0) -> 240500 | P60: =ROUND(MIN(tblPayroll[[#This Row],[Basic Salary]]+tblPayroll[[#This Row],[Fixed Allowance]],JPCap)*R_JPEr,0) -> 130000 | Q60: =SUM(tblPayroll[[#This Row],[BPJS Health (Er)]:[JP (Er)]]) -> 665600 | R60: =tblPayroll[[#This Row],[Gross Salary]]+tblPayroll[[#This Row],[BPJS Health (Er)]]+tblPayroll[[#This Row],[JKK (Er)]]+tblPayroll[[#This Row],[JKM (Er)]] -> 6795100 | S60: =IF(tblPayroll[[#This Row],[TER Cat]]="A",_xlfn.XLOOKUP(tblPayroll[[#This Row],[PPh 21 Base]],TerA_L,TerA_R,0,-1),IF(tblPayroll[[#This Row],[TER Cat]]="B",_xlfn.XLOOKUP(tblPayroll[[#This Row],[PPh 21 Base]],TerB_L,TerB_R,0,-1),_xlfn.XLOOKUP(tblPayroll[[#This Row],[PPh 21 Base]],TerC_L,TerC_R,0,-1))) -> 0.0125 | T60: =ROUND(tblPayroll[[#This Row],[PPh 21 Base]]*tblPayroll[[#This Row],[TER Rate]],0) -> 84939 | U60: =ROUND(MIN(tblPayroll[[#This Row],[Basic Salary]]+tblPayroll[[#This Row],[Fixed Allowance]],BPJSKesCap)*R_KesEe,0) -> 65000 | V60: =ROUND((tblPayroll[[#This Row],[Basic Salary]]+tblPayroll[[#This Row],[Fixed Allowance]])*R_JHTEe,0) -> 130000 | W60: =ROUND(MIN(tblPayroll[[#This Row],[Basic Salary]]+tblPayroll[[#This Row],[Fixed Allowance]],JPCap)*R_JPEe,0) -> 65000 | X60: =tblPayroll[[#This Row],[BPJS Health (Ee)]]+tblPayroll[[#This Row],[JHT (Ee)]]+tblPayroll[[#This Row],[JP (Ee)]] -> 260000 | Y60: =tblPayroll[[#This Row],[Gross Salary]]-tblPayroll[[#This Row],[PPh 21]]-tblPayroll[[#This Row],[Employee BPJS Total]] -> 6155061 | Z60: =tblPayroll[[#This Row],[Employer BPJS Total]]+tblPayroll[[#This Row],[Employee BPJS Total]] -> 925600 | AA60: =tblPayroll[[#This Row],[Gross Salary]]+tblPayroll[[#This Row],[Employer BPJS Total]] -> 7165600 | AB60: 1130 | AD60: 910000001 | AE60: 0.33
B61: 4 | C61: 46137 | D61: E010 | E61: =_xlfn.XLOOKUP(tblPayroll[[#This Row],[Employee ID]],tblEmployees[Employee ID],tblEmployees[Full Name],"") -> Dimas Pratama | F61: =_xlfn.XLOOKUP(tblPayroll[[#This Row],[Employee ID]],tblEmployees[Employee ID],tblEmployees[Department],"") -> Selling | G61: =_xlfn.XLOOKUP(tblPayroll[[#This Row],[Employee ID]],tblEmployees[Employee ID],tblEmployees[TER Category],"") -> A | H61: =_xlfn.XLOOKUP(tblPayroll[[#This Row],[Employee ID]],tblEmployees[Employee ID],tblEmployees[Basic Salary],"") -> 5800000 | I61: =_xlfn.XLOOKUP(tblPayroll[[#This Row],[Employee ID]],tblEmployees[Employee ID],tblEmployees[Fixed Allowance],"") -> 700000 | J61: 0 | K61: =tblPayroll[[#This Row],[Basic Salary]]+tblPayroll[[#This Row],[Fixed Allowance]]+tblPayroll[[#This Row],[THR / Bonus]] -> 6500000 | L61: =ROUND(MIN(tblPayroll[[#This Row],[Basic Salary]]+tblPayroll[[#This Row],[Fixed Allowance]],BPJSKesCap)*R_KesEr,0) -> 260000 | M61: =ROUND((tblPayroll[[#This Row],[Basic Salary]]+tblPayroll[[#This Row],[Fixed Allowance]])*R_JKK,0) -> 15600 | N61: =ROUND((tblPayroll[[#This Row],[Basic Salary]]+tblPayroll[[#This Row],[Fixed Allowance]])*R_JKM,0) -> 19500 | O61: =ROUND((tblPayroll[[#This Row],[Basic Salary]]+tblPayroll[[#This Row],[Fixed Allowance]])*R_JHTEr,0) -> 240500 | P61: =ROUND(MIN(tblPayroll[[#This Row],[Basic Salary]]+tblPayroll[[#This Row],[Fixed Allowance]],JPCap)*R_JPEr,0) -> 130000 | Q61: =SUM(tblPayroll[[#This Row],[BPJS Health (Er)]:[JP (Er)]]) -> 665600 | R61: =tblPayroll[[#This Row],[Gross Salary]]+tblPayroll[[#This Row],[BPJS Health (Er)]]+tblPayroll[[#This Row],[JKK (Er)]]+tblPayroll[[#This Row],[JKM (Er)]] -> 6795100 | S61: =IF(tblPayroll[[#This Row],[TER Cat]]="A",_xlfn.XLOOKUP(tblPayroll[[#This Row],[PPh 21 Base]],TerA_L,TerA_R,0,-1),IF(tblPayroll[[#This Row],[TER Cat]]="B",_xlfn.XLOOKUP(tblPayroll[[#This Row],[PPh 21 Base]],TerB_L,TerB_R,0,-1),_xlfn.XLOOKUP(tblPayroll[[#This Row],[PPh 21 Base]],TerC_L,TerC_R,0,-1))) -> 0.0125 | T61: =ROUND(tblPayroll[[#This Row],[PPh 21 Base]]*tblPayroll[[#This Row],[TER Rate]],0) -> 84939 | U61: =ROUND(MIN(tblPayroll[[#This Row],[Basic Salary]]+tblPayroll[[#This Row],[Fixed Allowance]],BPJSKesCap)*R_KesEe,0) -> 65000 | V61: =ROUND((tblPayroll[[#This Row],[Basic Salary]]+tblPayroll[[#This Row],[Fixed Allowance]])*R_JHTEe,0) -> 130000 | W61: =ROUND(MIN(tblPayroll[[#This Row],[Basic Salary]]+tblPayroll[[#This Row],[Fixed Allowance]],JPCap)*R_JPEe,0) -> 65000 | X61: =tblPayroll[[#This Row],[BPJS Health (Ee)]]+tblPayroll[[#This Row],[JHT (Ee)]]+tblPayroll[[#This Row],[JP (Ee)]] -> 260000 | Y61: =tblPayroll[[#This Row],[Gross Salary]]-tblPayroll[[#This Row],[PPh 21]]-tblPayroll[[#This Row],[Employee BPJS Total]] -> 6155061 | Z61: =tblPayroll[[#This Row],[Employer BPJS Total]]+tblPayroll[[#This Row],[Employee BPJS Total]] -> 925600 | AA61: =tblPayroll[[#This Row],[Gross Salary]]+tblPayroll[[#This Row],[Employer BPJS Total]] -> 7165600 | AB61: 1130 | AD61: 1400000001 | AE61: 0.34
B62: 4 | C62: 46137 | D62: E011 | E62: =_xlfn.XLOOKUP(tblPayroll[[#This Row],[Employee ID]],tblEmployees[Employee ID],tblEmployees[Full Name],"") -> Yusuf Hidayat | F62: =_xlfn.XLOOKUP(tblPayroll[[#This Row],[Employee ID]],tblEmployees[Employee ID],tblEmployees[Department],"") -> Selling | G62: =_xlfn.XLOOKUP(tblPayroll[[#This Row],[Employee ID]],tblEmployees[Employee ID],tblEmployees[TER Category],"") -> B | H62: =_xlfn.XLOOKUP(tblPayroll[[#This Row],[Employee ID]],tblEmployees[Employee ID],tblEmployees[Basic Salary],"") -> 7500000 | I62: =_xlfn.XLOOKUP(tblPayroll[[#This Row],[Employee ID]],tblEmployees[Employee ID],tblEmployees[Fixed Allowance],"") -> 1000000 | J62: 0 | K62: =tblPayroll[[#This Row],[Basic Salary]]+tblPayroll[[#This Row],[Fixed Allowance]]+tblPayroll[[#This Row],[THR / Bonus]] -> 8500000 | L62: =ROUND(MIN(tblPayroll[[#This Row],[Basic Salary]]+tblPayroll[[#This Row],[Fixed Allowance]],BPJSKesCap)*R_KesEr,0) -> 340000 | M62: =ROUND((tblPayroll[[#This Row],[Basic Salary]]+tblPayroll[[#This Row],[Fixed Allowance]])*R_JKK,0) -> 20400 | N62: =ROUND((tblPayroll[[#This Row],[Basic Salary]]+tblPayroll[[#This Row],[Fixed Allowance]])*R_JKM,0) -> 25500 | O62: =ROUND((tblPayroll[[#This Row],[Basic Salary]]+tblPayroll[[#This Row],[Fixed Allowance]])*R_JHTEr,0) -> 314500 | P62: =ROUND(MIN(tblPayroll[[#This Row],[Basic Salary]]+tblPayroll[[#This Row],[Fixed Allowance]],JPCap)*R_JPEr,0) -> 170000 | Q62: =SUM(tblPayroll[[#This Row],[BPJS Health (Er)]:[JP (Er)]]) -> 870400 | R62: =tblPayroll[[#This Row],[Gross Salary]]+tblPayroll[[#This Row],[BPJS Health (Er)]]+tblPayroll[[#This Row],[JKK (Er)]]+tblPayroll[[#This Row],[JKM (Er)]] -> 8885900 | S62: =IF(tblPayroll[[#This Row],[TER Cat]]="A",_xlfn.XLOOKUP(tblPayroll[[#This Row],[PPh 21 Base]],TerA_L,TerA_R,0,-1),IF(tblPayroll[[#This Row],[TER Cat]]="B",_xlfn.XLOOKUP(tblPayroll[[#This Row],[PPh 21 Base]],TerB_L,TerB_R,0,-1),_xlfn.XLOOKUP(tblPayroll[[#This Row],[PPh 21 Base]],TerC_L,TerC_R,0,-1))) -> 0.01 | T62: =ROUND(tblPayroll[[#This Row],[PPh 21 Base]]*tblPayroll[[#This Row],[TER Rate]],0) -> 88859 | U62: =ROUND(MIN(tblPayroll[[#This Row],[Basic Salary]]+tblPayroll[[#This Row],[Fixed Allowance]],BPJSKesCap)*R_KesEe,0) -> 85000 | V62: =ROUND((tblPayroll[[#This Row],[Basic Salary]]+tblPayroll[[#This Row],[Fixed Allowance]])*R_JHTEe,0) -> 170000 | W62: =ROUND(MIN(tblPayroll[[#This Row],[Basic Salary]]+tblPayroll[[#This Row],[Fixed Allowance]],JPCap)*R_JPEe,0) -> 85000 | X62: =tblPayroll[[#This Row],[BPJS Health (Ee)]]+tblPayroll[[#This Row],[JHT (Ee)]]+tblPayroll[[#This Row],[JP (Ee)]] -> 340000 | Y62: =tblPayroll[[#This Row],[Gross Salary]]-tblPayroll[[#This Row],[PPh 21]]-tblPayroll[[#This Row],[Employee BPJS Total]] -> 8071141 | Z62: =tblPayroll[[#This Row],[Employer BPJS Total]]+tblPayroll[[#This Row],[Employee BPJS Total]] -> 1210400 | AA62: =tblPayroll[[#This Row],[Gross Salary]]+tblPayroll[[#This Row],[Employer BPJS Total]] -> 9370400 | AB62: 1130
B63: 4 | C63: 46137 | D63: E012 | E63: =_xlfn.XLOOKUP(tblPayroll[[#This Row],[Employee ID]],tblEmployees[Employee ID],tblEmployees[Full Name],"") -> Lestari Wulandari | F63: =_xlfn.XLOOKUP(tblPayroll[[#This Row],[Employee ID]],tblEmployees[Employee ID],tblEmployees[Department],"") -> Selling | G63: =_xlfn.XLOOKUP(tblPayroll[[#This Row],[Employee ID]],tblEmployees[Employee ID],tblEmployees[TER Category],"") -> A | H63: =_xlfn.XLOOKUP(tblPayroll[[#This Row],[Employee ID]],tblEmployees[Employee ID],tblEmployees[Basic Salary],"") -> 5600000 | I63: =_xlfn.XLOOKUP(tblPayroll[[#This Row],[Employee ID]],tblEmployees[Employee ID],tblEmployees[Fixed Allowance],"") -> 600000 | J63: 0 | K63: =tblPayroll[[#This Row],[Basic Salary]]+tblPayroll[[#This Row],[Fixed Allowance]]+tblPayroll[[#This Row],[THR / Bonus]] -> 6200000 | L63: =ROUND(MIN(tblPayroll[[#This Row],[Basic Salary]]+tblPayroll[[#This Row],[Fixed Allowance]],BPJSKesCap)*R_KesEr,0) -> 248000 | M63: =ROUND((tblPayroll[[#This Row],[Basic Salary]]+tblPayroll[[#This Row],[Fixed Allowance]])*R_JKK,0) -> 14880 | N63: =ROUND((tblPayroll[[#This Row],[Basic Salary]]+tblPayroll[[#This Row],[Fixed Allowance]])*R_JKM,0) -> 18600 | O63: =ROUND((tblPayroll[[#This Row],[Basic Salary]]+tblPayroll[[#This Row],[Fixed Allowance]])*R_JHTEr,0) -> 229400 | P63: =ROUND(MIN(tblPayroll[[#This Row],[Basic Salary]]+tblPayroll[[#This Row],[Fixed Allowance]],JPCap)*R_JPEr,0) -> 124000 | Q63: =SUM(tblPayroll[[#This Row],[BPJS Health (Er)]:[JP (Er)]]) -> 634880 | R63: =tblPayroll[[#This Row],[Gross Salary]]+tblPayroll[[#This Row],[BPJS Health (Er)]]+tblPayroll[[#This Row],[JKK (Er)]]+tblPayroll[[#This Row],[JKM (Er)]] -> 6481480 | S63: =IF(tblPayroll[[#This Row],[TER Cat]]="A",_xlfn.XLOOKUP(tblPayroll[[#This Row],[PPh 21 Base]],TerA_L,TerA_R,0,-1),IF(tblPayroll[[#This Row],[TER Cat]]="B",_xlfn.XLOOKUP(tblPayroll[[#This Row],[PPh 21 Base]],TerB_L,TerB_R,0,-1),_xlfn.XLOOKUP(tblPayroll[[#This Row],[PPh 21 Base]],TerC_L,TerC_R,0,-1))) -> 0.01 | T63: =ROUND(tblPayroll[[#This Row],[PPh 21 Base]]*tblPayroll[[#This Row],[TER Rate]],0) -> 64815 | U63: =ROUND(MIN(tblPayroll[[#This Row],[Basic Salary]]+tblPayroll[[#This Row],[Fixed Allowance]],BPJSKesCap)*R_KesEe,0) -> 62000 | V63: =ROUND((tblPayroll[[#This Row],[Basic Salary]]+tblPayroll[[#This Row],[Fixed Allowance]])*R_JHTEe,0) -> 124000 | W63: =ROUND(MIN(tblPayroll[[#This Row],[Basic Salary]]+tblPayroll[[#This Row],[Fixed Allowance]],JPCap)*R_JPEe,0) -> 62000 | X63: =tblPayroll[[#This Row],[BPJS Health (Ee)]]+tblPayroll[[#This Row],[JHT (Ee)]]+tblPayroll[[#This Row],[JP (Ee)]] -> 248000 | Y63: =tblPayroll[[#This Row],[Gross Salary]]-tblPayroll[[#This Row],[PPh 21]]-tblPayroll[[#This Row],[Employee BPJS Total]] -> 5887185 | Z63: =tblPayroll[[#This Row],[Employer BPJS Total]]+tblPayroll[[#This Row],[Employee BPJS Total]] -> 882880 | AA63: =tblPayroll[[#This Row],[Gross Salary]]+tblPayroll[[#This Row],[Employer BPJS Total]] -> 6834880 | AB63: 1130
B64: 4 | C64: 46137 | D64: E013 | E64: =_xlfn.XLOOKUP(tblPayroll[[#This Row],[Employee ID]],tblEmployees[Employee ID],tblEmployees[Full Name],"") -> Bayu Nugroho | F64: =_xlfn.XLOOKUP(tblPayroll[[#This Row],[Employee ID]],tblEmployees[Employee ID],tblEmployees[Department],"") -> Selling | G64: =_xlfn.XLOOKUP(tblPayroll[[#This Row],[Employee ID]],tblEmployees[Employee ID],tblEmployees[TER Category],"") -> B | H64: =_xlfn.XLOOKUP(tblPayroll[[#This Row],[Employee ID]],tblEmployees[Employee ID],tblEmployees[Basic Salary],"") -> 5600000 | I64: =_xlfn.XLOOKUP(tblPayroll[[#This Row],[Employee ID]],tblEmployees[Employee ID],tblEmployees[Fixed Allowance],"") -> 600000 | J64: 0 | K64: =tblPayroll[[#This Row],[Basic Salary]]+tblPayroll[[#This Row],[Fixed Allowance]]+tblPayroll[[#This Row],[THR / Bonus]] -> 6200000 | L64: =ROUND(MIN(tblPayroll[[#This Row],[Basic Salary]]+tblPayroll[[#This Row],[Fixed Allowance]],BPJSKesCap)*R_KesEr,0) -> 248000 | M64: =ROUND((tblPayroll[[#This Row],[Basic Salary]]+tblPayroll[[#This Row],[Fixed Allowance]])*R_JKK,0) -> 14880 | N64: =ROUND((tblPayroll[[#This Row],[Basic Salary]]+tblPayroll[[#This Row],[Fixed Allowance]])*R_JKM,0) -> 18600 | O64: =ROUND((tblPayroll[[#This Row],[Basic Salary]]+tblPayroll[[#This Row],[Fixed Allowance]])*R_JHTEr,0) -> 229400 | P64: =ROUND(MIN(tblPayroll[[#This Row],[Basic Salary]]+tblPayroll[[#This Row],[Fixed Allowance]],JPCap)*R_JPEr,0) -> 124000 | Q64: =SUM(tblPayroll[[#This Row],[BPJS Health (Er)]:[JP (Er)]]) -> 634880 | R64: =tblPayroll[[#This Row],[Gross Salary]]+tblPayroll[[#This Row],[BPJS Health (Er)]]+tblPayroll[[#This Row],[JKK (Er)]]+tblPayroll[[#This Row],[JKM (Er)]] -> 6481480 | S64: =IF(tblPayroll[[#This Row],[TER Cat]]="A",_xlfn.XLOOKUP(tblPayroll[[#This Row],[PPh 21 Base]],TerA_L,TerA_R,0,-1),IF(tblPayroll[[#This Row],[TER Cat]]="B",_xlfn.XLOOKUP(tblPayroll[[#This Row],[PPh 21 Base]],TerB_L,TerB_R,0,-1),_xlfn.XLOOKUP(tblPayroll[[#This Row],[PPh 21 Base]],TerC_L,TerC_R,0,-1))) -> 0.0025 | T64: =ROUND(tblPayroll[[#This Row],[PPh 21 Base]]*tblPayroll[[#This Row],[TER Rate]],0) -> 16204 | U64: =ROUND(MIN(tblPayroll[[#This Row],[Basic Salary]]+tblPayroll[[#This Row],[Fixed Allowance]],BPJSKesCap)*R_KesEe,0) -> 62000 | V64: =ROUND((tblPayroll[[#This Row],[Basic Salary]]+tblPayroll[[#This Row],[Fixed Allowance]])*R_JHTEe,0) -> 124000 | W64: =ROUND(MIN(tblPayroll[[#This Row],[Basic Salary]]+tblPayroll[[#This Row],[Fixed Allowance]],JPCap)*R_JPEe,0) -> 62000 | X64: =tblPayroll[[#This Row],[BPJS Health (Ee)]]+tblPayroll[[#This Row],[JHT (Ee)]]+tblPayroll[[#This Row],[JP (Ee)]] -> 248000 | Y64: =tblPayroll[[#This Row],[Gross Salary]]-tblPayroll[[#This Row],[PPh 21]]-tblPayroll[[#This Row],[Employee BPJS Total]] -> 5935796 | Z64: =tblPayroll[[#This Row],[Employer BPJS Total]]+tblPayroll[[#This Row],[Employee BPJS Total]] -> 882880 | AA64: =tblPayroll[[#This Row],[Gross Salary]]+tblPayroll[[#This Row],[Employer BPJS Total]] -> 6834880 | AB64: 1130
B65: 4 | C65: 46137 | D65: E014 | E65: =_xlfn.XLOOKUP(tblPayroll[[#This Row],[Employee ID]],tblEmployees[Employee ID],tblEmployees[Full Name],"") -> Maya Sari | F65: =_xlfn.XLOOKUP(tblPayroll[[#This Row],[Employee ID]],tblEmployees[Employee ID],tblEmployees[Department],"") -> Selling | G65: =_xlfn.XLOOKUP(tblPayroll[[#This Row],[Employee ID]],tblEmployees[Employee ID],tblEmployees[TER Category],"") -> A | H65: =_xlfn.XLOOKUP(tblPayroll[[#This Row],[Employee ID]],tblEmployees[Employee ID],tblEmployees[Basic Salary],"") -> 5700000 | I65: =_xlfn.XLOOKUP(tblPayroll[[#This Row],[Employee ID]],tblEmployees[Employee ID],tblEmployees[Fixed Allowance],"") -> 600000 | J65: 0 | K65: =tblPayroll[[#This Row],[Basic Salary]]+tblPayroll[[#This Row],[Fixed Allowance]]+tblPayroll[[#This Row],[THR / Bonus]] -> 6300000 | L65: =ROUND(MIN(tblPayroll[[#This Row],[Basic Salary]]+tblPayroll[[#This Row],[Fixed Allowance]],BPJSKesCap)*R_KesEr,0) -> 252000 | M65: =ROUND((tblPayroll[[#This Row],[Basic Salary]]+tblPayroll[[#This Row],[Fixed Allowance]])*R_JKK,0) -> 15120 | N65: =ROUND((tblPayroll[[#This Row],[Basic Salary]]+tblPayroll[[#This Row],[Fixed Allowance]])*R_JKM,0) -> 18900 | O65: =ROUND((tblPayroll[[#This Row],[Basic Salary]]+tblPayroll[[#This Row],[Fixed Allowance]])*R_JHTEr,0) -> 233100 | P65: =ROUND(MIN(tblPayroll[[#This Row],[Basic Salary]]+tblPayroll[[#This Row],[Fixed Allowance]],JPCap)*R_JPEr,0) -> 126000 | Q65: =SUM(tblPayroll[[#This Row],[BPJS Health (Er)]:[JP (Er)]]) -> 645120 | R65: =tblPayroll[[#This Row],[Gross Salary]]+tblPayroll[[#This Row],[BPJS Health (Er)]]+tblPayroll[[#This Row],[JKK (Er)]]+tblPayroll[[#This Row],[JKM (Er)]] -> 6586020 | S65: =IF(tblPayroll[[#This Row],[TER Cat]]="A",_xlfn.XLOOKUP(tblPayroll[[#This Row],[PPh 21 Base]],TerA_L,TerA_R,0,-1),IF(tblPayroll[[#This Row],[TER Cat]]="B",_xlfn.XLOOKUP(tblPayroll[[#This Row],[PPh 21 Base]],TerB_L,TerB_R,0,-1),_xlfn.XLOOKUP(tblPayroll[[#This Row],[PPh 21 Base]],TerC_L,TerC_R,0,-1))) -> 0.01 | T65: =ROUND(tblPayroll[[#This Row],[PPh 21 Base]]*tblPayroll[[#This Row],[TER Rate]],0) -> 65860 | U65: =ROUND(MIN(tblPayroll[[#This Row],[Basic Salary]]+tblPayroll[[#This Row],[Fixed Allowance]],BPJSKesCap)*R_KesEe,0) -> 63000 | V65: =ROUND((tblPayroll[[#This Row],[Basic Salary]]+tblPayroll[[#This Row],[Fixed Allowance]])*R_JHTEe,0) -> 126000 | W65: =ROUND(MIN(tblPayroll[[#This Row],[Basic Salary]]+tblPayroll[[#This Row],[Fixed Allowance]],JPCap)*R_JPEe,0) -> 63000 | X65: =tblPayroll[[#This Row],[BPJS Health (Ee)]]+tblPayroll[[#This Row],[JHT (Ee)]]+tblPayroll[[#This Row],[JP (Ee)]] -> 252000 | Y65: =tblPayroll[[#This Row],[Gross Salary]]-tblPayroll[[#This Row],[PPh 21]]-tblPayroll[[#This Row],[Employee BPJS Total]] -> 5982140 | Z65: =tblPayroll[[#This Row],[Employer BPJS Total]]+tblPayroll[[#This Row],[Employee BPJS Total]] -> 897120 | AA65: =tblPayroll[[#This Row],[Gross Salary]]+tblPayroll[[#This Row],[Employer BPJS Total]] -> 6945120 | AB65: 1130
B66: 4 | C66: 46137 | D66: E015 | E66: =_xlfn.XLOOKUP(tblPayroll[[#This Row],[Employee ID]],tblEmployees[Employee ID],tblEmployees[Full Name],"") -> Hendra Wijaya | F66: =_xlfn.XLOOKUP(tblPayroll[[#This Row],[Employee ID]],tblEmployees[Employee ID],tblEmployees[Department],"") -> G&A | G66: =_xlfn.XLOOKUP(tblPayroll[[#This Row],[Employee ID]],tblEmployees[Employee ID],tblEmployees[TER Category],"") -> A | H66: =_xlfn.XLOOKUP(tblPayroll[[#This Row],[Employee ID]],tblEmployees[Employee ID],tblEmployees[Basic Salary],"") -> 9500000 | I66: =_xlfn.XLOOKUP(tblPayroll[[#This Row],[Employee ID]],tblEmployees[Employee ID],tblEmployees[Fixed Allowance],"") -> 1000000 | J66: 0 | K66: =tblPayroll[[#This Row],[Basic Salary]]+tblPayroll[[#This Row],[Fixed Allowance]]+tblPayroll[[#This Row],[THR / Bonus]] -> 10500000 | L66: =ROUND(MIN(tblPayroll[[#This Row],[Basic Salary]]+tblPayroll[[#This Row],[Fixed Allowance]],BPJSKesCap)*R_KesEr,0) -> 420000 | M66: =ROUND((tblPayroll[[#This Row],[Basic Salary]]+tblPayroll[[#This Row],[Fixed Allowance]])*R_JKK,0) -> 25200 | N66: =ROUND((tblPayroll[[#This Row],[Basic Salary]]+tblPayroll[[#This Row],[Fixed Allowance]])*R_JKM,0) -> 31500 | O66: =ROUND((tblPayroll[[#This Row],[Basic Salary]]+tblPayroll[[#This Row],[Fixed Allowance]])*R_JHTEr,0) -> 388500 | P66: =ROUND(MIN(tblPayroll[[#This Row],[Basic Salary]]+tblPayroll[[#This Row],[Fixed Allowance]],JPCap)*R_JPEr,0) -> 210000 | Q66: =SUM(tblPayroll[[#This Row],[BPJS Health (Er)]:[JP (Er)]]) -> 1075200 | R66: =tblPayroll[[#This Row],[Gross Salary]]+tblPayroll[[#This Row],[BPJS Health (Er)]]+tblPayroll[[#This Row],[JKK (Er)]]+tblPayroll[[#This Row],[JKM (Er)]] -> 10976700 | S66: =IF(tblPayroll[[#This Row],[TER Cat]]="A",_xlfn.XLOOKUP(tblPayroll[[#This Row],[PPh 21 Base]],TerA_L,TerA_R,0,-1),IF(tblPayroll[[#This Row],[TER Cat]]="B",_xlfn.XLOOKUP(tblPayroll[[#This Row],[PPh 21 Base]],TerB_L,TerB_R,0,-1),_xlfn.XLOOKUP(tblPayroll[[#This Row],[PPh 21 Base]],TerC_L,TerC_R,0,-1))) -> 0.03 | T66: =ROUND(tblPayroll[[#This Row],[PPh 21 Base]]*tblPayroll[[#This Row],[TER Rate]],0) -> 329301 | U66: =ROUND(MIN(tblPayroll[[#This Row],[Basic Salary]]+tblPayroll[[#This Row],[Fixed Allowance]],BPJSKesCap)*R_KesEe,0) -> 105000 | V66: =ROUND((tblPayroll[[#This Row],[Basic Salary]]+tblPayroll[[#This Row],[Fixed Allowance]])*R_JHTEe,0) -> 210000 | W66: =ROUND(MIN(tblPayroll[[#This Row],[Basic Salary]]+tblPayroll[[#This Row],[Fixed Allowance]],JPCap)*R_JPEe,0) -> 105000 | X66: =tblPayroll[[#This Row],[BPJS Health (Ee)]]+tblPayroll[[#This Row],[JHT (Ee)]]+tblPayroll[[#This Row],[JP (Ee)]] -> 420000 | Y66: =tblPayroll[[#This Row],[Gross Salary]]-tblPayroll[[#This Row],[PPh 21]]-tblPayroll[[#This Row],[Employee BPJS Total]] -> 9750699 | Z66: =tblPayroll[[#This Row],[Employer BPJS Total]]+tblPayroll[[#This Row],[Employee BPJS Total]] -> 1495200 | AA66: =tblPayroll[[#This Row],[Gross Salary]]+tblPayroll[[#This Row],[Employer BPJS Total]] -> 11575200 | AB66: 1130
